slave_fsm_rtl/slave_sda_gen_5.v
module slave_sda_generate #(
    parameter ADDR_LEN = 7,
    parameter ADDR_COUNTER_LEN = 3,
    parameter DATA_LEN = 8,
    parameter DATA_COUNTER_LEN = 3
)(
    //input clk;
    input scl,
    inout sda,
    input[DATA_LEN-1:0] data_received,
    output[DATA_LEN-1:0] data_sent

);

  reg [3:0] current_state = Idle;
  reg [3:0] next_state = Idle;
  reg R_W;
  reg sda_reg = 1'b1;
  reg start_signal = 1'b0;
  reg stop_signal = 1'b0;
  reg sda_write = 1'b0;
  reg reset_address_counter;
  reg [ADDR_COUNTER_LEN:0] address_counter;
  wire comp_bit;
  reg reset_rdata_counter;
  reg [DATA_COUNTER_LEN-1:0] rdata_counter;
  reg reset_wdata_counter;
  reg [DATA_COUNTER_LEN-1:0] wdata_counter;
  reg [DATA_LEN-1:0] received_data = 8'b00000000;
  reg [ADDR_LEN-1:0] slave_address = 7'b1011011;
  reg [ADDR_LEN-1:0] received_address = 7'b0000000;

  parameter Idle = 4'b0000;
  parameter Receive_address = 4'b0001;
  parameter delay_post_ack0 = 4'b0010;
  parameter delay_post_ack1 = 4'b0011;
  parameter Send_data = 4'b0100;
  parameter Check_ACK_NACK = 4'b0101;
  parameter Receive_data = 4'b0110;
  parameter GiveACK = 4'b0111;
  parameter Stop = 4'b1000;
  //parameter GiveACK = ;

  assign comp_bit = (received_address == slave_address);
  assign data_sent = received_data;
  assign sda = sda_write ? sda_reg : 1'bz;

  always @(current_state,sda,sda_reg,scl) begin
    case (current_state)
      Receive_address:
      begin
        if(scl) begin
          //address_counter = address_counter - 1;
          sda_reg = sda;
          if(address_counter == 1) R_W = sda_reg;
          else received_address = (received_address << 1) + sda_reg;
        end
        else if(~scl && address_counter == 0) begin
          if (comp_bit) begin
            sda_write = 1'b1;
            sda_reg = 1'b0;
            next_state = delay_post_ack0;
          end
          else begin
            sda_write = 1'b1;
            sda_reg = 1'b1;
            next_state = delay_post_ack1;
          end
        end

        else next_state = Receive_address;
      end
      delay_post_ack0:
      begin
        if (R_W == 1'b1) begin
          sda_write = 1'b1;
          next_state = Send_data;
          if (~scl) begin
          sda_reg = data_received[DATA_LEN-1];
          end
        end
        else begin
          if (~scl) sda_write = 1'b0;
          next_state = Receive_data;
        end
        //break;
      end
      delay_post_ack1:
      begin
        if (~scl) sda_write = 1'b0;
        next_state = Stop;
        //break;
      end
      Send_data:
      begin
        //rdata_counter -= 1;
        if (~scl) begin
          sda_write = 1'b1;
          if (rdata_counter == 0) begin
            sda_write = 1'b0;
            next_state = Check_ACK_NACK;
          end
          else begin
            sda_reg = data_received[rdata_counter];
            next_state = Send_data;
          end
        end
        
        //break;
      end
      Check_ACK_NACK:
      begin
        sda_write = 1'b0;
        next_state = Stop;
        //break;
      end
      Receive_data:
      begin
        
        if (wdata_counter == 0) begin
          next_state = GiveACK;
          if (~scl) begin 
            sda_write = 1'b1;
            sda_reg = 1'b0;
          end
        end
        else begin
          if (scl) begin
            sda_reg = sda;
            received_data = (received_data << 1) + sda_reg;
          end
          next_state = Receive_data;
        end
        
        //break;
      end
      GiveACK:
      begin
        if (~scl) sda_write = 1'b0;
        next_state = Stop;
      end
      Stop: 
      begin
        sda_write = 1'b0;
        //break;
      end
    endcase
  end

  always @(posedge scl) begin
    case (current_state)
      Idle:
      begin
        stop_signal <= 1'b0;
      end
      Receive_address:
      begin
        start_signal <= 1'b0;
        address_counter <= address_counter - 1;

      end
      delay_post_ack0:
      begin
        if (R_W == 1'b1) begin
          reset_rdata_counter <= 1'b1;
        end
        else begin
          reset_wdata_counter <= 1'b1;
        end
        //break;
      end
      /*delay_post_ack1:
      begin
        //sda <= sda_reg;
        sda_reg = 1'b1;
        reset_address_counter = 1'b1;
        next_state = Receive_address;
        //break;
      end*/
      Send_data:
      begin
        rdata_counter <= rdata_counter - 1;
        //sda_reg <= data_received[rdata_counter-1];
      end
      Check_ACK_NACK:
      begin
        //
      end
      Receive_data:
      begin
        wdata_counter <= wdata_counter - 1;
        
        //break;
      end
      GiveACK:
      begin
        next_state = Stop;
      end
    endcase
  end

always @(start_signal) begin
  if(start_signal) begin
    next_state = Receive_address;
  end
end

always @(posedge scl) begin
  current_state <= next_state;
end

always @(negedge sda) begin
  if (scl) begin
    reset_address_counter <= 1'b1;
    start_signal <= 1'b1;
  end
  
end

always @(posedge sda) begin
  if (scl) stop_signal <= 1'b1;
end

always @(stop_signal) begin
  if (stop_signal) begin
    current_state <= Idle;
  end
end

always @(address_counter, reset_address_counter) begin
  if (reset_address_counter || address_counter < 0 || address_counter > ADDR_LEN) begin
    address_counter = ADDR_LEN;
    reset_address_counter = 0;
  end
end
always @(rdata_counter, reset_rdata_counter) begin
  if (reset_rdata_counter || rdata_counter < 0 || rdata_counter > DATA_LEN-1) begin
    rdata_counter = DATA_LEN-1;
    reset_rdata_counter = 0;
  end
end

always @(wdata_counter, reset_wdata_counter) begin
  if (reset_wdata_counter || wdata_counter < 0 || wdata_counter > DATA_LEN-1) begin
    wdata_counter = DATA_LEN-1;
    reset_wdata_counter = 0;
  end
end

endmodule

master_fsm_rtl/slave_tb2.v
module slave_tb2;

    wire sda_pin;
    reg sda;
    reg sda_op;
    reg scl;
    //reg clk;
    reg [7:0] data_received;
    wire [7:0] data_sent;
    reg write_inout;

    //slave_sda_generate S1 (clk,scl,sda_pin,data_received,data_sent);
    slave_sda_generate S1 (scl,sda_pin,data_received,data_sent);

    assign sda_pin = write_inout ? sda : 1'bz;

    /*initial clk = 1'b0;
    always #2.5 clk <= ~clk;*/

    initial begin
        $dumpfile("slave2.vcd"); 
        $dumpvars(0, slave_tb2);
        $monitor($time," scl = %b sda = %b address_counter = %d",scl,sda, S1.address_counter);
        write_inout = 1; sda = 1; scl = 1;
        #5 sda = 1; scl = 1;
        #5 sda = 0;
        #5 scl = 0;
        #5 sda = 1;
        #5 scl = 1;
        #5 scl = 0; sda = 0;
        #5 scl = 1;
        #5 scl = 0; sda = 1;
        #5 scl = 1;
        #5 scl = 0; sda = 1;
        #5 scl = 1;
        #5 scl = 0; sda = 0;
        #5 scl = 1;
        #5 scl = 0; sda = 1;
        #5 scl = 1;
        #5 scl = 0; sda = 1;
        #5 scl = 1;
        #5 scl = 0; sda = 0;
        #5 scl = 1;
        #5 write_inout = 0; scl = 0;
        #5 scl = 1;
        #5 scl = 0; write_inout = 1; sda = 1;
        #5 scl = 1;
        #5 scl = 0; sda = 1;
        #5 scl = 1;
        #5 scl = 0; sda = 0;
        #5 scl = 1;
        #5 scl = 0; sda = 0;
        #5 scl = 1;
        #5 scl = 0; sda = 1;
        #5 scl = 1;
        #5 scl = 0; sda = 1;
        #5 scl = 1;
        #5 scl = 0; sda = 0;
        #5 scl = 1;
        #5 scl = 0; sda = 0;
        #5 scl = 1;
        #5 scl = 0; write_inout = 0;
        #5 scl = 1;

        #5 scl = 0;write_inout = 1;
        #5 scl = 1;
        #5 scl = 0;
        
        #5 scl = 1;
        #5 sda = 1;

        #500 $finish;
    end

endmodule

master_fsm_rtl/slave2.vcd
$date
	Tue Feb 06 16:31:17 2024
$end
$version
	Icarus Verilog
$end
$timescale
	1s
$end
$scope module slave_tb2 $end
$var wire 1 ! sda_pin $end
$var wire 8 " data_sent [7:0] $end
$var reg 8 # data_received [7:0] $end
$var reg 1 $ scl $end
$var reg 1 % sda $end
$var reg 1 & write_inout $end
$scope module S1 $end
$var wire 8 ' data_received [7:0] $end
$var wire 8 ( data_sent [7:0] $end
$var wire 1 $ scl $end
$var wire 1 ! sda $end
$var wire 1 ) comp_bit $end
$var reg 1 * R_W $end
$var reg 4 + address_counter [3:0] $end
$var reg 4 , current_state [3:0] $end
$var reg 4 - next_state [3:0] $end
$var reg 3 . rdata_counter [2:0] $end
$var reg 7 / received_address [6:0] $end
$var reg 8 0 received_data [7:0] $end
$var reg 1 1 reset_address_counter $end
$var reg 1 2 reset_rdata_counter $end
$var reg 1 3 reset_wdata_counter $end
$var reg 1 4 sda_reg $end
$var reg 1 5 sda_write $end
$var reg 7 6 slave_address [6:0] $end
$var reg 1 7 start_signal $end
$var reg 1 8 stop_signal $end
$var reg 3 9 wdata_counter [2:0] $end
$upscope $end
$upscope $end
$enddefinitions $end
#0
$dumpvars
bx 9
18
07
b1011011 6
05
14
x3
x2
x1
b0 0
b0 /
bx .
b0 -
b0 ,
bx +
x*
0)
b0 (
bx '
1&
1%
1$
bx #
b0 "
1!
$end
#10
b1 -
b111 +
17
01
0!
0%
#15
0$
#20
1!
1%
#25
b1 /
b1 ,
08
1$
#30
0!
0%
0$
#35
b110 +
07
b10 /
04
1$
#40
1!
1%
0$
#45
b101 +
b101 /
14
1$
#50
0$
#55
b100 +
b1011 /
1$
#60
0!
0%
0$
#65
b11 +
b10110 /
04
1$
#70
1!
1%
0$
#75
b10 +
b101101 /
14
1$
#80
0$
#85
b1 +
1)
b1011011 /
1$
#90
0!
0%
0$
#95
b0 +
0*
04
1$
#100
b10 -
15
0!
0$
0&
#105
b110 -
b10 ,
b111 +
0)
b110110 /
1$
#110
1!
05
1%
1&
0$
#115
b111 9
b1 "
b1 (
b1 0
14
03
b110 ,
1$
#120
0$
#125
b110 9
b11 "
b11 (
b11 0
1$
#130
0!
0%
0$
#135
b101 9
b110 "
b110 (
b110 0
04
1$
#140
0$
#145
b100 9
b1100 "
b1100 (
b1100 0
1$
#150
1!
1%
0$
#155
b11 9
b11001 "
b11001 (
b11001 0
14
1$
#160
0$
#165
b10 9
b110011 "
b110011 (
b110011 0
1$
#170
0!
0%
0$
#175
b1 9
b1100110 "
b1100110 (
b1100110 0
04
1$
#180
0$
#185
b0 9
b11001100 "
b11001100 (
b11001100 0
1$
#190
0!
15
b111 -
0&
0$
#195
b1000 -
b111 9
b111 ,
1$
#200
05
1&
0$
#205
b1000 ,
1$
#210
0$
#215
1$
#220
b0 ,
18
1!
1%
