master_fsm_rtl/sda_gen.v
module sda_generate #(
    parameter THRESHOLD     = 2,
    parameter ADDR_LEN      = 7,
    parameter DATA_LEN      = 8
)(
    input                       clk,
    input                       start,
    input                       scl,
    input [6:0]                 count_ctrl,
    input                       wait_for_sync,
    input                       add_sent,
    input                       data_received,
    input                       data_sent,
    input [ADDR_LEN-1:0]        add_reg,
    input                       R_W,
    input [DATA_LEN-1:0]        data_1,
    input [DATA_LEN-1:0]        data_2,
    inout                       sda,
    output                      rst_count,
    output [3:0]                state_master,
    output                      free
                                           );


    reg [3:0]           current_state = Idle;
    reg [3:0]           next_state;
    reg                 sda_reg;
    reg [2:0]           no_of_data_rec  = 0;
    reg [2:0]           no_of_data_sent = 0;
    reg [DATA_LEN-1:0]  data_mem [1:0];

    parameter Idle            = 4'b0000;
    parameter Ready           = 4'b0001;
    parameter Send_Address    = 4'b0010;
    parameter Write_Data      = 4'b0011;
    parameter Output_Data     = 4'b0100;
    parameter Check_ACK       = 4'b0101;
    parameter Read_Data       = 4'b0110;
    parameter Store_Data      = 4'b0111;
    parameter Check_for_Valid = 4'b1000;
    parameter Send_ACK        = 4'b1001;
    parameter Send_NACK       = 4'b1010;
    parameter Stop            = 4'b1011;

    always @(posedge clk)
    begin
        if(current_state == Ready)
        begin
            if(count_ctrl == 2*THRESHOLD) sda_reg = 0;
        end

        else if(current_state == Send_Address)
        begin
            if(~scl && ~add_sent && count_ctrl/(2*THRESHOLD) <= 6) sda_reg = add_reg[6 - count_ctrl/(2*THRESHOLD)];
            else if(~scl && add_sent && R_W)
            begin
                sda_reg    <= R_W;
            end
            else if(~scl && add_sent && ~R_W)
            begin
                sda_reg    <= R_W;
            end
        end

        else if(current_state == Read_Data)
        begin
            sda_reg <= 1'bz;
        end

        else if(current_state == Store_Data)
        begin
            sda_reg <= 1'bz;
            if(~scl && ~data_received && count_ctrl/(2*THRESHOLD) <= 7) data_mem[no_of_data_rec][7 - count_ctrl/(2*THRESHOLD)] = sda;
        end

        //else if(current_state == Check_for_Valid)
        //begin
        //    if(data_mem[no_of_data_rec] != 8'hFF) next_state <= Send_ACK;
        //    else next_state <= Send_NACK;
        //end

        else if(current_state == Send_ACK)
        begin
            if(~scl) 
            begin
                sda_reg <= 1'b0;
            end
        end

        //else if(current_state == Send_NACK)
        //begin
        //    next_state <= Stop;
        //end

        else if(current_state == Write_Data)
        begin
            sda_reg <= 1'bz;
        end

        else if(current_state == Output_Data)
        begin
            if(~scl && ~data_sent && count_ctrl/(2*THRESHOLD) <= 7) sda_reg <= data_mem[no_of_data_sent][7 - count_ctrl/(2*THRESHOLD)];
        end

        else if(current_state == Check_ACK)
        begin
            sda_reg <= 1'bz;
        end

        else if(current_state == Stop)
        begin
            if(count_ctrl == 4*THRESHOLD) 
            begin
                sda_reg    <= 1'b1;
            end
        end

        current_state <= next_state;
    end


//Combo Logic for next_state
always @(*)
    begin
        if(current_state == Idle)
        begin
            if(start)
            begin
                next_state <= Ready;
            end
        end

        else if(current_state == Ready)
        begin
            if(count_ctrl == 2*THRESHOLD) sda_reg = 0;
            else if(wait_for_sync)
            begin
                next_state  <= Send_Address;
            end
            else next_state <= Ready;
        end

        else if(current_state == Send_Address)
        begin
            if(~scl && add_sent && R_W)
            begin
                next_state <= Read_Data;
            end
            else if(~scl && add_sent && ~R_W)
            begin
                next_state = Write_Data;
            end
        end

        else if(current_state == Read_Data)
        begin
            if(~scl)
            begin
                if(sda) next_state <= Store_Data;
                else    next_state <= Stop;
            end
        end

        else if(current_state == Store_Data)
        begin
            if(data_received)
            begin
                next_state <= Check_for_Valid;
            end
        end

        else if(current_state == Check_for_Valid)
        begin
            if(data_mem[no_of_data_rec] != 8'hFF) next_state <= Send_ACK;
            else next_state <= Send_NACK;
        end

        else if(current_state == Send_ACK)
        begin
            if(~scl) 
            begin
                no_of_data_rec   <= no_of_data_rec + 1'b1;
            end
            if(no_of_data_rec < 2) next_state <= Store_Data;
            else next_state <= Stop;
        end

        else if(current_state == Send_NACK)
        begin
            next_state <= Stop;
        end

        else if(current_state == Write_Data)
        begin
            if(sda) next_state <= Output_Data;
            else next_state    <= Write_Data;
        end

        else if(current_state == Output_Data)
        begin
            if(data_sent)
            begin
                next_state <= Check_ACK;
            end
        end

        else if(current_state == Check_ACK)
        begin
            if(~scl)
            begin
                no_of_data_sent <= no_of_data_sent + 1'b1;
                if(sda && no_of_data_sent < 2) next_state <= Output_Data;
                else if(~sda) next_state <= Stop;
            end
        end

        else if(current_state == Stop)
        begin
            if(count_ctrl == 4*THRESHOLD) 
            begin
                next_state <= Idle;
            end
        end
end
    
    assign state_master = current_state;
    assign free = (current_state == Idle);
    assign rst_count = (current_state == Idle) || wait_for_sync || free || add_sent || (current_state == Read_Data) || 
                       (current_state == Write_Data) || data_received || (current_state == Check_for_Valid) ||
                       (current_state == Send_ACK) || (current_state == Check_ACK);
    assign sda = sda_reg;

endmodule

master_fsm_rtl/scl_gen.v
module scl_generate #(
    parameter THRESHOLD     = 2,
    parameter ADDR_LEN      = 7,
    parameter DATA_LEN      = 8
)(
    input              clk,
    input [3:0]        state_master,
    input              rst_count,
    output reg [6:0]   count_ctrl,
    output reg         scl,
    output             wait_for_sync,
    output             add_sent,
    output             data_received,
    output             data_sent
);

    

    parameter Idle            = 4'b0000;
    parameter Ready           = 4'b0001;
    parameter Send_Address    = 4'b0010;
    parameter Write_Data      = 4'b0011;
    parameter Output_Data     = 4'b0100;
    parameter Check_ACK       = 4'b0101;
    parameter Read_Data       = 4'b0110;
    parameter Store_Data      = 4'b0111;
    parameter Check_for_Valid = 4'b1000;
    parameter Send_ACK        = 4'b1001;
    parameter Send_NACK       = 4'b1010;
    parameter Stop            = 4'b1011;

    
    always @(posedge clk)
    begin
        if(rst_count) count_ctrl = 0;
        else
        begin
            count_ctrl = count_ctrl + 1'b1;

            if(state_master == Ready)
            begin
                if(count_ctrl == 4*THRESHOLD) 
                begin
                    scl   = 1'b0;
                    count_ctrl = 0;
                end
                else 
                begin
                    scl   = 1'b1;
                end
            end
            else if(state_master != Ready && state_master != Stop)
            begin
                if(count_ctrl == THRESHOLD)
                begin
                    scl   = ~scl;
                    count_ctrl = 0;
                end
            end
            else if(state_master == Stop)
            begin
                if(count_ctrl == 2*THRESHOLD)
                begin
                    scl = 1'b1;
                end
            end
        end
    end 

    assign wait_for_sync = (count_ctrl == 4*THRESHOLD) && (state_master == Ready);
    assign add_sent      = (count_ctrl == 2*ADDR_LEN*THRESHOLD) && (state_master == Send_Address);
    assign data_received = (count_ctrl == 2*DATA_LEN*THRESHOLD) && (state_master == Store_Data);
    assign data_sent     = (count_ctrl == 2*DATA_LEN*THRESHOLD) && (state_master == Output_Data);

endmodule

master_fsm_rtl/fsm_master.v
// `include "scl_gen.v"
// `include "sda_gen.v"

module fsm_master #(
    parameter FREQ_DIFF = 4,
    parameter ADDR_LEN  = 7,
    parameter DATA_LEN  = 8
                            )
    (
        input                   clk,
        input                   start,
        input [ADDR_LEN-1:0]    add_reg,
        input                   R_W,
        input [DATA_LEN-1:0]    data_1,
        input [DATA_LEN-1:0]    data_2,
        output                  scl,
        inout                   sda,
        output                  free
    );


    wire [3:0] state_master;
    wire [6:0] count_ctrl;
    wire       rst_count;
    wire       wait_for_sync;
    wire       add_sent;
    wire       data_received;
    wire       data_sent;

    scl_generate #(
        .THRESHOLD          (FREQ_DIFF/2    ),
        .ADDR_LEN           (ADDR_LEN       ),
        .DATA_LEN           (DATA_LEN       )
        ) 
        SCL
        (
            .clk                (clk            ),
            .state_master       (state_master   ),
            .rst_count          (rst_count      ),
            .count_ctrl         (count_ctrl     ),
            .scl                (scl            ),
            .wait_for_sync      (wait_for_sync  ),
            .add_sent           (add_sent       ),
            .data_received      (data_received  ),
            .data_sent          (data_sent      )
        );
    
    sda_generate #(
        .THRESHOLD          (FREQ_DIFF/2    ),
        .ADDR_LEN           (ADDR_LEN       ),
        .DATA_LEN           (DATA_LEN       )
        ) SDA(
            .clk                (clk            ),
            .start              (start          ),
            .scl                (scl            ),
            .count_ctrl         (count_ctrl     ),
            .wait_for_sync      (wait_for_sync  ),
            .add_sent           (add_sent       ),
            .data_received      (data_received  ),
            .data_sent          (data_sent      ),
            .add_reg            (add_reg        ),
            .R_W                (R_W            ),
            .data_1             (data_1         ),
            .data_2             (data_2         ),
            .sda                (sda            ),
            .rst_count          (rst_count      ),
            .state_master       (state_master   ),
            .free               (free           )
        );

endmodule

master_fsm_rtl/tb.v
module tb_;

parameter ADDR_LEN = 7;
parameter DATA_LEN = 8;
parameter FREQ_DIFF = 4;

reg clk;
reg rst;
reg start;
reg [ADDR_LEN-1:0] add_reg;
reg R_W;
reg [DATA_LEN-1:0] data_1;
reg [DATA_LEN-1:0] data_2;
wire scl;
wire sda;
wire free;


fsm_master #(
    .FREQ_DIFF(FREQ_DIFF),
    .ADDR_LEN(ADDR_LEN),
    .DATA_LEN(DATA_LEN)
) FSM_MASTER_DUT
(
    .clk                (clk        ),
    .start              (start      ),
    .add_reg            (add_reg    ),
    .R_W                (R_W        ),
    .data_1             (data_1     ),
    .data_2             (data_2     ),
    .scl                (scl        ),
    .sda                (sda        ),
    .free               (free       )
);

localparam CLK_PERIOD = 10;
always #(CLK_PERIOD/2) clk=~clk;

initial begin
    clk = 0;
    #5000 $finish;
end

initial begin
    $dumpfile("tb_.vcd");
    $dumpvars(0, tb_);
end

initial begin
    #CLK_PERIOD rst=0; rst=0; start=0; add_reg={ADDR_LEN{1'b0}}; R_W=0; data_1={DATA_LEN{1'b0}}; data_2={DATA_LEN{1'b0}};
    #CLK_PERIOD rst=1;
    #CLK_PERIOD rst=0;
    #CLK_PERIOD start=1; add_reg=7'b1010110;
end

endmodule
`default_nettype wire

master_fsm_rtl/tb_.vcd
$date
	Tue Jan 23 14:04:09 2024
$end
$version
	Icarus Verilog
$end
$timescale
	1s
$end
$scope module tb_ $end
$var wire 1 ! sda $end
$var wire 1 " scl $end
$var wire 1 # free $end
$var reg 1 $ R_W $end
$var reg 7 % add_reg [6:0] $end
$var reg 1 & clk $end
$var reg 8 ' data_1 [7:0] $end
$var reg 8 ( data_2 [7:0] $end
$var reg 1 ) rst $end
$var reg 1 * start $end
$scope module FSM_MASTER_DUT $end
$var wire 1 $ R_W $end
$var wire 7 + add_reg [6:0] $end
$var wire 1 & clk $end
$var wire 8 , data_1 [7:0] $end
$var wire 8 - data_2 [7:0] $end
$var wire 1 * start $end
$var wire 1 . wait_for_sync $end
$var wire 4 / state_master [3:0] $end
$var wire 1 ! sda $end
$var wire 1 " scl $end
$var wire 1 0 rst_count $end
$var wire 1 # free $end
$var wire 1 1 data_sent $end
$var wire 1 2 data_received $end
$var wire 7 3 count_ctrl [6:0] $end
$var wire 1 4 add_sent $end
$scope module SCL $end
$var wire 1 4 add_sent $end
$var wire 1 & clk $end
$var wire 1 2 data_received $end
$var wire 1 1 data_sent $end
$var wire 1 . wait_for_sync $end
$var wire 4 5 state_master [3:0] $end
$var wire 1 0 rst_count $end
$var reg 7 6 count_ctrl [6:0] $end
$var reg 1 " scl $end
$upscope $end
$scope module SDA $end
$var wire 1 $ R_W $end
$var wire 7 7 add_reg [6:0] $end
$var wire 1 4 add_sent $end
$var wire 1 & clk $end
$var wire 7 8 count_ctrl [6:0] $end
$var wire 8 9 data_1 [7:0] $end
$var wire 8 : data_2 [7:0] $end
$var wire 1 2 data_received $end
$var wire 1 1 data_sent $end
$var wire 1 0 rst_count $end
$var wire 1 " scl $end
$var wire 1 ! sda $end
$var wire 1 * start $end
$var wire 4 ; state_master [3:0] $end
$var wire 1 . wait_for_sync $end
$var wire 1 # free $end
$var reg 4 < current_state [3:0] $end
$var reg 4 = next_state [3:0] $end
$var reg 3 > no_of_data_rec [2:0] $end
$var reg 3 ? no_of_data_sent [2:0] $end
$var reg 1 @ sda_reg $end
$upscope $end
$upscope $end
$upscope $end
$enddefinitions $end
#0
$dumpvars
x@
b0 ?
b0 >
bx =
b0 <
b0 ;
bx :
bx 9
bx 8
bx 7
bx 6
b0 5
04
bx 3
02
01
10
b0 /
0.
bx -
bx ,
bx +
x*
x)
bx (
bx '
0&
bx %
x$
1#
x"
x!
$end
#5
x0
x#
bx /
bx 5
bx ;
bx <
b0 3
b0 6
b0 8
1&
#10
0&
b0 (
b0 -
b0 :
b0 '
b0 ,
b0 9
0$
b0 %
b0 +
b0 7
0*
0)
#15
b1 3
b1 6
b1 8
1&
#20
0&
1)
#25
b10 3
b10 6
b10 8
1&
#30
0&
0)
#35
b11 3
b11 6
b11 8
1&
#40
0&
b1010110 %
b1010110 +
b1010110 7
1*
#45
b100 3
b100 6
b100 8
1&
#50
0&
#55
b101 3
b101 6
b101 8
1&
#60
0&
#65
b110 3
b110 6
b110 8
1&
#70
0&
#75
b111 3
b111 6
b111 8
1&
#80
0&
#85
x.
b1000 3
b1000 6
b1000 8
1&
#90
0&
#95
0.
b1001 3
b1001 6
b1001 8
1&
#100
0&
#105
b1010 3
b1010 6
b1010 8
1&
#110
0&
#115
b1011 3
b1011 6
b1011 8
1&
#120
0&
#125
b1100 3
b1100 6
b1100 8
1&
#130
0&
#135
b1101 3
b1101 6
b1101 8
1&
#140
0&
#145
b1110 3
b1110 6
b1110 8
1&
#150
0&
#155
b1111 3
b1111 6
b1111 8
1&
#160
0&
#165
b10000 3
b10000 6
b10000 8
1&
#170
0&
#175
b10001 3
b10001 6
b10001 8
1&
#180
0&
#185
b10010 3
b10010 6
b10010 8
1&
#190
0&
#195
b10011 3
b10011 6
b10011 8
1&
#200
0&
#205
b10100 3
b10100 6
b10100 8
1&
#210
0&
#215
b10101 3
b10101 6
b10101 8
1&
#220
0&
#225
b10110 3
b10110 6
b10110 8
1&
#230
0&
#235
b10111 3
b10111 6
b10111 8
1&
#240
0&
#245
b11000 3
b11000 6
b11000 8
1&
#250
0&
#255
b11001 3
b11001 6
b11001 8
1&
#260
0&
#265
b11010 3
b11010 6
b11010 8
1&
#270
0&
#275
b11011 3
b11011 6
b11011 8
1&
#280
0&
#285
x4
b11100 3
b11100 6
b11100 8
1&
#290
0&
#295
04
b11101 3
b11101 6
b11101 8
1&
#300
0&
#305
b11110 3
b11110 6
b11110 8
1&
#310
0&
#315
b11111 3
b11111 6
b11111 8
1&
#320
0&
#325
x2
x1
b100000 3
b100000 6
b100000 8
1&
#330
0&
#335
02
01
b100001 3
b100001 6
b100001 8
1&
#340
0&
#345
b100010 3
b100010 6
b100010 8
1&
#350
0&
#355
b100011 3
b100011 6
b100011 8
1&
#360
0&
#365
b100100 3
b100100 6
b100100 8
1&
#370
0&
#375
b100101 3
b100101 6
b100101 8
1&
#380
0&
#385
b100110 3
b100110 6
b100110 8
1&
#390
0&
#395
b100111 3
b100111 6
b100111 8
1&
#400
0&
#405
b101000 3
b101000 6
b101000 8
1&
#410
0&
#415
b101001 3
b101001 6
b101001 8
1&
#420
0&
#425
b101010 3
b101010 6
b101010 8
1&
#430
0&
#435
b101011 3
b101011 6
b101011 8
1&
#440
0&
#445
b101100 3
b101100 6
b101100 8
1&
#450
0&
#455
b101101 3
b101101 6
b101101 8
1&
#460
0&
#465
b101110 3
b101110 6
b101110 8
1&
#470
0&
#475
b101111 3
b101111 6
b101111 8
1&
#480
0&
#485
b110000 3
b110000 6
b110000 8
1&
#490
0&
#495
b110001 3
b110001 6
b110001 8
1&
#500
0&
#505
b110010 3
b110010 6
b110010 8
1&
#510
0&
#515
b110011 3
b110011 6
b110011 8
1&
#520
0&
#525
b110100 3
b110100 6
b110100 8
1&
#530
0&
#535
b110101 3
b110101 6
b110101 8
1&
#540
0&
#545
b110110 3
b110110 6
b110110 8
1&
#550
0&
#555
b110111 3
b110111 6
b110111 8
1&
#560
0&
#565
b111000 3
b111000 6
b111000 8
1&
#570
0&
#575
b111001 3
b111001 6
b111001 8
1&
#580
0&
#585
b111010 3
b111010 6
b111010 8
1&
#590
0&
#595
b111011 3
b111011 6
b111011 8
1&
#600
0&
#605
b111100 3
b111100 6
b111100 8
1&
#610
0&
#615
b111101 3
b111101 6
b111101 8
1&
#620
0&
#625
b111110 3
b111110 6
b111110 8
1&
#630
0&
#635
b111111 3
b111111 6
b111111 8
1&
#640
0&
#645
b1000000 3
b1000000 6
b1000000 8
1&
#650
0&
#655
b1000001 3
b1000001 6
b1000001 8
1&
#660
0&
#665
b1000010 3
b1000010 6
b1000010 8
1&
#670
0&
#675
b1000011 3
b1000011 6
b1000011 8
1&
#680
0&
#685
b1000100 3
b1000100 6
b1000100 8
1&
#690
0&
#695
b1000101 3
b1000101 6
b1000101 8
1&
#700
0&
#705
b1000110 3
b1000110 6
b1000110 8
1&
#710
0&
#715
b1000111 3
b1000111 6
b1000111 8
1&
#720
0&
#725
b1001000 3
b1001000 6
b1001000 8
1&
#730
0&
#735
b1001001 3
b1001001 6
b1001001 8
1&
#740
0&
#745
b1001010 3
b1001010 6
b1001010 8
1&
#750
0&
#755
b1001011 3
b1001011 6
b1001011 8
1&
#760
0&
#765
b1001100 3
b1001100 6
b1001100 8
1&
#770
0&
#775
b1001101 3
b1001101 6
b1001101 8
1&
#780
0&
#785
b1001110 3
b1001110 6
b1001110 8
1&
#790
0&
#795
b1001111 3
b1001111 6
b1001111 8
1&
#800
0&
#805
b1010000 3
b1010000 6
b1010000 8
1&
#810
0&
#815
b1010001 3
b1010001 6
b1010001 8
1&
#820
0&
#825
b1010010 3
b1010010 6
b1010010 8
1&
#830
0&
#835
b1010011 3
b1010011 6
b1010011 8
1&
#840
0&
#845
b1010100 3
b1010100 6
b1010100 8
1&
#850
0&
#855
b1010101 3
b1010101 6
b1010101 8
1&
#860
0&
#865
b1010110 3
b1010110 6
b1010110 8
1&
#870
0&
#875
b1010111 3
b1010111 6
b1010111 8
1&
#880
0&
#885
b1011000 3
b1011000 6
b1011000 8
1&
#890
0&
#895
b1011001 3
b1011001 6
b1011001 8
1&
#900
0&
#905
b1011010 3
b1011010 6
b1011010 8
1&
#910
0&
#915
b1011011 3
b1011011 6
b1011011 8
1&
#920
0&
#925
b1011100 3
b1011100 6
b1011100 8
1&
#930
0&
#935
b1011101 3
b1011101 6
b1011101 8
1&
#940
0&
#945
b1011110 3
b1011110 6
b1011110 8
1&
#950
0&
#955
b1011111 3
b1011111 6
b1011111 8
1&
#960
0&
#965
b1100000 3
b1100000 6
b1100000 8
1&
#970
0&
#975
b1100001 3
b1100001 6
b1100001 8
1&
#980
0&
#985
b1100010 3
b1100010 6
b1100010 8
1&
#990
0&
#995
b1100011 3
b1100011 6
b1100011 8
1&
#1000
0&
#1005
b1100100 3
b1100100 6
b1100100 8
1&
#1010
0&
#1015
b1100101 3
b1100101 6
b1100101 8
1&
#1020
0&
#1025
b1100110 3
b1100110 6
b1100110 8
1&
#1030
0&
#1035
b1100111 3
b1100111 6
b1100111 8
1&
#1040
0&
#1045
b1101000 3
b1101000 6
b1101000 8
1&
#1050
0&
#1055
b1101001 3
b1101001 6
b1101001 8
1&
#1060
0&
#1065
b1101010 3
b1101010 6
b1101010 8
1&
#1070
0&
#1075
b1101011 3
b1101011 6
b1101011 8
1&
#1080
0&
#1085
b1101100 3
b1101100 6
b1101100 8
1&
#1090
0&
#1095
b1101101 3
b1101101 6
b1101101 8
1&
#1100
0&
#1105
b1101110 3
b1101110 6
b1101110 8
1&
#1110
0&
#1115
b1101111 3
b1101111 6
b1101111 8
1&
#1120
0&
#1125
b1110000 3
b1110000 6
b1110000 8
1&
#1130
0&
#1135
b1110001 3
b1110001 6
b1110001 8
1&
#1140
0&
#1145
b1110010 3
b1110010 6
b1110010 8
1&
#1150
0&
#1155
b1110011 3
b1110011 6
b1110011 8
1&
#1160
0&
#1165
b1110100 3
b1110100 6
b1110100 8
1&
#1170
0&
#1175
b1110101 3
b1110101 6
b1110101 8
1&
#1180
0&
#1185
b1110110 3
b1110110 6
b1110110 8
1&
#1190
0&
#1195
b1110111 3
b1110111 6
b1110111 8
1&
#1200
0&
#1205
b1111000 3
b1111000 6
b1111000 8
1&
#1210
0&
#1215
b1111001 3
b1111001 6
b1111001 8
1&
#1220
0&
#1225
b1111010 3
b1111010 6
b1111010 8
1&
#1230
0&
#1235
b1111011 3
b1111011 6
b1111011 8
1&
#1240
0&
#1245
b1111100 3
b1111100 6
b1111100 8
1&
#1250
0&
#1255
b1111101 3
b1111101 6
b1111101 8
1&
#1260
0&
#1265
b1111110 3
b1111110 6
b1111110 8
1&
#1270
0&
#1275
b1111111 3
b1111111 6
b1111111 8
1&
#1280
0&
#1285
b0 3
b0 6
b0 8
1&
#1290
0&
#1295
b1 3
b1 6
b1 8
1&
#1300
0&
#1305
b10 3
b10 6
b10 8
1&
#1310
0&
#1315
b11 3
b11 6
b11 8
1&
#1320
0&
#1325
b100 3
b100 6
b100 8
1&
#1330
0&
#1335
b101 3
b101 6
b101 8
1&
#1340
0&
#1345
b110 3
b110 6
b110 8
1&
#1350
0&
#1355
b111 3
b111 6
b111 8
1&
#1360
0&
#1365
x.
b1000 3
b1000 6
b1000 8
1&
#1370
0&
#1375
0.
b1001 3
b1001 6
b1001 8
1&
#1380
0&
#1385
b1010 3
b1010 6
b1010 8
1&
#1390
0&
#1395
b1011 3
b1011 6
b1011 8
1&
#1400
0&
#1405
b1100 3
b1100 6
b1100 8
1&
#1410
0&
#1415
b1101 3
b1101 6
b1101 8
1&
#1420
0&
#1425
b1110 3
b1110 6
b1110 8
1&
#1430
0&
#1435
b1111 3
b1111 6
b1111 8
1&
#1440
0&
#1445
b10000 3
b10000 6
b10000 8
1&
#1450
0&
#1455
b10001 3
b10001 6
b10001 8
1&
#1460
0&
#1465
b10010 3
b10010 6
b10010 8
1&
#1470
0&
#1475
b10011 3
b10011 6
b10011 8
1&
#1480
0&
#1485
b10100 3
b10100 6
b10100 8
1&
#1490
0&
#1495
b10101 3
b10101 6
b10101 8
1&
#1500
0&
#1505
b10110 3
b10110 6
b10110 8
1&
#1510
0&
#1515
b10111 3
b10111 6
b10111 8
1&
#1520
0&
#1525
b11000 3
b11000 6
b11000 8
1&
#1530
0&
#1535
b11001 3
b11001 6
b11001 8
1&
#1540
0&
#1545
b11010 3
b11010 6
b11010 8
1&
#1550
0&
#1555
b11011 3
b11011 6
b11011 8
1&
#1560
0&
#1565
x4
b11100 3
b11100 6
b11100 8
1&
#1570
0&
#1575
04
b11101 3
b11101 6
b11101 8
1&
#1580
0&
#1585
b11110 3
b11110 6
b11110 8
1&
#1590
0&
#1595
b11111 3
b11111 6
b11111 8
1&
#1600
0&
#1605
x2
x1
b100000 3
b100000 6
b100000 8
1&
#1610
0&
#1615
02
01
b100001 3
b100001 6
b100001 8
1&
#1620
0&
#1625
b100010 3
b100010 6
b100010 8
1&
#1630
0&
#1635
b100011 3
b100011 6
b100011 8
1&
#1640
0&
#1645
b100100 3
b100100 6
b100100 8
1&
#1650
0&
#1655
b100101 3
b100101 6
b100101 8
1&
#1660
0&
#1665
b100110 3
b100110 6
b100110 8
1&
#1670
0&
#1675
b100111 3
b100111 6
b100111 8
1&
#1680
0&
#1685
b101000 3
b101000 6
b101000 8
1&
#1690
0&
#1695
b101001 3
b101001 6
b101001 8
1&
#1700
0&
#1705
b101010 3
b101010 6
b101010 8
1&
#1710
0&
#1715
b101011 3
b101011 6
b101011 8
1&
#1720
0&
#1725
b101100 3
b101100 6
b101100 8
1&
#1730
0&
#1735
b101101 3
b101101 6
b101101 8
1&
#1740
0&
#1745
b101110 3
b101110 6
b101110 8
1&
#1750
0&
#1755
b101111 3
b101111 6
b101111 8
1&
#1760
0&
#1765
b110000 3
b110000 6
b110000 8
1&
#1770
0&
#1775
b110001 3
b110001 6
b110001 8
1&
#1780
0&
#1785
b110010 3
b110010 6
b110010 8
1&
#1790
0&
#1795
b110011 3
b110011 6
b110011 8
1&
#1800
0&
#1805
b110100 3
b110100 6
b110100 8
1&
#1810
0&
#1815
b110101 3
b110101 6
b110101 8
1&
#1820
0&
#1825
b110110 3
b110110 6
b110110 8
1&
#1830
0&
#1835
b110111 3
b110111 6
b110111 8
1&
#1840
0&
#1845
b111000 3
b111000 6
b111000 8
1&
#1850
0&
#1855
b111001 3
b111001 6
b111001 8
1&
#1860
0&
#1865
b111010 3
b111010 6
b111010 8
1&
#1870
0&
#1875
b111011 3
b111011 6
b111011 8
1&
#1880
0&
#1885
b111100 3
b111100 6
b111100 8
1&
#1890
0&
#1895
b111101 3
b111101 6
b111101 8
1&
#1900
0&
#1905
b111110 3
b111110 6
b111110 8
1&
#1910
0&
#1915
b111111 3
b111111 6
b111111 8
1&
#1920
0&
#1925
b1000000 3
b1000000 6
b1000000 8
1&
#1930
0&
#1935
b1000001 3
b1000001 6
b1000001 8
1&
#1940
0&
#1945
b1000010 3
b1000010 6
b1000010 8
1&
#1950
0&
#1955
b1000011 3
b1000011 6
b1000011 8
1&
#1960
0&
#1965
b1000100 3
b1000100 6
b1000100 8
1&
#1970
0&
#1975
b1000101 3
b1000101 6
b1000101 8
1&
#1980
0&
#1985
b1000110 3
b1000110 6
b1000110 8
1&
#1990
0&
#1995
b1000111 3
b1000111 6
b1000111 8
1&
#2000
0&
#2005
b1001000 3
b1001000 6
b1001000 8
1&
#2010
0&
#2015
b1001001 3
b1001001 6
b1001001 8
1&
#2020
0&
#2025
b1001010 3
b1001010 6
b1001010 8
1&
#2030
0&
#2035
b1001011 3
b1001011 6
b1001011 8
1&
#2040
0&
#2045
b1001100 3
b1001100 6
b1001100 8
1&
#2050
0&
#2055
b1001101 3
b1001101 6
b1001101 8
1&
#2060
0&
#2065
b1001110 3
b1001110 6
b1001110 8
1&
#2070
0&
#2075
b1001111 3
b1001111 6
b1001111 8
1&
#2080
0&
#2085
b1010000 3
b1010000 6
b1010000 8
1&
#2090
0&
#2095
b1010001 3
b1010001 6
b1010001 8
1&
#2100
0&
#2105
b1010010 3
b1010010 6
b1010010 8
1&
#2110
0&
#2115
b1010011 3
b1010011 6
b1010011 8
1&
#2120
0&
#2125
b1010100 3
b1010100 6
b1010100 8
1&
#2130
0&
#2135
b1010101 3
b1010101 6
b1010101 8
1&
#2140
0&
#2145
b1010110 3
b1010110 6
b1010110 8
1&
#2150
0&
#2155
b1010111 3
b1010111 6
b1010111 8
1&
#2160
0&
#2165
b1011000 3
b1011000 6
b1011000 8
1&
#2170
0&
#2175
b1011001 3
b1011001 6
b1011001 8
1&
#2180
0&
#2185
b1011010 3
b1011010 6
b1011010 8
1&
#2190
0&
#2195
b1011011 3
b1011011 6
b1011011 8
1&
#2200
0&
#2205
b1011100 3
b1011100 6
b1011100 8
1&
#2210
0&
#2215
b1011101 3
b1011101 6
b1011101 8
1&
#2220
0&
#2225
b1011110 3
b1011110 6
b1011110 8
1&
#2230
0&
#2235
b1011111 3
b1011111 6
b1011111 8
1&
#2240
0&
#2245
b1100000 3
b1100000 6
b1100000 8
1&
#2250
0&
#2255
b1100001 3
b1100001 6
b1100001 8
1&
#2260
0&
#2265
b1100010 3
b1100010 6
b1100010 8
1&
#2270
0&
#2275
b1100011 3
b1100011 6
b1100011 8
1&
#2280
0&
#2285
b1100100 3
b1100100 6
b1100100 8
1&
#2290
0&
#2295
b1100101 3
b1100101 6
b1100101 8
1&
#2300
0&
#2305
b1100110 3
b1100110 6
b1100110 8
1&
#2310
0&
#2315
b1100111 3
b1100111 6
b1100111 8
1&
#2320
0&
#2325
b1101000 3
b1101000 6
b1101000 8
1&
#2330
0&
#2335
b1101001 3
b1101001 6
b1101001 8
1&
#2340
0&
#2345
b1101010 3
b1101010 6
b1101010 8
1&
#2350
0&
#2355
b1101011 3
b1101011 6
b1101011 8
1&
#2360
0&
#2365
b1101100 3
b1101100 6
b1101100 8
1&
#2370
0&
#2375
b1101101 3
b1101101 6
b1101101 8
1&
#2380
0&
#2385
b1101110 3
b1101110 6
b1101110 8
1&
#2390
0&
#2395
b1101111 3
b1101111 6
b1101111 8
1&
#2400
0&
#2405
b1110000 3
b1110000 6
b1110000 8
1&
#2410
0&
#2415
b1110001 3
b1110001 6
b1110001 8
1&
#2420
0&
#2425
b1110010 3
b1110010 6
b1110010 8
1&
#2430
0&
#2435
b1110011 3
b1110011 6
b1110011 8
1&
#2440
0&
#2445
b1110100 3
b1110100 6
b1110100 8
1&
#2450
0&
#2455
b1110101 3
b1110101 6
b1110101 8
1&
#2460
0&
#2465
b1110110 3
b1110110 6
b1110110 8
1&
#2470
0&
#2475
b1110111 3
b1110111 6
b1110111 8
1&
#2480
0&
#2485
b1111000 3
b1111000 6
b1111000 8
1&
#2490
0&
#2495
b1111001 3
b1111001 6
b1111001 8
1&
#2500
0&
#2505
b1111010 3
b1111010 6
b1111010 8
1&
#2510
0&
#2515
b1111011 3
b1111011 6
b1111011 8
1&
#2520
0&
#2525
b1111100 3
b1111100 6
b1111100 8
1&
#2530
0&
#2535
b1111101 3
b1111101 6
b1111101 8
1&
#2540
0&
#2545
b1111110 3
b1111110 6
b1111110 8
1&
#2550
0&
#2555
b1111111 3
b1111111 6
b1111111 8
1&
#2560
0&
#2565
b0 3
b0 6
b0 8
1&
#2570
0&
#2575
b1 3
b1 6
b1 8
1&
#2580
0&
#2585
b10 3
b10 6
b10 8
1&
#2590
0&
#2595
b11 3
b11 6
b11 8
1&
#2600
0&
#2605
b100 3
b100 6
b100 8
1&
#2610
0&
#2615
b101 3
b101 6
b101 8
1&
#2620
0&
#2625
b110 3
b110 6
b110 8
1&
#2630
0&
#2635
b111 3
b111 6
b111 8
1&
#2640
0&
#2645
x.
b1000 3
b1000 6
b1000 8
1&
#2650
0&
#2655
0.
b1001 3
b1001 6
b1001 8
1&
#2660
0&
#2665
b1010 3
b1010 6
b1010 8
1&
#2670
0&
#2675
b1011 3
b1011 6
b1011 8
1&
#2680
0&
