master_fsm_rtl/counter.v
module counter(
               input            clk,
               input            rst_n,
               input            rst_count_2,
               input            count_inc,
               output reg [3:0] count
);

always @(posedge clk or negedge rst_n) begin
    if(~rst_n) count <= 0;
    else 
    begin
        if(rst_count_2) count <= 0;
        else if(count_inc)
        begin
            count <= count + 1'b1;
        end
    end
end
endmodule

master_fsm_rtl/sda_gen.v
module sda_generate #(
    parameter THRESHOLD         = 2,
    parameter ADDR_LEN          = 7,
    parameter DATA_LEN          = 8,
    parameter SETUP_SDA_START   = 2,
    parameter SETUP_SDA_STOP    = 2,
    parameter SETUP_SDA         = 3,
    parameter T_HIGH            = 4,
    parameter T_LOW             = 6
    )(
    input                       clk,
    input                       rst_n,
    input                       start,
    input                       scl,
    input [6:0]                 count_ctrl,
    input [3:0]                 count,
    input                       wait_for_sync,
    input                       add_sent,
    input                       data_received,
    input                       data_sent,
    input [ADDR_LEN-1:0]        add_reg,
    input                       R_W,
    input [DATA_LEN-1:0]        data_1,
    input [DATA_LEN-1:0]        data_2,
    inout                       sda,
    output                      rst_count,
    output                      rst_count_2,
    output [3:0]                state_master,
    output                      free
                                           );


    reg [3:0]           current_state;
    reg [3:0]           next_state;
    reg                 sda_reg;
    reg [1:0]           no_of_data_rec;
    reg [1:0]           no_of_data_sent; //See if one can be used
    reg [DATA_LEN-1:0]  data_mem [1:0];
    reg                 ack_reg;

    parameter Idle            = 4'b0000;
    parameter Ready           = 4'b0001;
    parameter Send_Address    = 4'b0010;
    parameter Write_Data      = 4'b0011;
    parameter Output_Data     = 4'b0100;
    parameter Check_ACK_data  = 4'b0101;
    parameter Read_Data       = 4'b0110;
    parameter Store_Data      = 4'b0111;
    parameter Check_for_Valid = 4'b1000;
    parameter Send_ACK        = 4'b1001;
    parameter Send_NACK       = 4'b1010;
    parameter Stop            = 4'b1011;
    parameter Check_ACK_addr  = 4'b1100;


//always block for curr_state
    always @(posedge clk or negedge rst_n)
        begin
            if(~rst_n) begin
                current_state <= Idle;
            end else begin
                current_state <= next_state;
            end

        end
    //always block for sda_reg
    always @(posedge clk or negedge rst_n)
    begin
        if(~rst_n) begin
            sda_reg <= 1'b1;
        end
     else begin
        case (current_state) 

        Idle: begin
            sda_reg <= 1'bz;
        end

        Ready : begin
            if(count_ctrl == (SETUP_SDA_START -1)) begin
                sda_reg <= 1'b0;
            end
        end
        
        Send_Address : begin
            if(count <= ADDR_LEN -1) begin
                if(count_ctrl == T_LOW - SETUP_SDA - 1) sda_reg <= add_reg[(ADDR_LEN - 1) - count];
            end else begin
                if(count_ctrl == T_LOW - SETUP_SDA - 1) sda_reg <= R_W;
            end
        end

        Check_ACK_addr: begin
            if(count_ctrl == T_LOW -SETUP_SDA - 1) begin
                sda_reg <= 1'bz;
            end
        end

        Write_Data: begin
            if(count_ctrl == T_LOW -SETUP_SDA -1 && no_of_data_sent == 0) sda_reg <= data_1[DATA_LEN-1-count];
            else if(count_ctrl == T_LOW -SETUP_SDA -1 && no_of_data_sent == 1) sda_reg <= data_2[DATA_LEN-1-count];
        end

        Check_ACK_data: begin
            if(count_ctrl == T_LOW -SETUP_SDA - 1) begin
                sda_reg <= 1'bz;
            end
        end

        // Read_Data

        Stop: begin
            if (count_ctrl == T_HIGH+T_LOW -1 ) begin
                sda_reg <= 1'bz;
            end else if(count_ctrl >= T_LOW + SETUP_SDA_STOP -1) begin
                sda_reg <= 1; 
            end else begin
                sda_reg <= 0;
            end
        end
    
        
     endcase 

     end
    end

//always block for ack_reg
always @(posedge clk or negedge rst_n) begin
    if(~rst_n) begin
        ack_reg <= 0;
    end else begin
        if(add_sent || data_sent) begin
            ack_reg <= 0;
        end else if((state_master == Check_ACK_addr || state_master == Check_ACK_data) &&scl && sda) begin
            ack_reg <= 1;
        end
    end 
end

//always block for no_of_data_sent
always @(posedge clk or negedge rst_n) begin
    if(~rst_n) begin
        no_of_data_sent <= 0;
    end else begin
        if(data_sent) no_of_data_sent <= no_of_data_sent + 1'b1;
        if(current_state == Idle) begin
            no_of_data_sent <= 0;
        end
    end
end

//Combo Logic for next_state
always @(*) begin
    next_state = current_state;

    case(current_state)
        Idle : begin
            if(start) begin
                next_state = Ready;
            end
        end

        Ready: begin
           if(wait_for_sync) begin
                next_state = Send_Address;
           end
        end

        Send_Address: begin
            if(add_sent) next_state = Check_ACK_addr;
        end

        Check_ACK_addr: begin
            if(~ack_reg && (count_ctrl==T_LOW+T_HIGH-1)) begin
                if(R_W) begin
                    next_state = Read_Data;
                end else begin
                    next_state = Write_Data;
                end
            end
            else if(ack_reg && (count_ctrl==T_LOW+T_HIGH-1)) begin
                next_state = Stop;
            end
        end

        Write_Data : begin
            if(data_sent) next_state = Check_ACK_data;
        end

        Check_ACK_data: begin
            if(no_of_data_sent == 1 && ~ack_reg && (count_ctrl==T_LOW+T_HIGH-1)) next_state = Write_Data;
            else if(no_of_data_sent == 1 && ack_reg && (count_ctrl==T_LOW+T_HIGH-1)) next_state = Stop;
            else if (no_of_data_sent == 2 && (count_ctrl == T_LOW + T_HIGH - 1)) next_state = Stop;
        end

        Stop: begin
            if((count_ctrl==T_LOW+T_HIGH-1)) next_state = Idle;
        end
       
    endcase

end

    
    assign state_master = current_state;
    assign free = (current_state == Idle);
    assign rst_count = (current_state == Idle) || wait_for_sync || free || add_sent || data_sent || 
                        data_received ;
    assign rst_count_2 = wait_for_sync || add_sent || data_sent;
    assign sda = sda_reg;

endmodule

master_fsm_rtl/scl_gen.v
module scl_generate #(
    //parameter THRESHOLD     = 2,
    parameter T_LOW         = 6,
    parameter T_HIGH        = 4,  //SCL is LOW for T_LOW*CLK_PERIOD and HIGH for T_HIGH*CLK_PERIOD
    parameter ADDR_LEN      = 7,
    parameter SETUP_SCL_START = 4,
    parameter DATA_LEN      = 8
)(
    input              clk,
    input              rst_n,
    input [3:0]        state_master,
    input              rst_count,
    input [3:0]        count,
    output reg [6:0]   count_ctrl,
    output reg         scl,
    output             wait_for_sync,
    output             add_sent,
    output             data_received,
    output             data_sent,
    output             count_inc
);


    parameter Idle            = 4'b0000;
    parameter Ready           = 4'b0001;
    parameter Send_Address    = 4'b0010;
    parameter Check_ACK_addr  = 4'b0011;
    parameter Write_Data      = 4'b0100;
    parameter Check_ACK_data  = 4'b0101;
    parameter Read_Data       = 4'b0110;
    parameter Send_ACK        = 4'b0111;
    parameter Stop            = 4'b1000;

//always block for count_ctrl
always @(posedge clk or negedge rst_n) begin
    if(~rst_n) begin
        count_ctrl <= 0;
    end else begin
        if (rst_count) begin
            count_ctrl <= 0;
        end else begin
            if (state_master == Ready) begin
                if(count_ctrl == (SETUP_SCL_START-1)) begin
                    count_ctrl <= 0;
                end else begin
                    count_ctrl <= count_ctrl + 1;
                end
            end else if(state_master != Ready && state_master != Stop && state_master!=Idle) begin
                if (count_ctrl == (T_LOW+T_HIGH-1)) begin
                    count_ctrl <= 0;
                end else begin
                    count_ctrl <= count_ctrl + 1; 
                end
            end else begin //what happens to cnt cntrl in other states?
                count_ctrl <= count_ctrl + 1;
            end
        end
    end
end

//always block for scl
always @(posedge clk or negedge rst_n) begin
    if (~rst_n) begin
        scl <= 1'b1; //check
    end else begin
        if (state_master == Ready) begin
            if (count_ctrl == SETUP_SCL_START-1) begin
                scl <= 1'b0;
            end
        end else if(state_master != Ready && state_master != Idle && state_master != Stop) begin
            if(count_ctrl < T_LOW -1 || count_ctrl == (T_HIGH + T_LOW -1) ) begin
                scl <= 1'b0;
            end else begin
                scl <= 1'b1;
            end
        end
        else if(state_master == Idle) begin
            scl <= 1'b1;
        end
        else if(state_master == Stop) begin
            if(count_ctrl < T_LOW -1) begin
                scl <= 1'b0;
            end else if (count_ctrl == T_HIGH+T_LOW -1 ) begin
                scl <= 1'b1;
            end
            else  begin
                scl <= 1'b1;
            end
        end
    end
end

    assign wait_for_sync = (count_ctrl == (SETUP_SCL_START-1)) && (state_master == Ready);
    assign add_sent      = (count      == ADDR_LEN) && (count_ctrl == T_HIGH + T_LOW -1 ) && (state_master == Send_Address);
    assign data_received = (count      == DATA_LEN-1) && (count_ctrl == T_HIGH + T_LOW - 1) && (state_master == Read_Data);
    assign data_sent     = (count      == DATA_LEN-1) && (count_ctrl == T_HIGH + T_LOW - 1) && (state_master == Write_Data);
    assign count_inc     = (count_ctrl == T_HIGH + T_LOW - 1) && (state_master == Send_Address || state_master == Write_Data|| state_master == Read_Data);

endmodule

master_fsm_rtl/fsm_master.v
// Master Controller
module fsm_master #(
    parameter FREQ_DIFF = 4,
    parameter T_LOW     = 6,
    parameter T_HIGH    = 4,
    parameter ADDR_LEN  = 7,
    parameter SETUP_SCL_START = 4,
    parameter SETUP_SDA_START = 2,
    parameter DATA_LEN  = 8
                            )
    (
        input                   clk,
        input                   rst_n,
        input                   start,
        input [ADDR_LEN-1:0]    add_reg,
        input                   R_W,
        input [DATA_LEN-1:0]    data_1,
        input [DATA_LEN-1:0]    data_2,
        output                  scl,
        inout                   sda,
        output                  free
    );


    wire [3:0] state_master;
    wire [6:0] count_ctrl;
    wire [3:0] count;
    wire       count_inc;
    wire       rst_count_2;
    wire       rst_count;
    wire       wait_for_sync;
    wire       add_sent;
    wire       data_received;
    wire       data_sent;

    scl_generate #(
        .THRESHOLD          (FREQ_DIFF/2    ),
        .T_LOW              (T_LOW          ),
        .T_HIGH             (T_HIGH         ),
        .ADDR_LEN           (ADDR_LEN       ),
        .SETUP_SCL_START    (SETUP_SCL_START),
        .DATA_LEN           (DATA_LEN       )
        ) 
        SCL
        (
            .clk                (clk            ),
            .rst_n              (rst_n          ),
            .state_master       (state_master   ),
            .rst_count          (rst_count      ),
            .count              (count          ),
            .count_ctrl         (count_ctrl     ),
            .scl                (scl            ),
            .wait_for_sync      (wait_for_sync  ),
            .add_sent           (add_sent       ),
            .data_received      (data_received  ),
            .data_sent          (data_sent      ),
            .count_inc          (count_inc      )
        );
    
    sda_generate #(
        .THRESHOLD          (FREQ_DIFF/2    ),
        .ADDR_LEN           (ADDR_LEN       ),
        .SETUP_SDA_START    (SETUP_SDA_START),
        .DATA_LEN           (DATA_LEN       )
        ) SDA(
            .clk                (clk            ),
            .rst_n              (rst_n          ),
            .start              (start          ),
            .scl                (scl            ),
            .count_ctrl         (count_ctrl     ),
            .count              (count          ),
            .wait_for_sync      (wait_for_sync  ),
            .add_sent           (add_sent       ),
            .data_received      (data_received  ),
            .data_sent          (data_sent      ),
            .add_reg            (add_reg        ),
            .R_W                (R_W            ),
            .data_1             (data_1         ),
            .data_2             (data_2         ),
            .sda                (sda            ),
            .rst_count          (rst_count      ),
            .rst_count_2        (rst_count_2    ),
            .state_master       (state_master   ),
            .free               (free           )
        );

    counter COUNTER(
            .clk                (clk            ),
            .rst_n              (rst_n          ),
            .rst_count_2        (rst_count_2    ),
            .count_inc          (count_inc      ),
            .count              (count          )
    );

endmodule

master_fsm_rtl/tb.v
module tb_;

parameter ADDR_LEN = 7;
parameter DATA_LEN = 8;
parameter FREQ_DIFF = 4;
parameter SETUP_SDA_START=2;
parameter SETUP_SCL_START=4;

reg clk;
reg rst_n;
reg start;
reg [ADDR_LEN-1:0] add_reg;
reg R_W;
reg [DATA_LEN-1:0] data_1;
reg [DATA_LEN-1:0] data_2;
wire scl;
wire sda;
wire free;


fsm_master #(
    .FREQ_DIFF              (FREQ_DIFF),
    .ADDR_LEN               (ADDR_LEN),
    .SETUP_SCL_START        (SETUP_SCL_START),
    .SETUP_SDA_START        (SETUP_SDA_START),
    .DATA_LEN               (DATA_LEN)
) FSM_MASTER_DUT
(
    .clk                (clk        ),
    .rst_n              (rst_n      ),
    .start              (start      ),
    .add_reg            (add_reg    ),
    .R_W                (R_W        ),
    .data_1             (data_1     ),
    .data_2             (data_2     ),
    .scl                (scl        ),
    .sda                (sda        ),
    .free               (free       )
);

localparam CLK_PERIOD = 10;
always #(CLK_PERIOD/2) clk=~clk;

initial begin
    clk = 0;
    #5000 $finish;
end

initial begin
    $dumpfile("tb_.vcd");
    $dumpvars(0, tb_);
end

initial begin
    #CLK_PERIOD RST_TEST;
    #CLK_PERIOD START_TEST(7'b1010110, 0);
    
end

task START_TEST(input[ADDR_LEN-1:0] addr, input r_w);
    begin
        wait(free);
        rst_n=1; start=1; data_1 =8'hab; data_2 = 8'hab; R_W=r_w;add_reg=addr; 
        #CLK_PERIOD; 
        if(free) begin
            $display("ERROR: free HIGH after start..");
            $finish;
        end
        else begin
            $display("Operation Started successfully..");
        end
        START_TEST_checker;
        SEND_ADDR_checker(addr);
    end
endtask

task START_TEST_checker;
    begin
        wait(~free);
        if(~sda || ~scl) begin
            $display("ERROR: START_TEST failed");
            $finish;
        end
        #SETUP_SDA_START
        if(sda || ~scl) begin
            $display("ERROR: START_TEST failed");
            $finish;
        end
        #(SETUP_SCL_START-SETUP_SDA_START)
        if(sda || scl) begin
            $display("ERROR: START_TEST failed");
            $finish;
        end
        $display("START condition verified..");
    end
endtask

task SEND_ADDR_checker(input[ADDR_LEN-1:0] addr);
    reg count;
    begin
        count = 0;
        wait(~scl);
        repeat(ADDR_LEN) begin
            wait(scl);
            if(sda != addr[ADDR_LEN-count -1]) begin
                $display("ERROR: Incorrect ADDR sent!");
                $finish;
            end
            count = count+1;
            wait(~scl);
        end
        $display("ADDR transmitted successfully..");
    end
endtask



task RST_TEST;
    begin
        @(posedge clk)
        rst_n = 1'b0; start=0; add_reg={ADDR_LEN{1'b0}}; R_W=0; data_1={DATA_LEN{1'b0}}; data_2={DATA_LEN{1'b0}};
        wait(CLK_PERIOD);
        if(~free || ~sda || ~scl) begin
            $display("RST_TEST FAILED");
            $finish;
        end else begin
            $display("RST_TEST passed.");
        end
    end

endtask

endmodule
// `default_nettype wire

master_fsm_rtl/tb_.vcd
$date
	Tue Jan 30 08:43:25 2024
$end
$version
	Icarus Verilog
$end
$timescale
	1s
$end
$scope module tb_ $end
$var wire 1 ! sda $end
$var wire 1 " scl $end
$var wire 1 # free $end
$var reg 1 $ R_W $end
$var reg 7 % add_reg [6:0] $end
$var reg 1 & clk $end
$var reg 8 ' data_1 [7:0] $end
$var reg 8 ( data_2 [7:0] $end
$var reg 1 ) rst_n $end
$var reg 1 * start $end
$scope module FSM_MASTER_DUT $end
$var wire 1 $ R_W $end
$var wire 7 + add_reg [6:0] $end
$var wire 1 & clk $end
$var wire 8 , data_1 [7:0] $end
$var wire 8 - data_2 [7:0] $end
$var wire 1 ) rst_n $end
$var wire 1 * start $end
$var wire 1 . wait_for_sync $end
$var wire 4 / state_master [3:0] $end
$var wire 1 ! sda $end
$var wire 1 " scl $end
$var wire 1 0 rst_count_2 $end
$var wire 1 1 rst_count $end
$var wire 1 # free $end
$var wire 1 2 data_sent $end
$var wire 1 3 data_received $end
$var wire 1 4 count_inc $end
$var wire 7 5 count_ctrl [6:0] $end
$var wire 4 6 count [3:0] $end
$var wire 1 7 add_sent $end
$scope module COUNTER $end
$var wire 1 & clk $end
$var wire 1 ) rst_n $end
$var wire 1 0 rst_count_2 $end
$var wire 1 4 count_inc $end
$var reg 4 8 count [3:0] $end
$upscope $end
$scope module SCL $end
$var wire 1 7 add_sent $end
$var wire 1 & clk $end
$var wire 4 9 count [3:0] $end
$var wire 1 4 count_inc $end
$var wire 1 3 data_received $end
$var wire 1 2 data_sent $end
$var wire 1 ) rst_n $end
$var wire 1 . wait_for_sync $end
$var wire 4 : state_master [3:0] $end
$var wire 1 1 rst_count $end
$var reg 7 ; count_ctrl [6:0] $end
$var reg 1 " scl $end
$upscope $end
$scope module SDA $end
$var wire 1 $ R_W $end
$var wire 7 < add_reg [6:0] $end
$var wire 1 7 add_sent $end
$var wire 1 & clk $end
$var wire 4 = count [3:0] $end
$var wire 7 > count_ctrl [6:0] $end
$var wire 8 ? data_1 [7:0] $end
$var wire 8 @ data_2 [7:0] $end
$var wire 1 3 data_received $end
$var wire 1 2 data_sent $end
$var wire 1 1 rst_count $end
$var wire 1 0 rst_count_2 $end
$var wire 1 ) rst_n $end
$var wire 1 " scl $end
$var wire 1 ! sda $end
$var wire 1 * start $end
$var wire 4 A state_master [3:0] $end
$var wire 1 . wait_for_sync $end
$var wire 1 # free $end
$var reg 1 B ack_reg $end
$var reg 4 C current_state [3:0] $end
$var reg 4 D next_state [3:0] $end
$var reg 2 E no_of_data_sent [1:0] $end
$var reg 1 F sda_reg $end
$upscope $end
$upscope $end
$scope task RST_TEST $end
$upscope $end
$scope task SEND_ADDR_checker $end
$var reg 7 G addr [6:0] $end
$var reg 1 H count $end
$upscope $end
$scope task START_TEST $end
$var reg 7 I addr [6:0] $end
$var reg 1 J r_w $end
$upscope $end
$scope task START_TEST_checker $end
$upscope $end
$upscope $end
$enddefinitions $end
#0
$dumpvars
xJ
bx I
xH
bx G
xF
bx E
bx D
bx C
xB
bx A
bx @
bx ?
bx >
bx =
bx <
bx ;
bx :
bx 9
bx 8
x7
bx 6
bx 5
x4
x3
x2
x1
x0
bx /
x.
bx -
bx ,
bx +
x*
x)
bx (
bx '
0&
bx %
x$
x#
x"
x!
$end
#5
1&
#10
0&
#15
11
00
02
07
0.
03
04
b0 D
b0 6
b0 8
b0 9
b0 =
b0 E
0B
1!
1F
1#
b0 /
b0 :
b0 A
b0 C
1"
b0 5
b0 ;
b0 >
b0 (
b0 -
b0 @
b0 '
b0 ,
b0 ?
0$
b0 %
b0 +
b0 <
0*
0)
1&
#20
0&
#25
01
z"
0#
b1 /
b1 :
b1 A
b1 C
z!
zF
b1 D
1&
b1010110 %
b1010110 +
b1010110 <
b10101011 (
b10101011 -
b10101011 @
b10101011 '
b10101011 ,
b10101011 ?
1*
1)
0J
b1010110 I
#30
0&
#35
b1 5
b1 ;
b1 >
1&
#39
0H
b1010110 G
#40
0&
#45
b10 5
b10 ;
b10 >
0!
0F
1&
#50
0&
#55
11
10
b10 D
1.
b11 5
b11 ;
b11 >
1&
#60
0&
#65
01
00
0.
b0 5
b0 ;
b0 >
0"
b10 /
b10 :
b10 A
b10 C
1&
#70
0&
#75
b1 5
b1 ;
b1 >
1&
#80
0&
#85
b10 5
b10 ;
b10 >
1&
#90
0&
#95
1!
1F
b11 5
b11 ;
b11 >
1&
#100
0&
#105
b100 5
b100 ;
b100 >
1&
#110
0&
#115
b101 5
b101 ;
b101 >
1&
#120
0&
#125
1H
b110 5
b110 ;
b110 >
1"
1&
#130
0&
#135
b111 5
b111 ;
b111 >
1&
#140
0&
#145
b1000 5
b1000 ;
b1000 >
1&
#150
0&
#155
14
b1001 5
b1001 ;
b1001 >
1&
#160
0&
#165
04
b0 5
b0 ;
b0 >
0"
b1 6
b1 8
b1 9
b1 =
1&
#170
0&
#175
b1 5
b1 ;
b1 >
1&
#180
0&
#185
b10 5
b10 ;
b10 >
1&
#190
0&
#195
0!
0F
b11 5
b11 ;
b11 >
1&
#200
0&
#205
b100 5
b100 ;
b100 >
1&
#210
0&
#215
b101 5
b101 ;
b101 >
1&
#220
0&
#225
0H
b110 5
b110 ;
b110 >
1"
1&
#230
0&
#235
b111 5
b111 ;
b111 >
1&
#240
0&
#245
b1000 5
b1000 ;
b1000 >
1&
#250
0&
#255
14
b1001 5
b1001 ;
b1001 >
1&
#260
0&
#265
04
b0 5
b0 ;
b0 >
0"
b10 6
b10 8
b10 9
b10 =
1&
#270
0&
#275
b1 5
b1 ;
b1 >
1&
#280
0&
#285
b10 5
b10 ;
b10 >
1&
#290
0&
#295
1!
1F
b11 5
b11 ;
b11 >
1&
#300
0&
#305
b100 5
b100 ;
b100 >
1&
#310
0&
#315
b101 5
b101 ;
b101 >
1&
#320
0&
#325
1H
b110 5
b110 ;
b110 >
1"
1&
#330
0&
#335
b111 5
b111 ;
b111 >
1&
#340
0&
#345
b1000 5
b1000 ;
b1000 >
1&
#350
0&
#355
14
b1001 5
b1001 ;
b1001 >
1&
#360
0&
#365
04
b0 5
b0 ;
b0 >
0"
b11 6
b11 8
b11 9
b11 =
1&
#370
0&
#375
b1 5
b1 ;
b1 >
1&
#380
0&
#385
b10 5
b10 ;
b10 >
1&
#390
0&
#395
0!
0F
b11 5
b11 ;
b11 >
1&
#400
0&
#405
b100 5
b100 ;
b100 >
1&
#410
0&
#415
b101 5
b101 ;
b101 >
1&
#420
0&
#425
0H
b110 5
b110 ;
b110 >
1"
1&
#430
0&
#435
b111 5
b111 ;
b111 >
1&
#440
0&
#445
b1000 5
b1000 ;
b1000 >
1&
#450
0&
#455
14
b1001 5
b1001 ;
b1001 >
1&
#460
0&
#465
04
b0 5
b0 ;
b0 >
0"
b100 6
b100 8
b100 9
b100 =
1&
#470
0&
#475
b1 5
b1 ;
b1 >
1&
#480
0&
#485
b10 5
b10 ;
b10 >
1&
#490
0&
#495
1!
1F
b11 5
b11 ;
b11 >
1&
#500
0&
#505
b100 5
b100 ;
b100 >
1&
#510
0&
#515
b101 5
b101 ;
b101 >
1&
#520
0&
#525
1H
b110 5
b110 ;
b110 >
1"
1&
#530
0&
#535
b111 5
b111 ;
b111 >
1&
#540
0&
#545
b1000 5
b1000 ;
b1000 >
1&
#550
0&
#555
14
b1001 5
b1001 ;
b1001 >
1&
#560
0&
#565
04
b0 5
b0 ;
b0 >
0"
b101 6
b101 8
b101 9
b101 =
1&
#570
0&
#575
b1 5
b1 ;
b1 >
1&
#580
0&
#585
b10 5
b10 ;
b10 >
1&
#590
0&
#595
b11 5
b11 ;
b11 >
1&
#600
0&
#605
b100 5
b100 ;
b100 >
1&
#610
0&
#615
b101 5
b101 ;
b101 >
1&
#620
0&
#625
b110 5
b110 ;
b110 >
1"
1&
