master_fsm_rtl/counter.v
module counter(
               input            clk,
               input            rst_n,
               input            rst_count_2,
               input            count_inc,
               output reg [3:0] count
);

always @(posedge clk or negedge rst_n) begin
    if(~rst_n) count <= 0;
    else 
    begin
        if(rst_count_2) count <= 0;
        else if(count_inc)
        begin
            count <= count + 1'b1;
        end
    end
end
endmodule

master_fsm_rtl/sda_gen.v
module sda_generate #(
    parameter THRESHOLD         = 2,
    parameter ADDR_LEN          = 7,
    parameter DATA_LEN          = 8,
    parameter SETUP_SDA_START   = 2,
    parameter SETUP_SDA_STOP    = 2,
    parameter SETUP_SDA         = 3,
    parameter T_HIGH            = 4,
    parameter T_LOW             = 6
    )(
    input                       clk,
    input                       rst_n,
    input                       start,
    input                       scl,
    input [6:0]                 count_ctrl,
    input [3:0]                 count,
    input                       wait_for_sync,
    input                       add_sent,
    input                       data_received,
    input                       data_sent,
    input [ADDR_LEN-1:0]        add_reg,
    input                       R_W,
    input [DATA_LEN-1:0]        data_1,
    input [DATA_LEN-1:0]        data_2,
    input                       ack_3p,
    inout                       sda,
    output                      rst_count,
    output                      rst_count_2,
    output [3:0]                state_master,
    output                      free
                                           );


    reg [3:0]           current_state;
    reg [3:0]           next_state;
    reg                 sda_reg;
    reg [1:0]           no_of_data_rec;
    reg [1:0]           no_of_data_sent; //See if one can be used
    reg [DATA_LEN-1:0]  data_mem [1:0];
    reg                 ack_reg;

    parameter Idle            = 4'b0000;
    parameter Ready           = 4'b0001;
    parameter Send_Address    = 4'b0010;
    parameter Write_Data      = 4'b0011;
    parameter Output_Data     = 4'b0100;
    parameter Check_ACK_data  = 4'b0101;
    parameter Read_Data       = 4'b0110;
    parameter Store_Data      = 4'b0111;
    parameter Check_for_Valid = 4'b1000;
    parameter Send_ACK        = 4'b1001;
    parameter Send_NACK       = 4'b1010;
    parameter Stop            = 4'b1011;
    parameter Check_ACK_addr  = 4'b1100;


//always block for curr_state
    always @(posedge clk or negedge rst_n)
        begin
            if(~rst_n) begin
                current_state <= Idle;
            end else begin
                current_state <= next_state;
            end

        end
    //always block for sda_reg
    always @(posedge clk or negedge rst_n)
    begin
        if(~rst_n) begin
            sda_reg <= 1'b1;
        end
     else begin
        case (current_state) 

        Idle: begin
            sda_reg <= 1'b1;
        end

        Ready : begin
            if(count_ctrl == (SETUP_SDA_START -1)) begin
                sda_reg <= 1'b0;
            end
        end
        
        Send_Address : begin
            if(count <= ADDR_LEN -1) begin
                if(count_ctrl == T_LOW - SETUP_SDA - 1) sda_reg <= add_reg[(ADDR_LEN - 1) - count];
            end else begin
                if(count_ctrl == T_LOW - SETUP_SDA - 1) sda_reg <= R_W;
            end
        end

        Check_ACK_addr: begin
            if(count_ctrl == T_LOW -SETUP_SDA - 1) begin
                sda_reg <= 1'bz;
            end
        end

        Write_Data: begin
            if(count_ctrl == T_LOW -SETUP_SDA -1 && no_of_data_sent == 0) sda_reg <= data_1[DATA_LEN-1-count];
            else if(count_ctrl == T_LOW -SETUP_SDA -1 && no_of_data_sent == 1) sda_reg <= data_2[DATA_LEN-1-count];
        end

        Check_ACK_data: begin
            if(count_ctrl == T_LOW -SETUP_SDA - 1) begin
                sda_reg <= 1'bz;
            end
        end

        Read_Data: begin
            if(count_ctrl == T_LOW -SETUP_SDA -1 && no_of_data_sent == 0) data_mem[no_of_data_sent][DATA_LEN-1-count] <= sda;
        end

        Send_ACK: begin
            if(count_ctrl == T_LOW -SETUP_SDA - 1) sda_reg <= ~ack_3p;
        end

        Stop: begin
            if (count_ctrl == T_HIGH+T_LOW -1 ) begin
                sda_reg <= 1'bz;
            end else if(count_ctrl >= T_LOW + SETUP_SDA_STOP -1) begin
                sda_reg <= 1; 
            end else begin
                sda_reg <= 0;
            end
        end
    
        
     endcase 

     end
    end

//always block for ack_reg
always @(posedge clk or negedge rst_n) begin
    if(~rst_n) begin
        ack_reg <= 0;
    end else begin
        if(add_sent || data_sent) begin
            ack_reg <= 0;
        end else if((state_master == Check_ACK_addr || state_master == Check_ACK_data) && scl && sda) begin
            ack_reg <= 1;
        end
    end 
end

//always block for no_of_data_sent
always @(posedge clk or negedge rst_n) begin
    if(~rst_n) begin
        no_of_data_sent <= 0;
    end else begin
        if(data_sent || data_received) no_of_data_sent <= no_of_data_sent + 1'b1;
        if(current_state == Idle) begin
            no_of_data_sent <= 0;
        end
    end
end

//Combo Logic for next_state
always @(*) begin
    next_state = current_state;

    case(current_state)
        Idle : begin
            if(start) begin
                next_state = Ready;
            end
        end

        Ready: begin
           if(wait_for_sync) begin
                next_state = Send_Address;
           end
        end

        Send_Address: begin
            if(add_sent) next_state = Check_ACK_addr;
        end

        Check_ACK_addr: begin
            if(~ack_reg && (count_ctrl==T_LOW+T_HIGH-1)) begin
                if(R_W) begin
                    next_state = Read_Data;
                end else begin
                    next_state = Write_Data;
                end
            end
            else if(ack_reg && (count_ctrl==T_LOW+T_HIGH-1)) begin
                next_state = Stop;
            end
        end

        Write_Data : begin
            if(data_sent) next_state = Check_ACK_data;
        end

        Check_ACK_data: begin
            if(no_of_data_sent == 1 && ~ack_reg && (count_ctrl==T_LOW+T_HIGH-1)) next_state = Write_Data;
            else if(no_of_data_sent == 1 && ack_reg && (count_ctrl==T_LOW+T_HIGH-1)) next_state = Stop;
            else if (no_of_data_sent == 2 && (count_ctrl == T_LOW + T_HIGH - 1)) next_state = Stop;
        end

        Read_Data: begin
            if(data_received) next_state = Send_ACK;
        end

        Send_ACK: begin
            if(no_of_data_sent < 2 && ack_3p && (count_ctrl==T_LOW+T_HIGH-1)) next_state = Read_Data;
            else if(no_of_data_sent < 2 && ~ack_3p && (count_ctrl==T_LOW+T_HIGH-1)) next_state = Stop;
            else if(no_of_data_sent == 2 && (count_ctrl==T_LOW+T_HIGH-1)) next_state = Stop;
        end

        Stop: begin
            if((count_ctrl==T_LOW+T_HIGH-1)) next_state = Idle;
        end
       
    endcase

end

    
    assign state_master = current_state;
    assign free = (current_state == Idle);
    assign rst_count = (current_state == Idle) || wait_for_sync || free || add_sent || data_sent || 
                        data_received ;
    assign rst_count_2 = wait_for_sync || add_sent || data_sent || data_received;
    assign sda = sda_reg;

endmodule

master_fsm_rtl/scl_gen.v
module scl_generate #(
    parameter THRESHOLD     = 2,
    parameter T_LOW         = 6,
    parameter T_HIGH        = 4,  //SCL is LOW for T_LOW*CLK_PERIOD and HIGH for T_HIGH*CLK_PERIOD
    parameter ADDR_LEN      = 7,
    parameter SETUP_SCL_START = 4,
    parameter DATA_LEN      = 8
)(
    input              clk,
    input              rst_n,
    input [3:0]        state_master,
    input              rst_count,
    input [3:0]        count,
    output reg [6:0]   count_ctrl,
    output reg         scl,
    output             wait_for_sync,
    output             add_sent,
    output             data_received,
    output             data_sent,
    output             count_inc
);

    

    parameter Idle            = 4'b0000;
    parameter Ready           = 4'b0001;
    parameter Send_Address    = 4'b0010;
    parameter Write_Data      = 4'b0011;
    parameter Output_Data     = 4'b0100;
    parameter Check_ACK       = 4'b0101;
    parameter Read_Data       = 4'b0110;
    parameter Store_Data      = 4'b0111;
    parameter Check_for_Valid = 4'b1000;
    parameter Send_ACK        = 4'b1001;
    parameter Send_NACK       = 4'b1010;
    parameter Stop            = 4'b1011;

//always block for count_ctrl
always @(posedge clk or negedge rst_n) begin
    if(~rst_n) begin
        count_ctrl <= 0;
    end else begin
        if (rst_count) begin
            count_ctrl <= 0;
        end else begin
            if (state_master == Ready) begin
                if(count_ctrl == (SETUP_SCL_START-1)) begin
                    count_ctrl <= 0;
                end else begin
                    count_ctrl <= count_ctrl + 1;
                end
            end else if(state_master != Ready && state_master != Stop && state_master!=Idle) begin
                if (count_ctrl == (T_LOW+T_HIGH-1)) begin
                    count_ctrl <= 0;
                end else begin
                    count_ctrl <= count_ctrl + 1; 
                end
            end else begin //what happens to cnt cntrl in other states?
                count_ctrl <= count_ctrl + 1;
            end
        end
    end
end

//always block for scl
always @(posedge clk or negedge rst_n) begin
    if (~rst_n) begin
        scl <= 1; //check
    end else begin
        if (state_master == Ready) begin
            if (count_ctrl == SETUP_SCL_START-1) begin
                scl <= 1'b0;
            end
        end else if(state_master != Ready && state_master != Idle && state_master != Stop) begin
            if(count_ctrl < T_LOW -1 || count_ctrl == (T_HIGH + T_LOW -1) ) begin
                scl <= 1'b0;
            end else begin
                scl <= 1'b1;
            end
        end
        else if(state_master == Idle) begin
            scl <= 1'b1;
        end
        else if(state_master == Stop) begin
            if(count_ctrl < T_LOW -1) begin
                scl <= 1'b0;
            end else if (count_ctrl == T_HIGH+T_LOW -1 ) begin
                scl <= 1'bz;
            end
            else  begin
                scl <= 1'b1;
            end
        end
    end
end

    assign wait_for_sync = (count_ctrl == (SETUP_SCL_START-1)) && (state_master == Ready);
    assign add_sent      = (count      == ADDR_LEN) && (count_ctrl == T_HIGH + T_LOW -1 ) && (state_master == Send_Address);
    assign data_received = (count      == DATA_LEN-1) && (count_ctrl == T_HIGH + T_LOW - 1) && (state_master == Read_Data);
    assign data_sent     = (count      == DATA_LEN-1) && (count_ctrl == T_HIGH + T_LOW - 1) && (state_master == Write_Data);
    assign count_inc     = (count_ctrl == T_HIGH + T_LOW - 1) && (state_master == Send_Address || state_master == Write_Data|| state_master == Read_Data);

endmodule

master_fsm_rtl/fsm_master.v
// Master Controller
module fsm_master #(
    parameter FREQ_DIFF = 4,
    parameter T_LOW     = 6,
    parameter T_HIGH    = 4,
    parameter ADDR_LEN  = 7,
    parameter SETUP_SCL_START = 4,
    parameter SETUP_SDA_START = 2,
    parameter DATA_LEN  = 8
                            )
    (
        input                   clk,
        input                   rst_n,
        input                   start,
        input [ADDR_LEN-1:0]    add_reg,
        input                   R_W,
        input [DATA_LEN-1:0]    data_1,
        input [DATA_LEN-1:0]    data_2,
        input                   ack_3p,
        output                  scl,
        inout                   sda,
        output [3:0]            state_master,
        output                  free
    );


    //wire [3:0] state_master;
    wire [6:0] count_ctrl;
    wire [3:0] count;
    wire       count_inc;
    wire       rst_count_2;
    wire       rst_count;
    wire       wait_for_sync;
    wire       add_sent;
    wire       data_received;
    wire       data_sent;

    scl_generate #(
        .THRESHOLD          (FREQ_DIFF/2    ),
        .T_LOW              (T_LOW          ),
        .T_HIGH             (T_HIGH         ),
        .ADDR_LEN           (ADDR_LEN       ),
        .SETUP_SCL_START    (SETUP_SCL_START),
        .DATA_LEN           (DATA_LEN       )
        ) 
        SCL
        (
            .clk                (clk            ),
            .rst_n              (rst_n          ),
            .state_master       (state_master   ),
            .rst_count          (rst_count      ),
            .count              (count          ),
            .count_ctrl         (count_ctrl     ),
            .scl                (scl            ),
            .wait_for_sync      (wait_for_sync  ),
            .add_sent           (add_sent       ),
            .data_received      (data_received  ),
            .data_sent          (data_sent      ),
            .count_inc          (count_inc      )
        );
    
    sda_generate #(
        .THRESHOLD          (FREQ_DIFF/2    ),
        .ADDR_LEN           (ADDR_LEN       ),
        .SETUP_SDA_START    (SETUP_SDA_START),
        .DATA_LEN           (DATA_LEN       )
        ) SDA(
            .clk                (clk            ),
            .rst_n              (rst_n          ),
            .start              (start          ),
            .scl                (scl            ),
            .count_ctrl         (count_ctrl     ),
            .count              (count          ),
            .wait_for_sync      (wait_for_sync  ),
            .add_sent           (add_sent       ),
            .data_received      (data_received  ),
            .data_sent          (data_sent      ),
            .add_reg            (add_reg        ),
            .R_W                (R_W            ),
            .data_1             (data_1         ),
            .data_2             (data_2         ),
            .ack_3p             (ack_3p         ),
            .sda                (sda            ),
            .rst_count          (rst_count      ),
            .rst_count_2        (rst_count_2    ),
            .state_master       (state_master   ),
            .free               (free           )
        );

    counter COUNTER(
            .clk                (clk            ),
            .rst_n              (rst_n          ),
            .rst_count_2        (rst_count_2    ),
            .count_inc          (count_inc      ),
            .count              (count          )
    );

endmodule

master_fsm_rtl/tb.v
module tb_;

parameter ADDR_LEN = 7;
parameter DATA_LEN = 8;
parameter FREQ_DIFF = 4;
parameter SETUP_SDA_START=2;
parameter SETUP_SCL_START=4;
parameter T_LOW         = 6;
parameter T_HIGH        = 4;
parameter SETUP_SDA     = 3;


reg clk;
reg rst_n;
reg start;
reg [ADDR_LEN-1:0] add_reg;
reg R_W;
reg [DATA_LEN-1:0] data_1;
reg [DATA_LEN-1:0] data_2;
reg                ack_3p;
reg dummy;
wire scl;
wire sda;
wire[3:0] state_master;
wire free;
reg output_value_valid;


fsm_master #(
    .FREQ_DIFF              (FREQ_DIFF),
    .ADDR_LEN               (ADDR_LEN),
    .SETUP_SCL_START        (SETUP_SCL_START),
    .SETUP_SDA_START        (SETUP_SDA_START),
    .DATA_LEN               (DATA_LEN)
) FSM_MASTER_DUT
(
    .clk                (clk        ),
    .rst_n              (rst_n      ),
    .start              (start      ),
    .add_reg            (add_reg    ),
    .R_W                (R_W        ),
    .data_1             (data_1     ),
    .data_2             (data_2     ),
    .ack_3p             (ack_3p     ),
    .scl                (scl        ),
    .sda                (sda        ),
    .state_master       (state_master),
    .free               (free       )
);

assign sda = (output_value_valid==1'b1)? dummy : 8'hZZ;

localparam CLK_PERIOD = 10;
always #(CLK_PERIOD/2) clk=~clk;

initial begin
    clk = 0;
    #5000 $finish;
end

initial begin
    $dumpfile("tb_.vcd");
    $dumpvars(0, tb_);
end

initial begin
    #CLK_PERIOD RST_TEST;
    #CLK_PERIOD START_TEST(7'b1010110, 1);
    
end

task START_TEST(input[ADDR_LEN-1:0] addr, input r_w);
    begin
        wait(free);
        rst_n=1; start=1; data_1 =8'hab; data_2 = 8'hab; R_W=r_w;add_reg=addr; 
        #CLK_PERIOD; 
        start = 0;
        if(free) begin
            $display("ERROR: free HIGH after start..");
            $finish;
        end
        else begin
            $display("Operation Started successfully..");
        end
        wait(state_master == 4'b0110);
        output_value_valid = 1;
        #(T_LOW-SETUP_SDA-1) dummy = 1;
        #(T_LOW+T_HIGH) dummy = 0;
        #(T_LOW+T_HIGH);
        dummy = 1;
        #(T_LOW+T_HIGH);
        dummy = 1;
        #(T_LOW+T_HIGH);
        dummy = 1;
        #(T_LOW+T_HIGH);
        dummy = 0;
        #(T_LOW+T_HIGH);
        dummy = 0;
        #(T_LOW+T_HIGH);
        dummy = 1;
        ack_3p = 1;
        #(T_LOW+T_HIGH);
        output_value_valid = 1'b0;
        //START_TEST_checker;
        //SEND_ADDR_checker(addr);
    end
endtask

task START_TEST_checker;
    begin
        wait(~free);
        if(~sda || ~scl) begin
            $display("ERROR: START_TEST failed");
            $finish;
        end
        #SETUP_SDA_START
        if(sda || ~scl) begin
            $display("ERROR: START_TEST failed");
            $finish;
        end
        #(SETUP_SCL_START-SETUP_SDA_START)
        if(sda || scl) begin
            $display("ERROR: START_TEST failed");
            $finish;
        end
        $display("START condition verified..");
    end
endtask

task SEND_ADDR_checker(input[ADDR_LEN-1:0] addr);
    reg count;
    begin
        count = 0;
        wait(~scl);
        repeat(ADDR_LEN) begin
            wait(scl);
            if(sda != addr[ADDR_LEN-count -1]) begin
                $display("ERROR: Incorrect ADDR sent!");
                //$finish;
            end
            count = count+1;
            wait(~scl);
        end
        $display("ADDR transmitted successfully..");
    end
endtask



task RST_TEST;
    begin
        @(posedge clk)
        rst_n = 1'b0; start=0; add_reg={ADDR_LEN{1'b0}}; R_W=0; data_1={DATA_LEN{1'b0}}; data_2={DATA_LEN{1'b0}};
        wait(CLK_PERIOD);
        if(~free || ~sda || ~scl) begin
            $display("RST_TEST FAILED");
            $finish;
        end else begin
            $display("RST_TEST passed.");
        end
    end

endtask

endmodule
// `default_nettype wire

master_fsm_rtl/tb_.vcd
$date
	Tue Jan 30 15:33:56 2024
$end
$version
	Icarus Verilog
$end
$timescale
	1s
$end
$scope module tb_ $end
$var wire 1 ! free $end
$var wire 1 " scl $end
$var wire 1 # sda $end
$var wire 4 $ state_master [3:0] $end
$var reg 1 % R_W $end
$var reg 1 & ack_3p $end
$var reg 7 ' add_reg [6:0] $end
$var reg 1 ( clk $end
$var reg 8 ) data_1 [7:0] $end
$var reg 8 * data_2 [7:0] $end
$var reg 1 + dummy $end
$var reg 1 , output_value_valid $end
$var reg 1 - rst_n $end
$var reg 1 . start $end
$scope module FSM_MASTER_DUT $end
$var wire 1 / R_W $end
$var wire 1 0 ack_3p $end
$var wire 7 1 add_reg [6:0] $end
$var wire 1 2 add_sent $end
$var wire 1 3 clk $end
$var wire 4 4 count [3:0] $end
$var wire 7 5 count_ctrl [6:0] $end
$var wire 1 6 count_inc $end
$var wire 8 7 data_1 [7:0] $end
$var wire 8 8 data_2 [7:0] $end
$var wire 1 9 data_received $end
$var wire 1 : data_sent $end
$var wire 1 ! free $end
$var wire 1 ; rst_count $end
$var wire 1 < rst_count_2 $end
$var wire 1 = rst_n $end
$var wire 1 " scl $end
$var wire 1 # sda $end
$var wire 1 > start $end
$var wire 4 ? state_master [3:0] $end
$var wire 1 @ wait_for_sync $end
$scope module SCL $end
$var wire 1 2 add_sent $end
$var wire 1 3 clk $end
$var wire 4 A count [3:0] $end
$var wire 1 6 count_inc $end
$var wire 1 9 data_received $end
$var wire 1 : data_sent $end
$var wire 1 ; rst_count $end
$var wire 1 = rst_n $end
$var wire 4 B state_master [3:0] $end
$var wire 1 @ wait_for_sync $end
$var reg 7 C count_ctrl [6:0] $end
$var reg 1 D scl $end
$upscope $end
$scope module SDA $end
$var wire 1 / R_W $end
$var wire 1 0 ack_3p $end
$var wire 7 E add_reg [6:0] $end
$var wire 1 2 add_sent $end
$var wire 1 3 clk $end
$var wire 4 F count [3:0] $end
$var wire 7 G count_ctrl [6:0] $end
$var wire 8 H data_1 [7:0] $end
$var wire 8 I data_2 [7:0] $end
$var wire 1 9 data_received $end
$var wire 1 : data_sent $end
$var wire 1 ! free $end
$var wire 1 ; rst_count $end
$var wire 1 < rst_count_2 $end
$var wire 1 = rst_n $end
$var wire 1 " scl $end
$var wire 1 # sda $end
$var wire 1 > start $end
$var wire 4 J state_master [3:0] $end
$var wire 1 @ wait_for_sync $end
$var reg 1 K ack_reg $end
$var reg 4 L current_state [3:0] $end
$var reg 4 M next_state [3:0] $end
$var reg 2 N no_of_data_sent [1:0] $end
$var reg 1 O sda_reg $end
$upscope $end
$scope module COUNTER $end
$var wire 1 3 clk $end
$var wire 1 6 count_inc $end
$var wire 1 < rst_count_2 $end
$var wire 1 = rst_n $end
$var reg 4 P count [3:0] $end
$upscope $end
$upscope $end
$scope task RST_TEST $end
$upscope $end
$scope task SEND_ADDR_checker $end
$var reg 7 Q addr [6:0] $end
$var reg 1 R count $end
$upscope $end
$scope task START_TEST $end
$var reg 7 S addr [6:0] $end
$var reg 1 T r_w $end
$upscope $end
$scope task START_TEST_checker $end
$upscope $end
$upscope $end
$enddefinitions $end
#0
$dumpvars
xT
bx S
xR
bx Q
bx P
xO
bx N
bx M
bx L
xK
bx J
bx I
bx H
bx G
bx F
bx E
xD
bx C
bx B
bx A
x@
bx ?
x>
x=
x<
x;
x:
x9
bx 8
bx 7
x6
bx 5
bx 4
03
x2
bx 1
x0
x/
x.
x-
x,
x+
bx *
bx )
0(
bx '
x&
x%
bx $
x#
x"
x!
$end
#5
1(
13
#10
0(
03
#15
1;
0<
0:
09
02
0@
06
b0 M
b0 P
b0 4
b0 A
b0 F
b0 N
0K
1O
b0 L
1!
b0 $
b0 ?
b0 B
b0 J
1D
1"
b0 C
b0 5
b0 G
b0 *
b0 8
b0 I
b0 )
b0 7
b0 H
0%
0/
b0 '
b0 1
b0 E
0.
0>
0-
0=
1(
13
#20
0(
03
#25
0;
b1 L
0!
b1 $
b1 ?
b1 B
b1 J
b1 M
1(
13
b1010110 '
b1010110 1
b1010110 E
1%
1/
b10101011 *
b10101011 8
b10101011 I
b10101011 )
b10101011 7
b10101011 H
1.
1>
1-
1=
1T
b1010110 S
#30
0(
03
#35
b1 C
b1 5
b1 G
1(
13
0.
0>
#40
0(
03
#45
b10 C
b10 5
b10 G
0O
1(
13
#50
0(
03
#55
1;
1<
b10 M
1@
b11 C
b11 5
b11 G
1(
13
#60
0(
03
#65
0;
0<
0@
b0 C
b0 5
b0 G
0D
0"
b10 L
b10 $
b10 ?
b10 B
b10 J
1(
13
#70
0(
03
#75
b1 C
b1 5
b1 G
1(
13
#80
0(
03
#85
b10 C
b10 5
b10 G
1(
13
#90
0(
03
#95
1O
b11 C
b11 5
b11 G
1(
13
#100
0(
03
#105
b100 C
b100 5
b100 G
1(
13
#110
0(
03
#115
b101 C
b101 5
b101 G
1(
13
#120
0(
03
#125
b110 C
b110 5
b110 G
1D
1"
1(
13
#130
0(
03
#135
b111 C
b111 5
b111 G
1(
13
#140
0(
03
#145
b1000 C
b1000 5
b1000 G
1(
13
#150
0(
03
#155
16
b1001 C
b1001 5
b1001 G
1(
13
#160
0(
03
#165
06
b0 C
b0 5
b0 G
0D
0"
b1 P
b1 4
b1 A
b1 F
1(
13
#170
0(
03
#175
b1 C
b1 5
b1 G
1(
13
#180
0(
03
#185
b10 C
b10 5
b10 G
1(
13
#190
0(
03
#195
0O
b11 C
b11 5
b11 G
1(
13
#200
0(
03
#205
b100 C
b100 5
b100 G
1(
13
#210
0(
03
#215
b101 C
b101 5
b101 G
1(
13
#220
0(
03
#225
b110 C
b110 5
b110 G
1D
1"
1(
13
#230
0(
03
#235
b111 C
b111 5
b111 G
1(
13
#240
0(
03
#245
b1000 C
b1000 5
b1000 G
1(
13
#250
0(
03
#255
16
b1001 C
b1001 5
b1001 G
1(
13
#260
0(
03
#265
06
b0 C
b0 5
b0 G
0D
0"
b10 P
b10 4
b10 A
b10 F
1(
13
#270
0(
03
#275
b1 C
b1 5
b1 G
1(
13
#280
0(
03
#285
b10 C
b10 5
b10 G
1(
13
#290
0(
03
#295
1O
b11 C
b11 5
b11 G
1(
13
#300
0(
03
#305
b100 C
b100 5
b100 G
1(
13
#310
0(
03
#315
b101 C
b101 5
b101 G
1(
13
#320
0(
03
#325
b110 C
b110 5
b110 G
1D
1"
1(
13
#330
0(
03
#335
b111 C
b111 5
b111 G
1(
13
#340
0(
03
#345
b1000 C
b1000 5
b1000 G
1(
13
#350
0(
03
#355
16
b1001 C
b1001 5
b1001 G
1(
13
#360
0(
03
#365
06
b0 C
b0 5
b0 G
0D
0"
b11 P
b11 4
b11 A
b11 F
1(
13
#370
0(
03
#375
b1 C
b1 5
b1 G
1(
13
#380
0(
03
#385
b10 C
b10 5
b10 G
1(
13
#390
0(
03
#395
0O
b11 C
b11 5
b11 G
1(
13
#400
0(
03
#405
b100 C
b100 5
b100 G
1(
13
#410
0(
03
#415
b101 C
b101 5
b101 G
1(
13
#420
0(
03
#425
b110 C
b110 5
b110 G
1D
1"
1(
13
#430
0(
03
#435
b111 C
b111 5
b111 G
1(
13
#440
0(
03
#445
b1000 C
b1000 5
b1000 G
1(
13
#450
0(
03
#455
16
b1001 C
b1001 5
b1001 G
1(
13
#460
0(
03
#465
06
b0 C
b0 5
b0 G
0D
0"
b100 P
b100 4
b100 A
b100 F
1(
13
#470
0(
03
#475
b1 C
b1 5
b1 G
1(
13
#480
0(
03
#485
b10 C
b10 5
b10 G
1(
13
#490
0(
03
#495
1O
b11 C
b11 5
b11 G
1(
13
#500
0(
03
#505
b100 C
b100 5
b100 G
1(
13
#510
0(
03
#515
b101 C
b101 5
b101 G
1(
13
#520
0(
03
#525
b110 C
b110 5
b110 G
1D
1"
1(
13
#530
0(
03
#535
b111 C
b111 5
b111 G
1(
13
#540
0(
03
#545
b1000 C
b1000 5
b1000 G
1(
13
#550
0(
03
#555
16
b1001 C
b1001 5
b1001 G
1(
13
#560
0(
03
#565
06
b0 C
b0 5
b0 G
0D
0"
b101 P
b101 4
b101 A
b101 F
1(
13
#570
0(
03
#575
b1 C
b1 5
b1 G
1(
13
#580
0(
03
#585
b10 C
b10 5
b10 G
1(
13
#590
0(
03
#595
b11 C
b11 5
b11 G
1(
13
#600
0(
03
#605
b100 C
b100 5
b100 G
1(
13
#610
0(
03
#615
b101 C
b101 5
b101 G
1(
13
#620
0(
03
#625
b110 C
b110 5
b110 G
1D
1"
1(
13
#630
0(
03
#635
b111 C
b111 5
b111 G
1(
13
#640
0(
03
#645
b1000 C
b1000 5
b1000 G
1(
13
#650
0(
03
#655
16
b1001 C
b1001 5
b1001 G
1(
13
#660
0(
03
#665
06
b0 C
b0 5
b0 G
0D
0"
b110 P
b110 4
b110 A
b110 F
1(
13
#670
0(
03
#675
b1 C
b1 5
b1 G
1(
13
#680
0(
03
#685
b10 C
b10 5
b10 G
1(
13
#690
0(
03
#695
0O
b11 C
b11 5
b11 G
1(
13
#700
0(
03
#705
b100 C
b100 5
b100 G
1(
13
#710
0(
03
#715
b101 C
b101 5
b101 G
1(
13
#720
0(
03
#725
b110 C
b110 5
b110 G
1D
1"
1(
13
#730
0(
03
#735
b111 C
b111 5
b111 G
1(
13
#740
0(
03
#745
b1000 C
b1000 5
b1000 G
1(
13
#750
0(
03
#755
16
b1001 C
b1001 5
b1001 G
1(
13
#760
0(
03
#765
06
b0 C
b0 5
b0 G
0D
0"
b111 P
b111 4
b111 A
b111 F
1(
13
#770
0(
03
#775
b1 C
b1 5
b1 G
1(
13
#780
0(
03
#785
b10 C
b10 5
b10 G
1(
13
#790
0(
03
#795
1O
b11 C
b11 5
b11 G
1(
13
#800
0(
03
#805
b100 C
b100 5
b100 G
1(
13
#810
0(
03
#815
b101 C
b101 5
b101 G
1(
13
#820
0(
03
#825
b110 C
b110 5
b110 G
1D
1"
1(
13
#830
0(
03
#835
b111 C
b111 5
b111 G
1(
13
#840
0(
03
#845
b1000 C
b1000 5
b1000 G
1(
13
#850
0(
03
#855
1;
1<
b1100 M
12
16
b1001 C
b1001 5
b1001 G
1(
13
#860
0(
03
#865
0;
0<
06
02
b0 C
b0 5
b0 G
0D
0"
b1100 L
b1100 $
b1100 ?
b1100 B
b1100 J
b0 P
b0 4
b0 A
b0 F
1(
13
#870
0(
03
#875
b1 C
b1 5
b1 G
1(
13
#880
0(
03
#885
b10 C
b10 5
b10 G
1(
13
#890
0(
03
#895
zO
b11 C
b11 5
b11 G
1(
13
#900
0(
03
#905
b100 C
b100 5
b100 G
1(
13
#910
0(
03
#915
b101 C
b101 5
b101 G
1(
13
#920
0(
03
#925
b110 C
b110 5
b110 G
1D
1"
1(
13
#930
0(
03
#935
b111 C
b111 5
b111 G
1(
13
#940
0(
03
#945
b1000 C
b1000 5
b1000 G
1(
13
#950
0(
03
#955
b110 M
b1001 C
b1001 5
b1001 G
1(
13
#960
0(
03
#965
1,
b0 C
b0 5
b0 G
0D
0"
b110 L
b110 $
b110 ?
b110 B
b110 J
1(
13
#967
1#
1+
#970
0(
03
#975
b1 C
b1 5
b1 G
1(
13
#977
0#
0+
#980
0(
03
#985
b10 C
b10 5
b10 G
1(
13
#987
1#
1+
#990
0(
03
#995
b11 C
b11 5
b11 G
1(
13
#1000
0(
03
#1005
b100 C
b100 5
b100 G
1(
13
#1010
0(
03
#1015
b101 C
b101 5
b101 G
1(
13
#1017
0#
0+
#1020
0(
03
#1025
b110 C
b110 5
b110 G
1D
1"
1(
13
#1030
0(
03
#1035
b111 C
b111 5
b111 G
1(
13
#1037
1#
1&
10
1+
#1040
0(
03
#1045
b1000 C
b1000 5
b1000 G
1(
13
#1047
z#
0,
#1050
0(
03
#1055
16
b1001 C
b1001 5
b1001 G
1(
13
#1060
0(
03
#1065
06
b0 C
b0 5
b0 G
0D
0"
b1 P
b1 4
b1 A
b1 F
1(
13
#1070
0(
03
#1075
b1 C
b1 5
b1 G
1(
13
#1080
0(
03
#1085
b10 C
b10 5
b10 G
1(
13
#1090
0(
03
#1095
b11 C
b11 5
b11 G
1(
13
#1100
0(
03
#1105
b100 C
b100 5
b100 G
1(
13
#1110
0(
03
#1115
b101 C
b101 5
b101 G
1(
13
#1120
0(
03
#1125
b110 C
b110 5
b110 G
1D
1"
1(
13
#1130
0(
03
#1135
b111 C
b111 5
b111 G
1(
13
#1140
0(
03
#1145
b1000 C
b1000 5
b1000 G
1(
13
#1150
0(
03
#1155
16
b1001 C
b1001 5
b1001 G
1(
13
#1160
0(
03
#1165
06
b0 C
b0 5
b0 G
0D
0"
b10 P
b10 4
b10 A
b10 F
1(
13
#1170
0(
03
#1175
b1 C
b1 5
b1 G
1(
13
#1180
0(
03
#1185
b10 C
b10 5
b10 G
1(
13
#1190
0(
03
#1195
b11 C
b11 5
b11 G
1(
13
#1200
0(
03
#1205
b100 C
b100 5
b100 G
1(
13
#1210
0(
03
#1215
b101 C
b101 5
b101 G
1(
13
#1220
0(
03
#1225
b110 C
b110 5
b110 G
1D
1"
1(
13
#1230
0(
03
#1235
b111 C
b111 5
b111 G
1(
13
#1240
0(
03
#1245
b1000 C
b1000 5
b1000 G
1(
13
#1250
0(
03
#1255
16
b1001 C
b1001 5
b1001 G
1(
13
#1260
0(
03
#1265
06
b0 C
b0 5
b0 G
0D
0"
b11 P
b11 4
b11 A
b11 F
1(
13
#1270
0(
03
#1275
b1 C
b1 5
b1 G
1(
13
#1280
0(
03
#1285
b10 C
b10 5
b10 G
1(
13
#1290
0(
03
#1295
b11 C
b11 5
b11 G
1(
13
#1300
0(
03
#1305
b100 C
b100 5
b100 G
1(
13
#1310
0(
03
#1315
b101 C
b101 5
b101 G
1(
13
#1320
0(
03
#1325
b110 C
b110 5
b110 G
1D
1"
1(
13
#1330
0(
03
#1335
b111 C
b111 5
b111 G
1(
13
#1340
0(
03
#1345
b1000 C
b1000 5
b1000 G
1(
13
#1350
0(
03
#1355
16
b1001 C
b1001 5
b1001 G
1(
13
#1360
0(
03
#1365
06
b0 C
b0 5
b0 G
0D
0"
b100 P
b100 4
b100 A
b100 F
1(
13
#1370
0(
03
#1375
b1 C
b1 5
b1 G
1(
13
#1380
0(
03
#1385
b10 C
b10 5
b10 G
1(
13
#1390
0(
03
