master_fsm_rtl/sda_gen.v
module sda_generate #(
    parameter THRESHOLD         = 2,
    parameter ADDR_LEN          = 7,
    parameter DATA_LEN          = 8,
    parameter SETUP_SDA_START   = 2
    )(
    input                       clk,
    input                       rst_n,
    input                       start,
    input                       scl,
    input [6:0]                 count_ctrl,
    input                       wait_for_sync,
    input                       add_sent,
    input                       data_received,
    input                       data_sent,
    input [ADDR_LEN-1:0]        add_reg,
    input                       R_W,
    input [DATA_LEN-1:0]        data_1,
    input [DATA_LEN-1:0]        data_2,
    inout                       sda,
    output                      rst_count,
    output [3:0]                state_master,
    output                      free
                                           );


    reg [3:0]           current_state;
    reg [3:0]           next_state;
    reg                 sda_reg;
    reg [2:0]           no_of_data_rec;
    reg [2:0]           no_of_data_sent; //See if one can be used
    reg [DATA_LEN-1:0]  data_mem [1:0];

    parameter Idle            = 4'b0000;
    parameter Ready           = 4'b0001;
    parameter Send_Address    = 4'b0010;
    parameter Write_Data      = 4'b0011;
    parameter Output_Data     = 4'b0100;
    parameter Check_ACK       = 4'b0101;
    parameter Read_Data       = 4'b0110;
    parameter Store_Data      = 4'b0111;
    parameter Check_for_Valid = 4'b1000;
    parameter Send_ACK        = 4'b1001;
    parameter Send_NACK       = 4'b1010;
    parameter Stop            = 4'b1011;

//always block for curr_state
    always @(posedge clk or negedge rst_n)
        begin
            if(~rst_n) begin
                current_state <= Idle;
            end else begin
                current_state <= next_state;
            end

        end
    //always block for sda_reg
    always @(posedge clk or negedge rst_n)
    begin
        if(~rst_n) begin
            sda_reg <= 1'b1;
        end
     else begin
        case (current_state) 
        Ready : begin
            if(count_ctrl == (SETUP_SDA_START -1)) begin
                sda_reg <= 1'b0;
            end
        end

     endcase 

     end

        begin
            // if(current_state == Ready)
            // begin
            //     if(count_ctrl == 2*THRESHOLD ) sda_reg = 0;
            // end

            if(current_state == Send_Address)
            begin
                if(~scl && ~add_sent && count_ctrl/(2*THRESHOLD) <= 6) sda_reg = add_reg[6 - count_ctrl/(2*THRESHOLD)];
                else if(~scl && add_sent && R_W)
                begin
                    sda_reg    <= R_W;
                end
                else if(~scl && add_sent && ~R_W)
                begin
                    sda_reg    <= R_W;
                end
            end

            else if(current_state == Read_Data)
            begin
                sda_reg <= 1'bz;
            end

            else if(current_state == Store_Data)
            begin
                sda_reg <= 1'bz;
                if(~scl && ~data_received && count_ctrl/(2*THRESHOLD) <= 7) data_mem[no_of_data_rec][7 - count_ctrl/(2*THRESHOLD)] = sda;
            end

            //else if(current_state == Check_for_Valid)
            //begin
            //    if(data_mem[no_of_data_rec] != 8'hFF) next_state <= Send_ACK;
            //    else next_state <= Send_NACK;
            //end

            else if(current_state == Send_ACK)
            begin
                if(~scl) 
                begin
                    sda_reg <= 1'b0;
                end
            end

            //else if(current_state == Send_NACK)
            //begin
            //    next_state <= Stop;
            //end

            else if(current_state == Write_Data)
            begin
                sda_reg <= 1'bz;
            end

            else if(current_state == Output_Data)
            begin
                if(~scl && ~data_sent && count_ctrl/(2*THRESHOLD) <= 7) sda_reg <= data_mem[no_of_data_sent][7 - count_ctrl/(2*THRESHOLD)];
            end

            else if(current_state == Check_ACK)
            begin
                sda_reg <= 1'bz;
            end

            else if(current_state == Stop)
            begin
                if(count_ctrl == 4*THRESHOLD) 
                begin
                    sda_reg    <= 1'b1;
                end
            end
        end
    end

//Combo Logic for next_state
always @(*) begin
    next_state = current_state;

    case(current_state)
        Idle : begin
            if(start) begin
                next_state = Ready;
            end
        end
        // Ready: begin
            
        // end
    endcase

end


always @(*) 
begin
    next_state = current_state;
    
        if(current_state == Idle)
        begin
            if(start)
            begin
                next_state = Ready;
            end
        end

        else if(current_state == Ready)
        begin
            if(count_ctrl == 2*THRESHOLD) sda_reg = 0;
            else if(wait_for_sync)
            begin
                next_state  = Send_Address;
            end
            else next_state = Ready;
        end

        else if(current_state == Send_Address)
        begin
            if(~scl && add_sent && R_W)
            begin
                next_state = Read_Data;
            end
            else if(~scl && add_sent && ~R_W)
            begin
                next_state = Write_Data;
            end
        end

        else if(current_state == Read_Data)
        begin
            if(~scl)
            begin
                if(sda) next_state = Store_Data;
                else    next_state = Stop;
            end
        end

        else if(current_state == Store_Data)
        begin
            if(data_received)
            begin
                next_state = Check_for_Valid;
            end
        end

        else if(current_state == Check_for_Valid)
        begin
            if(data_mem[no_of_data_rec] != 8'hFF) next_state = Send_ACK;
            else next_state = Send_NACK;
        end

        else if(current_state == Send_ACK)
        begin
            if(~scl) 
            begin
                no_of_data_rec   <= no_of_data_rec + 1'b1;
            end
            if(no_of_data_rec < 2) next_state = Store_Data;
            else next_state <= Stop;
        end

        else if(current_state == Send_NACK)
        begin
            next_state = Stop;
        end

        else if(current_state == Write_Data)
        begin
            if(sda) next_state = Output_Data;
            else next_state    = Write_Data;
        end

        else if(current_state == Output_Data)
        begin
            if(data_sent)
            begin
                next_state = Check_ACK;
            end
        end

        else if(current_state == Check_ACK)
        begin
            if(~scl)
            begin
                no_of_data_sent <= no_of_data_sent + 1'b1;
                if(sda && no_of_data_sent < 2) next_state <= Output_Data;
                else if(~sda) next_state = Stop;
            end
        end

        else if(current_state == Stop)
        begin
            if(count_ctrl == 4*THRESHOLD) 
            begin
                next_state = Idle;
            end
        end
end
    
    assign state_master = current_state;
    assign free = (current_state == Idle);
    assign rst_count = (current_state == Idle) || wait_for_sync || free || add_sent || (current_state == Read_Data) || 
                       (current_state == Write_Data) || data_received || (current_state == Check_for_Valid) ||
                       (current_state == Send_ACK) || (current_state == Check_ACK);
    assign sda = sda_reg;

endmodule

master_fsm_rtl/scl_gen.v
module scl_generate #(
    parameter THRESHOLD     = 2,
    parameter T_LOW         = 6,
    parameter T_HIGH        = 4,  //SCL is LOW for T_LOW*CLK_PERIOD and HIGH for T_HIGH*CLK_PERIOD
    parameter ADDR_LEN      = 7,
    parameter SETUP_SCL_START = 4,
    parameter DATA_LEN      = 8
)(
    input              clk,
    input              rst_n,
    input [3:0]        state_master,
    input              rst_count,
    output reg [6:0]   count_ctrl,
    output reg         scl,
    output             wait_for_sync,
    output             add_sent,
    output             data_received,
    output             data_sent
);

    

    parameter Idle            = 4'b0000;
    parameter Ready           = 4'b0001;
    parameter Send_Address    = 4'b0010;
    parameter Write_Data      = 4'b0011;
    parameter Output_Data     = 4'b0100;
    parameter Check_ACK       = 4'b0101;
    parameter Read_Data       = 4'b0110;
    parameter Store_Data      = 4'b0111;
    parameter Check_for_Valid = 4'b1000;
    parameter Send_ACK        = 4'b1001;
    parameter Send_NACK       = 4'b1010;
    parameter Stop            = 4'b1011;

    
    // always @(posedge clk)
    // begin
    //     if(rst_count) count_ctrl = 0;
    //     else
    //     begin
    //         count_ctrl = count_ctrl + 1'b1;

    //         if(state_master == Ready)
    //         begin
    //             if(count_ctrl == 4*THRESHOLD) 
    //             begin
    //                 scl   = 1'b0;
    //                 count_ctrl = 0;
    //             end
    //             else 
    //             begin
    //                 scl   = 1'b1;
    //             end
    //         end
    //         else if(state_master != Ready && state_master != Stop)
    //         begin
    //             if(count_ctrl == THRESHOLD)
    //             begin
    //                 scl   = ~scl;
    //                 count_ctrl = 0;
    //             end
    //         end
    //         else if(state_master == Stop)
    //         begin
    //             if(count_ctrl == 2*THRESHOLD)
    //             begin
    //                 scl = 1'b1;
    //             end
    //         end
    //     end
    // end 

//always block for count_ctrl
always @(posedge clk or negedge rst_n) begin
    if(~rst_n) begin
        count_ctrl <= 0;
    end else begin
        if (rst_count) begin
            count_ctrl <= 0;
        end else begin
            if (state_master == Ready) begin
                if(count_ctrl == (SETUP_SCL_START-1)) begin
                    count_ctrl <= 0;
                end else begin
                    count_ctrl <= count_ctrl + 1;
                end
            end else if(state_master != Ready && state_master != Stop) begin
                if (count_ctrl == (T_LOW+T_HIGH-1)) begin
                    count_ctrl <= 0;
                end else begin
                    count_ctrl <= count_ctrl + 1; 
                end
            end else begin //what happens to cnt cntrl in other states?
                count_ctrl <= count_ctrl + 1;
            end
        end
    end
end

//always block for scl
always @(posedge clk or negedge rst_n) begin
    if (~rst_n) begin
        scl <= 1; //check
    end else begin
        if (state_master == Ready) begin
            if (count_ctrl == SETUP_SCL_START-1) begin
                scl <= 1'b0;
            end
        end else if(state_master != Ready && state_master != Stop && state_master != Idle) begin
            if(count_ctrl < T_LOW) begin
                scl <= 1'b0;
            end else begin
                scl <= 1'b1;
            end
        end else if(state_master == Stop) begin
            if(count_ctrl == 2*THRESHOLD) begin
                scl <= 1'b1;
            end
        end
    end
end

    assign wait_for_sync = (count_ctrl == 4*THRESHOLD) && (state_master == Ready);
    assign add_sent      = (count_ctrl == 2*(ADDR_LEN-1)*THRESHOLD) && (state_master == Send_Address);
    assign data_received = (count_ctrl == 2*DATA_LEN*THRESHOLD) && (state_master == Store_Data);
    assign data_sent     = (count_ctrl == 2*DATA_LEN*THRESHOLD) && (state_master == Output_Data);

endmodule

master_fsm_rtl/fsm_master.v
module fsm_master #(
    parameter FREQ_DIFF = 4,
    parameter T_LOW     = 6,
    parameter T_HIGH    = 4,
    parameter ADDR_LEN  = 7,
    parameter DATA_LEN  = 8
                            )
    (
        input                   clk,
        input                   rst_n,
        input                   start,
        input [ADDR_LEN-1:0]    add_reg,
        input                   R_W,
        input [DATA_LEN-1:0]    data_1,
        input [DATA_LEN-1:0]    data_2,
        output                  scl,
        inout                   sda,
        output                  free
    );


    wire [3:0] state_master;
    wire [6:0] count_ctrl;
    wire       rst_count;
    wire       wait_for_sync;
    wire       add_sent;
    wire       data_received;
    wire       data_sent;

    scl_generate #(
        .THRESHOLD          (FREQ_DIFF/2    ),
        .T_LOW              (T_LOW          ),
        .T_HIGH             (T_HIGH         ),
        .ADDR_LEN           (ADDR_LEN       ),
        .DATA_LEN           (DATA_LEN       )
        ) 
        SCL
        (
            .clk                (clk            ),
            .rst_n              (rst_n          ),
            .state_master       (state_master   ),
            .rst_count          (rst_count      ),
            .count_ctrl         (count_ctrl     ),
            .scl                (scl            ),
            .wait_for_sync      (wait_for_sync  ),
            .add_sent           (add_sent       ),
            .data_received      (data_received  ),
            .data_sent          (data_sent      )
        );
    
    sda_generate #(
        .THRESHOLD          (FREQ_DIFF/2    ),
        .ADDR_LEN           (ADDR_LEN       ),
        .DATA_LEN           (DATA_LEN       )
        ) SDA(
            .clk                (clk            ),
            .rst_n              (rst_n          ),
            .start              (start          ),
            .scl                (scl            ),
            .count_ctrl         (count_ctrl     ),
            .wait_for_sync      (wait_for_sync  ),
            .add_sent           (add_sent       ),
            .data_received      (data_received  ),
            .data_sent          (data_sent      ),
            .add_reg            (add_reg        ),
            .R_W                (R_W            ),
            .data_1             (data_1         ),
            .data_2             (data_2         ),
            .sda                (sda            ),
            .rst_count          (rst_count      ),
            .state_master       (state_master   ),
            .free               (free           )
        );

endmodule

master_fsm_rtl/tb.v
module tb_;

parameter ADDR_LEN = 7;
parameter DATA_LEN = 8;
parameter FREQ_DIFF = 4;

reg clk;
reg rst_n;
reg start;
reg [ADDR_LEN-1:0] add_reg;
reg R_W;
reg [DATA_LEN-1:0] data_1;
reg [DATA_LEN-1:0] data_2;
wire scl;
wire sda;
wire free;


fsm_master #(
    .FREQ_DIFF(FREQ_DIFF),
    .ADDR_LEN(ADDR_LEN),
    .DATA_LEN(DATA_LEN)
) FSM_MASTER_DUT
(
    .clk                (clk        ),
    .rst_n              (rst_n      ),
    .start              (start      ),
    .add_reg            (add_reg    ),
    .R_W                (R_W        ),
    .data_1             (data_1     ),
    .data_2             (data_2     ),
    .scl                (scl        ),
    .sda                (sda        ),
    .free               (free       )
);

localparam CLK_PERIOD = 10;
always #(CLK_PERIOD/2) clk=~clk;

initial begin
    clk = 0;
    #5000 $finish;
end

initial begin
    $dumpfile("tb_.vcd");
    $dumpvars(0, tb_);
end

initial begin
    #CLK_PERIOD rst_n=1; start=0; add_reg={ADDR_LEN{1'b0}}; R_W=0; data_1={DATA_LEN{1'b0}}; data_2={DATA_LEN{1'b0}};
    #CLK_PERIOD rst_n=0;
    #CLK_PERIOD rst_n=1;
    #CLK_PERIOD start=1; add_reg=7'b1010110; data_1 = 8'hab ; data_2 = 8'hef;
end

endmodule
`default_nettype wire

master_fsm_rtl/tb_.vcd
$date
	Wed Jan 24 16:06:21 2024
$end
$version
	Icarus Verilog
$end
$timescale
	1s
$end
$scope module tb_ $end
$var wire 1 ! sda $end
$var wire 1 " scl $end
$var wire 1 # free $end
$var reg 1 $ R_W $end
$var reg 7 % add_reg [6:0] $end
$var reg 1 & clk $end
$var reg 8 ' data_1 [7:0] $end
$var reg 8 ( data_2 [7:0] $end
$var reg 1 ) rst_n $end
$var reg 1 * start $end
$scope module FSM_MASTER_DUT $end
$var wire 1 $ R_W $end
$var wire 7 + add_reg [6:0] $end
$var wire 1 & clk $end
$var wire 8 , data_1 [7:0] $end
$var wire 8 - data_2 [7:0] $end
$var wire 1 ) rst_n $end
$var wire 1 * start $end
$var wire 1 . wait_for_sync $end
$var wire 4 / state_master [3:0] $end
$var wire 1 ! sda $end
$var wire 1 " scl $end
$var wire 1 0 rst_count $end
$var wire 1 # free $end
$var wire 1 1 data_sent $end
$var wire 1 2 data_received $end
$var wire 7 3 count_ctrl [6:0] $end
$var wire 1 4 add_sent $end
$scope module SCL $end
$var wire 1 4 add_sent $end
$var wire 1 & clk $end
$var wire 1 2 data_received $end
$var wire 1 1 data_sent $end
$var wire 1 ) rst_n $end
$var wire 1 . wait_for_sync $end
$var wire 4 5 state_master [3:0] $end
$var wire 1 0 rst_count $end
$var reg 7 6 count_ctrl [6:0] $end
$var reg 1 " scl $end
$upscope $end
$scope module SDA $end
$var wire 1 $ R_W $end
$var wire 7 7 add_reg [6:0] $end
$var wire 1 4 add_sent $end
$var wire 1 & clk $end
$var wire 7 8 count_ctrl [6:0] $end
$var wire 8 9 data_1 [7:0] $end
$var wire 8 : data_2 [7:0] $end
$var wire 1 2 data_received $end
$var wire 1 1 data_sent $end
$var wire 1 0 rst_count $end
$var wire 1 ) rst_n $end
$var wire 1 " scl $end
$var wire 1 ! sda $end
$var wire 1 * start $end
$var wire 4 ; state_master [3:0] $end
$var wire 1 . wait_for_sync $end
$var wire 1 # free $end
$var reg 4 < current_state [3:0] $end
$var reg 4 = next_state [3:0] $end
$var reg 3 > no_of_data_rec [2:0] $end
$var reg 3 ? no_of_data_sent [2:0] $end
$var reg 1 @ sda_reg $end
$upscope $end
$upscope $end
$upscope $end
$enddefinitions $end
#0
$dumpvars
x@
bx ?
bx >
bx =
bx <
bx ;
bx :
bx 9
bx 8
bx 7
bx 6
bx 5
x4
bx 3
x2
x1
x0
bx /
x.
bx -
bx ,
bx +
x*
x)
bx (
bx '
0&
bx %
x$
x#
x"
x!
$end
#5
1&
#10
0&
b0 (
b0 -
b0 :
b0 '
b0 ,
b0 9
0$
b0 %
b0 +
b0 7
0*
1)
#15
1&
#20
10
01
02
04
0.
b0 =
b0 3
b0 6
b0 8
1"
1#
b0 /
b0 5
b0 ;
b0 <
1!
1@
0&
0)
#25
1&
#30
0&
1)
#35
1&
#40
b1 =
0&
b1010110 %
b1010110 +
b1010110 7
1*
#45
00
0#
b1 /
b1 5
b1 ;
b1 <
1&
#50
0&
#55
b1 3
b1 6
b1 8
1&
#60
0&
#65
0!
0@
b10 3
b10 6
b10 8
1&
#70
0&
#75
b11 3
b11 6
b11 8
1&
#80
0&
#85
0"
b0 3
b0 6
b0 8
1&
#90
0&
#95
b1 3
b1 6
b1 8
1&
#100
0&
#105
b10 3
b10 6
b10 8
1&
#110
0&
#115
b11 3
b11 6
b11 8
1&
#120
0&
#125
b0 3
b0 6
b0 8
1&
#130
0&
#135
b1 3
b1 6
b1 8
1&
#140
0&
#145
b10 3
b10 6
b10 8
1&
#150
0&
#155
b11 3
b11 6
b11 8
1&
#160
0&
#165
b0 3
b0 6
b0 8
1&
#170
0&
#175
b1 3
b1 6
b1 8
1&
#180
0&
#185
b10 3
b10 6
b10 8
1&
#190
0&
#195
b11 3
b11 6
b11 8
1&
#200
0&
#205
b0 3
b0 6
b0 8
1&
#210
0&
#215
b1 3
b1 6
b1 8
1&
#220
0&
#225
b10 3
b10 6
b10 8
1&
#230
0&
#235
b11 3
b11 6
b11 8
1&
#240
0&
#245
b0 3
b0 6
b0 8
1&
#250
0&
#255
b1 3
b1 6
b1 8
1&
#260
0&
#265
b10 3
b10 6
b10 8
1&
#270
0&
#275
b11 3
b11 6
b11 8
1&
#280
0&
#285
b0 3
b0 6
b0 8
1&
#290
0&
#295
b1 3
b1 6
b1 8
1&
#300
0&
#305
b10 3
b10 6
b10 8
1&
#310
0&
#315
b11 3
b11 6
b11 8
1&
#320
0&
#325
b0 3
b0 6
b0 8
1&
#330
0&
#335
b1 3
b1 6
b1 8
1&
#340
0&
#345
b10 3
b10 6
b10 8
1&
#350
0&
#355
b11 3
b11 6
b11 8
1&
#360
0&
#365
b0 3
b0 6
b0 8
1&
#370
0&
#375
b1 3
b1 6
b1 8
1&
#380
0&
#385
b10 3
b10 6
b10 8
1&
#390
0&
#395
b11 3
b11 6
b11 8
1&
#400
0&
#405
b0 3
b0 6
b0 8
1&
#410
0&
#415
b1 3
b1 6
b1 8
1&
#420
0&
#425
b10 3
b10 6
b10 8
1&
#430
0&
#435
b11 3
b11 6
b11 8
1&
#440
0&
#445
b0 3
b0 6
b0 8
1&
#450
0&
#455
b1 3
b1 6
b1 8
1&
#460
0&
#465
b10 3
b10 6
b10 8
1&
#470
0&
#475
b11 3
b11 6
b11 8
1&
#480
0&
#485
b0 3
b0 6
b0 8
1&
#490
0&
#495
b1 3
b1 6
b1 8
1&
#500
0&
#505
b10 3
b10 6
b10 8
1&
#510
0&
#515
b11 3
b11 6
b11 8
1&
#520
0&
#525
b0 3
b0 6
b0 8
1&
#530
0&
#535
b1 3
b1 6
b1 8
1&
#540
0&
#545
b10 3
b10 6
b10 8
1&
#550
0&
#555
b11 3
b11 6
b11 8
1&
#560
0&
#565
b0 3
b0 6
b0 8
1&
#570
0&
#575
b1 3
b1 6
b1 8
1&
#580
0&
#585
b10 3
b10 6
b10 8
1&
#590
0&
#595
b11 3
b11 6
b11 8
1&
#600
0&
#605
b0 3
b0 6
b0 8
1&
#610
0&
#615
b1 3
b1 6
b1 8
1&
#620
0&
#625
b10 3
b10 6
b10 8
1&
#630
0&
#635
b11 3
b11 6
b11 8
1&
#640
0&
#645
b0 3
b0 6
b0 8
1&
#650
0&
#655
b1 3
b1 6
b1 8
1&
#660
0&
#665
b10 3
b10 6
b10 8
1&
#670
0&
#675
b11 3
b11 6
b11 8
1&
#680
0&
#685
b0 3
b0 6
b0 8
1&
#690
0&
#695
b1 3
b1 6
b1 8
1&
#700
0&
#705
b10 3
b10 6
b10 8
1&
#710
0&
#715
b11 3
b11 6
b11 8
1&
#720
0&
#725
b0 3
b0 6
b0 8
1&
#730
0&
#735
b1 3
b1 6
b1 8
1&
#740
0&
#745
b10 3
b10 6
b10 8
1&
#750
0&
#755
b11 3
b11 6
b11 8
1&
#760
0&
#765
b0 3
b0 6
b0 8
1&
#770
0&
#775
b1 3
b1 6
b1 8
1&
#780
0&
#785
b10 3
b10 6
b10 8
1&
#790
0&
#795
b11 3
b11 6
b11 8
1&
#800
0&
#805
b0 3
b0 6
b0 8
1&
#810
0&
#815
b1 3
b1 6
b1 8
1&
#820
0&
#825
b10 3
b10 6
b10 8
1&
#830
0&
#835
b11 3
b11 6
b11 8
1&
#840
0&
#845
b0 3
b0 6
b0 8
1&
#850
0&
#855
b1 3
b1 6
b1 8
1&
#860
0&
#865
b10 3
b10 6
b10 8
1&
#870
0&
#875
b11 3
b11 6
b11 8
1&
#880
0&
#885
b0 3
b0 6
b0 8
1&
#890
0&
#895
b1 3
b1 6
b1 8
1&
#900
0&
#905
b10 3
b10 6
b10 8
1&
#910
0&
#915
b11 3
b11 6
b11 8
1&
#920
0&
#925
b0 3
b0 6
b0 8
1&
#930
0&
#935
b1 3
b1 6
b1 8
1&
#940
0&
#945
b10 3
b10 6
b10 8
1&
#950
0&
#955
b11 3
b11 6
b11 8
1&
#960
0&
#965
b0 3
b0 6
b0 8
1&
#970
0&
#975
b1 3
b1 6
b1 8
1&
#980
0&
#985
b10 3
b10 6
b10 8
1&
#990
0&
#995
b11 3
b11 6
b11 8
1&
#1000
0&
#1005
b0 3
b0 6
b0 8
1&
#1010
0&
#1015
b1 3
b1 6
b1 8
1&
#1020
0&
#1025
b10 3
b10 6
b10 8
1&
#1030
0&
#1035
b11 3
b11 6
b11 8
1&
#1040
0&
#1045
b0 3
b0 6
b0 8
1&
#1050
0&
#1055
b1 3
b1 6
b1 8
1&
#1060
0&
#1065
b10 3
b10 6
b10 8
1&
#1070
0&
#1075
b11 3
b11 6
b11 8
1&
#1080
0&
#1085
b0 3
b0 6
b0 8
1&
#1090
0&
#1095
b1 3
b1 6
b1 8
1&
#1100
0&
#1105
b10 3
b10 6
b10 8
1&
#1110
0&
#1115
b11 3
b11 6
b11 8
1&
#1120
0&
#1125
b0 3
b0 6
b0 8
1&
#1130
0&
#1135
b1 3
b1 6
b1 8
1&
#1140
0&
#1145
b10 3
b10 6
b10 8
1&
#1150
0&
#1155
b11 3
b11 6
b11 8
1&
#1160
0&
#1165
b0 3
b0 6
b0 8
1&
#1170
0&
#1175
b1 3
b1 6
b1 8
1&
#1180
0&
#1185
b10 3
b10 6
b10 8
1&
#1190
0&
#1195
b11 3
b11 6
b11 8
1&
#1200
0&
#1205
b0 3
b0 6
b0 8
1&
#1210
0&
#1215
b1 3
b1 6
b1 8
1&
#1220
0&
#1225
b10 3
b10 6
b10 8
1&
#1230
0&
#1235
b11 3
b11 6
b11 8
1&
#1240
0&
#1245
b0 3
b0 6
b0 8
1&
#1250
0&
#1255
b1 3
b1 6
b1 8
1&
#1260
0&
#1265
b10 3
b10 6
b10 8
1&
#1270
0&
#1275
b11 3
b11 6
b11 8
1&
#1280
0&
#1285
b0 3
b0 6
b0 8
1&
#1290
0&
#1295
b1 3
b1 6
b1 8
1&
#1300
0&
#1305
b10 3
b10 6
b10 8
1&
#1310
0&
#1315
b11 3
b11 6
b11 8
1&
#1320
0&
#1325
b0 3
b0 6
b0 8
1&
#1330
0&
#1335
b1 3
b1 6
b1 8
1&
#1340
0&
#1345
b10 3
b10 6
b10 8
1&
#1350
0&
#1355
b11 3
b11 6
b11 8
1&
#1360
0&
#1365
b0 3
b0 6
b0 8
1&
#1370
0&
#1375
b1 3
b1 6
b1 8
1&
#1380
0&
#1385
b10 3
b10 6
b10 8
1&
#1390
0&
#1395
b11 3
b11 6
b11 8
1&
#1400
0&
#1405
b0 3
b0 6
b0 8
1&
#1410
0&
#1415
b1 3
b1 6
b1 8
1&
#1420
0&
#1425
b10 3
b10 6
b10 8
1&
#1430
0&
#1435
b11 3
b11 6
b11 8
1&
#1440
0&
#1445
b0 3
b0 6
b0 8
1&
#1450
0&
#1455
b1 3
b1 6
b1 8
1&
#1460
0&
#1465
b10 3
b10 6
b10 8
1&
#1470
0&
#1475
b11 3
b11 6
b11 8
1&
#1480
0&
#1485
b0 3
b0 6
b0 8
1&
#1490
0&
#1495
b1 3
b1 6
b1 8
1&
#1500
0&
#1505
b10 3
b10 6
b10 8
1&
#1510
0&
#1515
b11 3
b11 6
b11 8
1&
#1520
0&
#1525
b0 3
b0 6
b0 8
1&
#1530
0&
#1535
b1 3
b1 6
b1 8
1&
#1540
0&
#1545
b10 3
b10 6
b10 8
1&
#1550
0&
#1555
b11 3
b11 6
b11 8
1&
#1560
0&
#1565
b0 3
b0 6
b0 8
1&
#1570
0&
#1575
b1 3
b1 6
b1 8
1&
#1580
0&
#1585
b10 3
b10 6
b10 8
1&
#1590
0&
#1595
b11 3
b11 6
b11 8
1&
#1600
0&
#1605
b0 3
b0 6
b0 8
1&
#1610
0&
#1615
b1 3
b1 6
b1 8
1&
#1620
0&
#1625
b10 3
b10 6
b10 8
1&
#1630
0&
#1635
b11 3
b11 6
b11 8
1&
#1640
0&
#1645
b0 3
b0 6
b0 8
1&
#1650
0&
#1655
b1 3
b1 6
b1 8
1&
#1660
0&
#1665
b10 3
b10 6
b10 8
1&
#1670
0&
#1675
b11 3
b11 6
b11 8
1&
#1680
0&
#1685
b0 3
b0 6
b0 8
1&
#1690
0&
#1695
b1 3
b1 6
b1 8
1&
#1700
0&
#1705
b10 3
b10 6
b10 8
1&
#1710
0&
#1715
b11 3
b11 6
b11 8
1&
#1720
0&
#1725
b0 3
b0 6
b0 8
1&
#1730
0&
#1735
b1 3
b1 6
b1 8
1&
#1740
0&
#1745
b10 3
b10 6
b10 8
1&
#1750
0&
#1755
b11 3
b11 6
b11 8
1&
#1760
0&
#1765
b0 3
b0 6
b0 8
1&
#1770
0&
#1775
b1 3
b1 6
b1 8
1&
#1780
0&
#1785
b10 3
b10 6
b10 8
1&
#1790
0&
#1795
b11 3
b11 6
b11 8
1&
#1800
0&
#1805
b0 3
b0 6
b0 8
1&
#1810
0&
#1815
b1 3
b1 6
b1 8
1&
#1820
0&
#1825
b10 3
b10 6
b10 8
1&
#1830
0&
#1835
b11 3
b11 6
b11 8
1&
#1840
0&
#1845
b0 3
b0 6
b0 8
1&
#1850
0&
#1855
b1 3
b1 6
b1 8
1&
#1860
0&
#1865
b10 3
b10 6
b10 8
1&
#1870
0&
#1875
b11 3
b11 6
b11 8
1&
#1880
0&
#1885
b0 3
b0 6
b0 8
1&
#1890
0&
#1895
b1 3
b1 6
b1 8
1&
#1900
0&
#1905
b10 3
b10 6
b10 8
1&
#1910
0&
#1915
b11 3
b11 6
b11 8
1&
#1920
0&
#1925
b0 3
b0 6
b0 8
1&
#1930
0&
#1935
b1 3
b1 6
b1 8
1&
#1940
0&
#1945
b10 3
b10 6
b10 8
1&
#1950
0&
#1955
b11 3
b11 6
b11 8
1&
#1960
0&
#1965
b0 3
b0 6
b0 8
1&
#1970
0&
#1975
b1 3
b1 6
b1 8
1&
#1980
0&
#1985
b10 3
b10 6
b10 8
1&
#1990
0&
#1995
b11 3
b11 6
b11 8
1&
#2000
0&
#2005
b0 3
b0 6
b0 8
1&
#2010
0&
#2015
b1 3
b1 6
b1 8
1&
#2020
0&
#2025
b10 3
b10 6
b10 8
1&
#2030
0&
#2035
b11 3
b11 6
b11 8
1&
#2040
0&
#2045
b0 3
b0 6
b0 8
1&
#2050
0&
#2055
b1 3
b1 6
b1 8
1&
#2060
0&
#2065
b10 3
b10 6
b10 8
1&
#2070
0&
#2075
b11 3
b11 6
b11 8
1&
#2080
0&
#2085
b0 3
b0 6
b0 8
1&
#2090
0&
#2095
b1 3
b1 6
b1 8
1&
#2100
0&
#2105
b10 3
b10 6
b10 8
1&
#2110
0&
#2115
b11 3
b11 6
b11 8
1&
#2120
0&
#2125
b0 3
b0 6
b0 8
1&
#2130
0&
#2135
b1 3
b1 6
b1 8
1&
#2140
0&
#2145
b10 3
b10 6
b10 8
1&
#2150
0&
#2155
b11 3
b11 6
b11 8
1&
#2160
0&
#2165
b0 3
b0 6
b0 8
1&
#2170
0&
#2175
b1 3
b1 6
b1 8
1&
#2180
0&
#2185
b10 3
b10 6
b10 8
1&
#2190
0&
#2195
b11 3
b11 6
b11 8
1&
#2200
0&
#2205
b0 3
b0 6
b0 8
1&
#2210
0&
#2215
b1 3
b1 6
b1 8
1&
#2220
0&
#2225
b10 3
b10 6
b10 8
1&
#2230
0&
#2235
b11 3
b11 6
b11 8
1&
#2240
0&
#2245
b0 3
b0 6
b0 8
1&
#2250
0&
#2255
b1 3
b1 6
b1 8
1&
#2260
0&
#2265
b10 3
b10 6
b10 8
1&
#2270
0&
#2275
b11 3
b11 6
b11 8
1&
#2280
0&
#2285
b0 3
b0 6
b0 8
1&
#2290
0&
#2295
b1 3
b1 6
b1 8
1&
#2300
0&
#2305
b10 3
b10 6
b10 8
1&
#2310
0&
#2315
b11 3
b11 6
b11 8
1&
#2320
0&
#2325
b0 3
b0 6
b0 8
1&
#2330
0&
#2335
b1 3
b1 6
b1 8
1&
#2340
0&
#2345
b10 3
b10 6
b10 8
1&
#2350
0&
#2355
b11 3
b11 6
b11 8
1&
#2360
0&
#2365
b0 3
b0 6
b0 8
1&
#2370
0&
#2375
b1 3
b1 6
b1 8
1&
#2380
0&
#2385
b10 3
b10 6
b10 8
1&
#2390
0&
#2395
b11 3
b11 6
b11 8
1&
#2400
0&
#2405
b0 3
b0 6
b0 8
1&
#2410
0&
#2415
b1 3
b1 6
b1 8
1&
#2420
0&
#2425
b10 3
b10 6
b10 8
1&
#2430
0&
#2435
b11 3
b11 6
b11 8
1&
#2440
0&
#2445
b0 3
b0 6
b0 8
1&
#2450
0&
#2455
b1 3
b1 6
b1 8
1&
#2460
0&
#2465
b10 3
b10 6
b10 8
1&
#2470
0&
#2475
b11 3
b11 6
b11 8
1&
#2480
0&
#2485
b0 3
b0 6
b0 8
1&
#2490
0&
#2495
b1 3
b1 6
b1 8
1&
#2500
0&
#2505
b10 3
b10 6
b10 8
1&
#2510
0&
#2515
b11 3
b11 6
b11 8
1&
#2520
0&
#2525
b0 3
b0 6
b0 8
1&
#2530
0&
#2535
b1 3
b1 6
b1 8
1&
#2540
0&
#2545
b10 3
b10 6
b10 8
1&
#2550
0&
#2555
b11 3
b11 6
b11 8
1&
#2560
0&
#2565
b0 3
b0 6
b0 8
1&
#2570
0&
#2575
b1 3
b1 6
b1 8
1&
#2580
0&
#2585
b10 3
b10 6
b10 8
1&
#2590
0&
#2595
b11 3
b11 6
b11 8
1&
#2600
0&
#2605
b0 3
b0 6
b0 8
1&
#2610
0&
#2615
b1 3
b1 6
b1 8
1&
#2620
0&
#2625
b10 3
b10 6
b10 8
1&
#2630
0&
#2635
b11 3
b11 6
b11 8
1&
#2640
0&
