master_fsm_rtl/counter.v
module counter(
               input            clk,
               input            rst_n,
               input            rst_count_2,
               input            count_inc,
               output reg [3:0] count
);

always @(posedge clk or negedge rst_n) begin
    if(~rst_n) count <= 0;
    else 
    begin
        if(rst_count_2) count <= 0;
        else if(count_inc)
        begin
            count <= count + 1'b1;
        end
    end
end
endmodule

master_fsm_rtl/sda_gen.v
module sda_generate #(
    //parameter THRESHOLD         = 2,
    parameter ADDR_LEN          = 7,
    parameter DATA_LEN          = 8,
    parameter SETUP_SDA_START   = 2,
    parameter SETUP_SDA_STOP    = 2,
    parameter SETUP_SDA         = 3,
    parameter T_HIGH            = 4,
    parameter T_LOW             = 6
    )(
    input                       clk,
    input                       rst_n,
    input                       start,
    input                       scl,
    input [6:0]                 count_ctrl,
    input [3:0]                 count,
    input                       wait_for_sync,
    input                       add_sent,
    input                       data_received,
    input                       data_sent,
    input [ADDR_LEN-1:0]        add_reg,
    input                       R_W,
    input [DATA_LEN-1:0]        data_1,
    input [DATA_LEN-1:0]        data_2,
    input                       ack_3p,
    inout                       sda,
    output                      rst_count,
    output                      rst_count_2,
    output [3:0]                state_master,
    output                      free
                                           );


    reg [3:0]           current_state;
    reg [3:0]           next_state;
    reg                 sda_reg;
    reg [1:0]           no_of_data_rec;
    reg [1:0]           no_of_data_sent; //See if one can be used
    reg [DATA_LEN-1:0]  data_mem [1:0];
    reg                 ack_reg;

    parameter Idle            = 4'b0000;
    parameter Ready           = 4'b0001;
    parameter Send_Address    = 4'b0010;
    parameter Write_Data      = 4'b0011;
    //parameter Output_Data     = 4'b0100;
    parameter Check_ACK_data  = 4'b0101;
    parameter Read_Data       = 4'b0110;
    //parameter Store_Data      = 4'b0111;
    parameter Check_for_Valid = 4'b1000;
    parameter Send_ACK        = 4'b1001;
    parameter Send_NACK       = 4'b1010;
    parameter Stop            = 4'b1011;
    parameter Check_ACK_addr  = 4'b1100;


//always block for curr_state
    always @(posedge clk or negedge rst_n)
        begin
            if(~rst_n) begin
                current_state <= Idle;
            end else begin
                current_state <= next_state;
            end

        end
    //always block for sda_reg
    always @(posedge clk or negedge rst_n)
    begin
        if(~rst_n) begin
            sda_reg <= 1'b1;
        end
     else begin
        case (current_state) 

        Idle: begin
            sda_reg <= 1'b1;
        end

        Ready : begin
            if(count_ctrl == (SETUP_SDA_START -1)) begin
                sda_reg <= 1'b0;
            end
        end
        
        Send_Address : begin
            if(count <= ADDR_LEN -1) begin
                if(count_ctrl == T_LOW - SETUP_SDA - 1) sda_reg <= add_reg[(ADDR_LEN - 1) - count];
            end else begin
                if(count_ctrl == T_LOW - SETUP_SDA - 1) sda_reg <= R_W;
            end
        end

        Check_ACK_addr: begin
            if(count_ctrl == T_LOW -SETUP_SDA - 1) begin
                sda_reg <= 1'bz;
            end
        end

        Write_Data: begin
            if(count_ctrl == T_LOW -SETUP_SDA -1 && no_of_data_sent == 0) sda_reg <= data_1[DATA_LEN-1-count];
            else if(count_ctrl == T_LOW -SETUP_SDA -1 && no_of_data_sent == 1) sda_reg <= data_2[DATA_LEN-1-count];
        end

        Check_ACK_data: begin
            if(count_ctrl == T_LOW -SETUP_SDA - 1) begin
                sda_reg <= 1'bz;
            end
        end

        Read_Data: begin
            if(count_ctrl == T_LOW -SETUP_SDA -1 && no_of_data_sent == 0) data_mem[no_of_data_sent][DATA_LEN-1-count] <= sda;
        end

        Send_ACK: begin
            if(count_ctrl == T_LOW -SETUP_SDA - 1) sda_reg <= ~ack_3p;
        end

        Stop: begin
            if (count_ctrl == T_HIGH+T_LOW -1 ) begin
                sda_reg <= 1'bz;
            end else if(count_ctrl >= T_LOW + SETUP_SDA_STOP -1) begin
                sda_reg <= 1; 
            end else begin
                sda_reg <= 0;
            end
        end
    
        
     endcase 

     end
    end

//always block for ack_reg
always @(posedge clk or negedge rst_n) begin
    if(~rst_n) begin
        ack_reg <= 0;
    end else begin
        if(add_sent || data_sent) begin
            ack_reg <= 0;
        end else if((state_master == Check_ACK_addr || state_master == Check_ACK_data) && scl && sda) begin
            ack_reg <= 1;
        end
    end 
end

//always block for no_of_data_sent
always @(posedge clk or negedge rst_n) begin
    if(~rst_n) begin
        no_of_data_sent <= 0;
    end else begin
        if(data_sent || data_received) no_of_data_sent <= no_of_data_sent + 1'b1;
        if(current_state == Idle) begin
            no_of_data_sent <= 0;
        end
    end
end

//Combo Logic for next_state
always @(*) begin
    next_state = current_state;

    case(current_state)
        Idle : begin
            if(start) begin
                next_state = Ready;
            end
        end

        Ready: begin
           if(wait_for_sync) begin
                next_state = Send_Address;
           end
        end

        Send_Address: begin
            if(add_sent) next_state = Check_ACK_addr;
        end

        Check_ACK_addr: begin
            if(~ack_reg && (count_ctrl==T_LOW+T_HIGH-1)) begin
                if(R_W) begin
                    next_state = Read_Data;
                end else begin
                    next_state = Write_Data;
                end
            end
            else if(ack_reg && (count_ctrl==T_LOW+T_HIGH-1)) begin
                next_state = Stop;
            end
        end

        Write_Data : begin
            if(data_sent) next_state = Check_ACK_data;
        end

        Check_ACK_data: begin
            if(no_of_data_sent == 1 && ~ack_reg && (count_ctrl==T_LOW+T_HIGH-1)) next_state = Write_Data;
            else if(no_of_data_sent == 1 && ack_reg && (count_ctrl==T_LOW+T_HIGH-1)) next_state = Stop;
            else if (no_of_data_sent == 2 && (count_ctrl == T_LOW + T_HIGH - 1)) next_state = Stop;
        end

        Read_Data: begin
            if(data_received) next_state = Send_ACK;
        end

        Send_ACK: begin
            if(no_of_data_sent < 2 && ack_3p && (count_ctrl==T_LOW+T_HIGH-1)) next_state = Read_Data;
            else if(no_of_data_sent < 2 && ~ack_3p && (count_ctrl==T_LOW+T_HIGH-1)) next_state = Stop;
            else if(no_of_data_sent == 2 && (count_ctrl==T_LOW+T_HIGH-1)) next_state = Stop;
        end

        Stop: begin
            if((count_ctrl==T_LOW+T_HIGH-1)) next_state = Idle;
        end
       
    endcase

end

    
    assign state_master = current_state;
    assign free = (current_state == Idle);
    assign rst_count = (current_state == Idle) || wait_for_sync || free || add_sent || data_sent || 
                        data_received ;
    assign rst_count_2 = wait_for_sync || add_sent || data_sent || data_received;
    assign sda = sda_reg;

endmodule

master_fsm_rtl/scl_gen.v
module scl_generate #(
    //parameter THRESHOLD     = 2,
    parameter T_LOW         = 6,
    parameter T_HIGH        = 4,  //SCL is LOW for T_LOW*CLK_PERIOD and HIGH for T_HIGH*CLK_PERIOD
    parameter ADDR_LEN      = 7,
    parameter SETUP_SCL_START = 4,
    parameter DATA_LEN      = 8
)(
    input              clk,
    input              rst_n,
    input [3:0]        state_master,
    input              rst_count,
    input [3:0]        count,
    output reg [6:0]   count_ctrl,
    output reg         scl,
    output             wait_for_sync,
    output             add_sent,
    output             data_received,
    output             data_sent,
    output             count_inc
);

    

    parameter Idle            = 4'b0000;
    parameter Ready           = 4'b0001;
    parameter Send_Address    = 4'b0010;
    parameter Write_Data      = 4'b0011;
    parameter Output_Data     = 4'b0100;
    parameter Check_ACK       = 4'b0101;
    parameter Read_Data       = 4'b0110;
    parameter Store_Data      = 4'b0111;
    parameter Check_for_Valid = 4'b1000;
    parameter Send_ACK        = 4'b1001;
    parameter Send_NACK       = 4'b1010;
    parameter Stop            = 4'b1011;

//always block for count_ctrl
always @(posedge clk or negedge rst_n) begin
    if(~rst_n) begin
        count_ctrl <= 0;
    end else begin
        if (rst_count) begin
            count_ctrl <= 0;
        end else begin
            if (state_master == Ready) begin
                if(count_ctrl == (SETUP_SCL_START-1)) begin
                    count_ctrl <= 0;
                end else begin
                    count_ctrl <= count_ctrl + 1;
                end
            end else if(state_master != Ready && state_master != Stop && state_master!=Idle) begin
                if (count_ctrl == (T_LOW+T_HIGH-1)) begin
                    count_ctrl <= 0;
                end else begin
                    count_ctrl <= count_ctrl + 1; 
                end
            end else begin //what happens to cnt cntrl in other states?
                count_ctrl <= count_ctrl + 1;
            end
        end
    end
end

//always block for scl
always @(posedge clk or negedge rst_n) begin
    if (~rst_n) begin
        scl <= 1; //check
    end else begin
        if (state_master == Ready) begin
            if (count_ctrl == SETUP_SCL_START-1) begin
                scl <= 1'b0;
            end
        end else if(state_master != Ready && state_master != Idle && state_master != Stop) begin
            if(count_ctrl < T_LOW -1 || count_ctrl == (T_HIGH + T_LOW -1) ) begin
                scl <= 1'b0;
            end else begin
                scl <= 1'b1;
            end
        end
        else if(state_master == Idle) begin
            scl <= 1'b1;
        end
        else if(state_master == Stop) begin
            if(count_ctrl < T_LOW -1) begin
                scl <= 1'b0;
            end else if (count_ctrl == T_HIGH+T_LOW -1 ) begin
                scl <= 1'bz;
            end
            else  begin
                scl <= 1'b1;
            end
        end
    end
end

    assign wait_for_sync = (count_ctrl == (SETUP_SCL_START-1)) && (state_master == Ready);
    assign add_sent      = (count      == ADDR_LEN) && (count_ctrl == T_HIGH + T_LOW -1 ) && (state_master == Send_Address);
    assign data_received = (count      == DATA_LEN-1) && (count_ctrl == T_HIGH + T_LOW - 1) && (state_master == Read_Data);
    assign data_sent     = (count      == DATA_LEN-1) && (count_ctrl == T_HIGH + T_LOW - 1) && (state_master == Write_Data);
    assign count_inc     = (count_ctrl == T_HIGH + T_LOW - 1) && (state_master == Send_Address || state_master == Write_Data|| state_master == Read_Data);

endmodule

master_fsm_rtl/fsm_master.v
// Master Controller
module fsm_master #(
    //parameter FREQ_DIFF = 4,
    parameter T_LOW     = 6,
    parameter T_HIGH    = 4,
    parameter ADDR_LEN  = 7,
    parameter SETUP_SCL_START = 4,
    parameter SETUP_SDA_START = 2,
    parameter SETUP_SDA = 3,
    parameter SETUP_SDA_STOP = 2,
    parameter DATA_LEN  = 8
                            )
    (
        input                   clk,
        input                   rst_n,
        input                   start,
        input [ADDR_LEN-1:0]    add_reg,
        input                   R_W,
        input [DATA_LEN-1:0]    data_1,
        input [DATA_LEN-1:0]    data_2,
        input                   ack_3p,
        output                  scl,
        inout                   sda,
        output [3:0]            state_master,
        output                  free
    );


    //wire [3:0] state_master;
    wire [6:0] count_ctrl;
    wire [3:0] count;
    wire       count_inc;
    wire       rst_count_2;
    wire       rst_count;
    wire       wait_for_sync;
    wire       add_sent;
    wire       data_received;
    wire       data_sent;

    scl_generate #(
        //.THRESHOLD          (FREQ_DIFF/2    ),
        .T_LOW              (T_LOW          ),
        .T_HIGH             (T_HIGH         ),
        .ADDR_LEN           (ADDR_LEN       ),
        .SETUP_SCL_START    (SETUP_SCL_START),
        .DATA_LEN           (DATA_LEN       )
        ) 
        SCL
        (
            .clk                (clk            ),
            .rst_n              (rst_n          ),
            .state_master       (state_master   ),
            .rst_count          (rst_count      ),
            .count              (count          ),
            .count_ctrl         (count_ctrl     ),
            .scl                (scl            ),
            .wait_for_sync      (wait_for_sync  ),
            .add_sent           (add_sent       ),
            .data_received      (data_received  ),
            .data_sent          (data_sent      ),
            .count_inc          (count_inc      )
        );
    
    sda_generate #(
        //.THRESHOLD          (FREQ_DIFF/2    ),
        .ADDR_LEN           (ADDR_LEN       ),
        .SETUP_SDA_START    (SETUP_SDA_START),
        .SETUP_SDA_STOP     (SETUP_SDA_STOP ),
        .SETUP_SDA          (SETUP_SDA      ),
        .DATA_LEN           (DATA_LEN       ),
        .T_LOW              (T_LOW          ),
        .T_HIGH             (T_HIGH         )
        ) SDA(
            .clk                (clk            ),
            .rst_n              (rst_n          ),
            .start              (start          ),
            .scl                (scl            ),
            .count_ctrl         (count_ctrl     ),
            .count              (count          ),
            .wait_for_sync      (wait_for_sync  ),
            .add_sent           (add_sent       ),
            .data_received      (data_received  ),
            .data_sent          (data_sent      ),
            .add_reg            (add_reg        ),
            .R_W                (R_W            ),
            .data_1             (data_1         ),
            .data_2             (data_2         ),
            .ack_3p             (ack_3p         ),
            .sda                (sda            ),
            .rst_count          (rst_count      ),
            .rst_count_2        (rst_count_2    ),
            .state_master       (state_master   ),
            .free               (free           )
        );

    counter COUNTER(
            .clk                (clk            ),
            .rst_n              (rst_n          ),
            .rst_count_2        (rst_count_2    ),
            .count_inc          (count_inc      ),
            .count              (count          )
    );

endmodule

master_fsm_rtl/tb.v
module tb_;

parameter ADDR_LEN = 7;
parameter DATA_LEN = 8;
//parameter FREQ_DIFF = 4;
parameter SETUP_SDA_START=2;
parameter SETUP_SCL_START=4;
parameter SETUP_SDA_STOP = 2;
parameter T_LOW         = 6;
parameter T_HIGH        = 4;
parameter SETUP_SDA     = 3;

reg clk;
reg rst_n;
reg start;
reg [ADDR_LEN-1:0] add_reg;
reg R_W;
reg [DATA_LEN-1:0] data_1;
reg [DATA_LEN-1:0] data_2;
reg                ack_3p;
reg dummy;
wire scl;
wire sda;
wire[3:0] state_master;
wire free;
reg output_value_valid;


fsm_master #(
    //.FREQ_DIFF              (FREQ_DIFF),
    .T_LOW                  (T_LOW          ),
    .T_HIGH                 (T_HIGH         ),
    .ADDR_LEN               (ADDR_LEN       ),
    .SETUP_SCL_START        (SETUP_SCL_START),
    .SETUP_SDA_START        (SETUP_SDA_START),
    .SETUP_SDA              (SETUP_SDA      ),
    .SETUP_SDA_STOP         (SETUP_SDA_STOP ),
    .DATA_LEN               (DATA_LEN       )
) FSM_MASTER_DUT
(
    .clk                (clk        ),
    .rst_n              (rst_n      ),
    .start              (start      ),
    .add_reg            (add_reg    ),
    .R_W                (R_W        ),
    .data_1             (data_1     ),
    .data_2             (data_2     ),
    .ack_3p             (ack_3p     ),
    .scl                (scl        ),
    .sda                (sda        ),
    .state_master       (state_master),
    .free               (free       )
);

assign sda = (output_value_valid==1'b1)? dummy : 8'hZZ;

localparam CLK_PERIOD = 10;
always #(CLK_PERIOD/2) clk=~clk;

initial begin
    clk = 0;
    #5000 $finish;
end

initial begin
    $dumpfile("tb_.vcd");
    $dumpvars(0, tb_);
end

initial begin
    #CLK_PERIOD RST_TEST;
    #CLK_PERIOD START_TEST(7'b1010110, 0);
    
end

task START_TEST(input[ADDR_LEN-1:0] addr, input r_w);
    begin
        wait(free);
        rst_n=1; start=1; data_1 =8'hab; data_2 = 8'hab; R_W=r_w;add_reg=addr; output_value_valid = 0;
        #CLK_PERIOD; 
        start = 0;
        if(free) begin
            $display("ERROR: free HIGH after start..");
            $finish;
        end
        else begin
            $display("Operation Started successfully..");
        end
        repeat(2) begin
        wait(state_master == 4'b1001);
        wait(state_master == 4'b0110);
        output_value_valid = 1;
        #((T_LOW-SETUP_SDA-1)*CLK_PERIOD) dummy = 1;
        #((T_LOW+T_HIGH)*CLK_PERIOD) dummy = 0;
        #((T_LOW+T_HIGH)*CLK_PERIOD);
        dummy = 1;
        #((T_LOW+T_HIGH)*CLK_PERIOD);
        dummy = 1;
        #((T_LOW+T_HIGH)*CLK_PERIOD);
        dummy = 1;
        #((T_LOW+T_HIGH)*CLK_PERIOD);
        dummy = 0;
        #((T_LOW+T_HIGH)*CLK_PERIOD);
        dummy = 0;
        #((T_LOW+T_HIGH)*CLK_PERIOD);
        dummy = 1;
        ack_3p = 1;
        #((T_LOW+T_HIGH)*CLK_PERIOD);
        output_value_valid = 1'b0;
        end
        //START_TEST_checker;
        //SEND_ADDR_checker(addr);
    end
endtask

task START_TEST_checker;
    begin
        wait(~free);
        if(~sda || ~scl) begin
            $display("ERROR: START_TEST failed");
            $finish;
        end
        #SETUP_SDA_START
        if(sda || ~scl) begin
            $display("ERROR: START_TEST failed");
            $finish;
        end
        #(SETUP_SCL_START-SETUP_SDA_START)
        if(sda || scl) begin
            $display("ERROR: START_TEST failed");
            $finish;
        end
        $display("START condition verified..");
    end
endtask

task SEND_ADDR_checker(input[ADDR_LEN-1:0] addr);
    reg count;
    begin
        count = 0;
        wait(~scl);
        repeat(ADDR_LEN) begin
            wait(scl);
            if(sda != addr[ADDR_LEN-count -1]) begin
                $display("ERROR: Incorrect ADDR sent!");
                //$finish;
            end
            count = count+1;
            wait(~scl);
        end
        $display("ADDR transmitted successfully..");
    end
endtask



task RST_TEST;
    begin
        @(posedge clk)
        rst_n = 1'b0; start=0; add_reg={ADDR_LEN{1'b0}}; R_W=0; data_1={DATA_LEN{1'b0}}; data_2={DATA_LEN{1'b0}};
        wait(CLK_PERIOD);
        if(~free || ~sda || ~scl) begin
            $display("RST_TEST FAILED");
            $finish;
        end else begin
            $display("RST_TEST passed.");
        end
    end

endtask

endmodule
// `default_nettype wire

master_fsm_rtl/tb_.vcd
$date
	Wed Jan 31 15:01:55 2024
$end
$version
	Icarus Verilog
$end
$timescale
	1s
$end
$scope module tb_ $end
$var wire 1 ! sda $end
$var wire 4 " state_master [3:0] $end
$var wire 1 # scl $end
$var wire 1 $ free $end
$var reg 1 % R_W $end
$var reg 1 & ack_3p $end
$var reg 7 ' add_reg [6:0] $end
$var reg 1 ( clk $end
$var reg 8 ) data_1 [7:0] $end
$var reg 8 * data_2 [7:0] $end
$var reg 1 + dummy $end
$var reg 1 , output_value_valid $end
$var reg 1 - rst_n $end
$var reg 1 . start $end
$scope module FSM_MASTER_DUT $end
$var wire 1 % R_W $end
$var wire 1 & ack_3p $end
$var wire 7 / add_reg [6:0] $end
$var wire 1 ( clk $end
$var wire 8 0 data_1 [7:0] $end
$var wire 8 1 data_2 [7:0] $end
$var wire 1 - rst_n $end
$var wire 1 ! sda $end
$var wire 1 . start $end
$var wire 1 2 wait_for_sync $end
$var wire 4 3 state_master [3:0] $end
$var wire 1 # scl $end
$var wire 1 4 rst_count_2 $end
$var wire 1 5 rst_count $end
$var wire 1 $ free $end
$var wire 1 6 data_sent $end
$var wire 1 7 data_received $end
$var wire 1 8 count_inc $end
$var wire 7 9 count_ctrl [6:0] $end
$var wire 4 : count [3:0] $end
$var wire 1 ; add_sent $end
$scope module COUNTER $end
$var wire 1 ( clk $end
$var wire 1 - rst_n $end
$var wire 1 4 rst_count_2 $end
$var wire 1 8 count_inc $end
$var reg 4 < count [3:0] $end
$upscope $end
$scope module SCL $end
$var wire 1 ; add_sent $end
$var wire 1 ( clk $end
$var wire 4 = count [3:0] $end
$var wire 1 8 count_inc $end
$var wire 1 7 data_received $end
$var wire 1 6 data_sent $end
$var wire 1 - rst_n $end
$var wire 1 2 wait_for_sync $end
$var wire 4 > state_master [3:0] $end
$var wire 1 5 rst_count $end
$var reg 7 ? count_ctrl [6:0] $end
$var reg 1 # scl $end
$upscope $end
$scope module SDA $end
$var wire 1 % R_W $end
$var wire 1 & ack_3p $end
$var wire 7 @ add_reg [6:0] $end
$var wire 1 ; add_sent $end
$var wire 1 ( clk $end
$var wire 4 A count [3:0] $end
$var wire 7 B count_ctrl [6:0] $end
$var wire 8 C data_1 [7:0] $end
$var wire 8 D data_2 [7:0] $end
$var wire 1 7 data_received $end
$var wire 1 6 data_sent $end
$var wire 1 5 rst_count $end
$var wire 1 4 rst_count_2 $end
$var wire 1 - rst_n $end
$var wire 1 # scl $end
$var wire 1 ! sda $end
$var wire 1 . start $end
$var wire 4 E state_master [3:0] $end
$var wire 1 2 wait_for_sync $end
$var wire 1 $ free $end
$var reg 1 F ack_reg $end
$var reg 4 G current_state [3:0] $end
$var reg 4 H next_state [3:0] $end
$var reg 2 I no_of_data_sent [1:0] $end
$var reg 1 J sda_reg $end
$upscope $end
$upscope $end
$scope task RST_TEST $end
$upscope $end
$scope task SEND_ADDR_checker $end
$var reg 7 K addr [6:0] $end
$var reg 1 L count $end
$upscope $end
$scope task START_TEST $end
$var reg 7 M addr [6:0] $end
$var reg 1 N r_w $end
$upscope $end
$scope task START_TEST_checker $end
$upscope $end
$upscope $end
$enddefinitions $end
#0
$dumpvars
xN
bx M
xL
bx K
xJ
bx I
bx H
bx G
xF
bx E
bx D
bx C
bx B
bx A
bx @
bx ?
bx >
bx =
bx <
x;
bx :
bx 9
x8
x7
x6
x5
x4
bx 3
x2
bx 1
bx 0
bx /
x.
x-
x,
x+
bx *
bx )
0(
bx '
x&
x%
x$
x#
bx "
x!
$end
#5
1(
#10
0(
#15
15
04
06
07
0;
02
08
b0 H
b0 :
b0 <
b0 =
b0 A
b0 I
0F
1J
1$
b0 "
b0 3
b0 >
b0 E
b0 G
1#
b0 9
b0 ?
b0 B
b0 *
b0 1
b0 D
b0 )
b0 0
b0 C
0%
b0 '
b0 /
b0 @
0.
0-
1(
#20
0(
#25
05
0$
b1 "
b1 3
b1 >
b1 E
b1 G
1!
b1 H
1(
0,
b1010110 '
b1010110 /
b1010110 @
b10101011 *
b10101011 1
b10101011 D
b10101011 )
b10101011 0
b10101011 C
1.
1-
0N
b1010110 M
#30
0(
#35
b1 9
b1 ?
b1 B
1(
0.
#40
0(
#45
b10 9
b10 ?
b10 B
0!
0J
1(
#50
0(
#55
15
14
b10 H
12
b11 9
b11 ?
b11 B
1(
#60
0(
#65
05
04
02
b0 9
b0 ?
b0 B
0#
b10 "
b10 3
b10 >
b10 E
b10 G
1(
#70
0(
#75
b1 9
b1 ?
b1 B
1(
#80
0(
#85
b10 9
b10 ?
b10 B
1(
#90
0(
#95
1!
1J
b11 9
b11 ?
b11 B
1(
#100
0(
#105
b100 9
b100 ?
b100 B
1(
#110
0(
#115
b101 9
b101 ?
b101 B
1(
#120
0(
#125
b110 9
b110 ?
b110 B
1#
1(
#130
0(
#135
b111 9
b111 ?
b111 B
1(
#140
0(
#145
b1000 9
b1000 ?
b1000 B
1(
#150
0(
#155
18
b1001 9
b1001 ?
b1001 B
1(
#160
0(
#165
08
b0 9
b0 ?
b0 B
0#
b1 :
b1 <
b1 =
b1 A
1(
#170
0(
#175
b1 9
b1 ?
b1 B
1(
#180
0(
#185
b10 9
b10 ?
b10 B
1(
#190
0(
#195
0!
0J
b11 9
b11 ?
b11 B
1(
#200
0(
#205
b100 9
b100 ?
b100 B
1(
#210
0(
#215
b101 9
b101 ?
b101 B
1(
#220
0(
#225
b110 9
b110 ?
b110 B
1#
1(
#230
0(
#235
b111 9
b111 ?
b111 B
1(
#240
0(
#245
b1000 9
b1000 ?
b1000 B
1(
#250
0(
#255
18
b1001 9
b1001 ?
b1001 B
1(
#260
0(
#265
08
b0 9
b0 ?
b0 B
0#
b10 :
b10 <
b10 =
b10 A
1(
#270
0(
#275
b1 9
b1 ?
b1 B
1(
#280
0(
#285
b10 9
b10 ?
b10 B
1(
#290
0(
#295
1!
1J
b11 9
b11 ?
b11 B
1(
#300
0(
#305
b100 9
b100 ?
b100 B
1(
#310
0(
#315
b101 9
b101 ?
b101 B
1(
#320
0(
#325
b110 9
b110 ?
b110 B
1#
1(
#330
0(
#335
b111 9
b111 ?
b111 B
1(
#340
0(
#345
b1000 9
b1000 ?
b1000 B
1(
#350
0(
#355
18
b1001 9
b1001 ?
b1001 B
1(
#360
0(
#365
08
b0 9
b0 ?
b0 B
0#
b11 :
b11 <
b11 =
b11 A
1(
#370
0(
#375
b1 9
b1 ?
b1 B
1(
#380
0(
#385
b10 9
b10 ?
b10 B
1(
#390
0(
#395
0!
0J
b11 9
b11 ?
b11 B
1(
#400
0(
#405
b100 9
b100 ?
b100 B
1(
#410
0(
#415
b101 9
b101 ?
b101 B
1(
#420
0(
#425
b110 9
b110 ?
b110 B
1#
1(
#430
0(
#435
b111 9
b111 ?
b111 B
1(
#440
0(
#445
b1000 9
b1000 ?
b1000 B
1(
#450
0(
#455
18
b1001 9
b1001 ?
b1001 B
1(
#460
0(
#465
08
b0 9
b0 ?
b0 B
0#
b100 :
b100 <
b100 =
b100 A
1(
#470
0(
#475
b1 9
b1 ?
b1 B
1(
#480
0(
#485
b10 9
b10 ?
b10 B
1(
#490
0(
#495
1!
1J
b11 9
b11 ?
b11 B
1(
#500
0(
#505
b100 9
b100 ?
b100 B
1(
#510
0(
#515
b101 9
b101 ?
b101 B
1(
#520
0(
#525
b110 9
b110 ?
b110 B
1#
1(
#530
0(
#535
b111 9
b111 ?
b111 B
1(
#540
0(
#545
b1000 9
b1000 ?
b1000 B
1(
#550
0(
#555
18
b1001 9
b1001 ?
b1001 B
1(
#560
0(
#565
08
b0 9
b0 ?
b0 B
0#
b101 :
b101 <
b101 =
b101 A
1(
#570
0(
#575
b1 9
b1 ?
b1 B
1(
#580
0(
#585
b10 9
b10 ?
b10 B
1(
#590
0(
#595
b11 9
b11 ?
b11 B
1(
#600
0(
#605
b100 9
b100 ?
b100 B
1(
#610
0(
#615
b101 9
b101 ?
b101 B
1(
#620
0(
#625
b110 9
b110 ?
b110 B
1#
1(
#630
0(
#635
b111 9
b111 ?
b111 B
1(
#640
0(
#645
b1000 9
b1000 ?
b1000 B
1(
#650
0(
#655
18
b1001 9
b1001 ?
b1001 B
1(
#660
0(
#665
08
b0 9
b0 ?
b0 B
0#
b110 :
b110 <
b110 =
b110 A
1(
#670
0(
#675
b1 9
b1 ?
b1 B
1(
#680
0(
#685
b10 9
b10 ?
b10 B
1(
#690
0(
#695
0!
0J
b11 9
b11 ?
b11 B
1(
#700
0(
#705
b100 9
b100 ?
b100 B
1(
#710
0(
#715
b101 9
b101 ?
b101 B
1(
#720
0(
#725
b110 9
b110 ?
b110 B
1#
1(
#730
0(
#735
b111 9
b111 ?
b111 B
1(
#740
0(
#745
b1000 9
b1000 ?
b1000 B
1(
#750
0(
#755
18
b1001 9
b1001 ?
b1001 B
1(
#760
0(
#765
08
b0 9
b0 ?
b0 B
0#
b111 :
b111 <
b111 =
b111 A
1(
#770
0(
#775
b1 9
b1 ?
b1 B
1(
#780
0(
#785
b10 9
b10 ?
b10 B
1(
#790
0(
#795
b11 9
b11 ?
b11 B
1(
#800
0(
#805
b100 9
b100 ?
b100 B
1(
#810
0(
#815
b101 9
b101 ?
b101 B
1(
#820
0(
#825
b110 9
b110 ?
b110 B
1#
1(
#830
0(
#835
b111 9
b111 ?
b111 B
1(
#840
0(
#845
b1000 9
b1000 ?
b1000 B
1(
#850
0(
#855
15
14
b1100 H
1;
18
b1001 9
b1001 ?
b1001 B
1(
#860
0(
#865
05
04
08
0;
b0 9
b0 ?
b0 B
0#
b1100 "
b1100 3
b1100 >
b1100 E
b1100 G
b0 :
b0 <
b0 =
b0 A
1(
#870
0(
#875
b1 9
b1 ?
b1 B
1(
#880
0(
#885
b10 9
b10 ?
b10 B
1(
#890
0(
#895
z!
zJ
b11 9
b11 ?
b11 B
1(
#900
0(
#905
b100 9
b100 ?
b100 B
1(
#910
0(
#915
b101 9
b101 ?
b101 B
1(
#920
0(
#925
b110 9
b110 ?
b110 B
1#
1(
#930
0(
#935
b111 9
b111 ?
b111 B
1(
#940
0(
#945
b1000 9
b1000 ?
b1000 B
1(
#950
0(
#955
b11 H
b1001 9
b1001 ?
b1001 B
1(
#960
0(
#965
b0 9
b0 ?
b0 B
0#
b11 "
b11 3
b11 >
b11 E
b11 G
1(
#970
0(
#975
b1 9
b1 ?
b1 B
1(
#980
0(
#985
b10 9
b10 ?
b10 B
1(
#990
0(
#995
1!
1J
b11 9
b11 ?
b11 B
1(
#1000
0(
#1005
b100 9
b100 ?
b100 B
1(
#1010
0(
#1015
b101 9
b101 ?
b101 B
1(
#1020
0(
#1025
b110 9
b110 ?
b110 B
1#
1(
#1030
0(
#1035
b111 9
b111 ?
b111 B
1(
#1040
0(
#1045
b1000 9
b1000 ?
b1000 B
1(
#1050
0(
#1055
18
b1001 9
b1001 ?
b1001 B
1(
#1060
0(
#1065
08
b0 9
b0 ?
b0 B
0#
b1 :
b1 <
b1 =
b1 A
1(
#1070
0(
#1075
b1 9
b1 ?
b1 B
1(
#1080
0(
#1085
b10 9
b10 ?
b10 B
1(
#1090
0(
#1095
0!
0J
b11 9
b11 ?
b11 B
1(
#1100
0(
#1105
b100 9
b100 ?
b100 B
1(
#1110
0(
#1115
b101 9
b101 ?
b101 B
1(
#1120
0(
#1125
b110 9
b110 ?
b110 B
1#
1(
#1130
0(
#1135
b111 9
b111 ?
b111 B
1(
#1140
0(
#1145
b1000 9
b1000 ?
b1000 B
1(
#1150
0(
#1155
18
b1001 9
b1001 ?
b1001 B
1(
#1160
0(
#1165
08
b0 9
b0 ?
b0 B
0#
b10 :
b10 <
b10 =
b10 A
1(
#1170
0(
#1175
b1 9
b1 ?
b1 B
1(
#1180
0(
#1185
b10 9
b10 ?
b10 B
1(
#1190
0(
#1195
1!
1J
b11 9
b11 ?
b11 B
1(
#1200
0(
#1205
b100 9
b100 ?
b100 B
1(
#1210
0(
#1215
b101 9
b101 ?
b101 B
1(
#1220
0(
#1225
b110 9
b110 ?
b110 B
1#
1(
#1230
0(
#1235
b111 9
b111 ?
b111 B
1(
#1240
0(
#1245
b1000 9
b1000 ?
b1000 B
1(
#1250
0(
#1255
18
b1001 9
b1001 ?
b1001 B
1(
#1260
0(
#1265
08
b0 9
b0 ?
b0 B
0#
b11 :
b11 <
b11 =
b11 A
1(
#1270
0(
#1275
b1 9
b1 ?
b1 B
1(
#1280
0(
#1285
b10 9
b10 ?
b10 B
1(
#1290
0(
#1295
0!
0J
b11 9
b11 ?
b11 B
1(
#1300
0(
#1305
b100 9
b100 ?
b100 B
1(
#1310
0(
#1315
b101 9
b101 ?
b101 B
1(
#1320
0(
#1325
b110 9
b110 ?
b110 B
1#
1(
#1330
0(
#1335
b111 9
b111 ?
b111 B
1(
#1340
0(
#1345
b1000 9
b1000 ?
b1000 B
1(
#1350
0(
#1355
18
b1001 9
b1001 ?
b1001 B
1(
#1360
0(
#1365
08
b0 9
b0 ?
b0 B
0#
b100 :
b100 <
b100 =
b100 A
1(
#1370
0(
#1375
b1 9
b1 ?
b1 B
1(
#1380
0(
#1385
b10 9
b10 ?
b10 B
1(
#1390
0(
#1395
1!
1J
b11 9
b11 ?
b11 B
1(
#1400
0(
#1405
b100 9
b100 ?
b100 B
1(
#1410
0(
#1415
b101 9
b101 ?
b101 B
1(
#1420
0(
#1425
b110 9
b110 ?
b110 B
1#
1(
#1430
0(
#1435
b111 9
b111 ?
b111 B
1(
#1440
0(
