slave_fsm_rtl/slave_sda_gen_5.v
module slave_sda_generate #(
    parameter ADDR_LEN = 7,
    parameter ADDR_COUNTER_LEN = 3,
    parameter DATA_LEN = 8,
    parameter DATA_COUNTER_LEN = 3
)(
    //input clk;
    input scl,
    inout sda,
    input[DATA_LEN-1:0] data_received,
    output[DATA_LEN-1:0] data_sent

);

  reg [3:0] current_state = Idle;
  reg [3:0] next_state = Idle;
  reg R_W;
  reg sda_reg = 1'b1;
  reg start_signal = 1'b0;
  reg stop_signal = 1'b0;
  reg sda_write = 1'b0;
  reg reset_address_counter;
  reg [ADDR_COUNTER_LEN:0] address_counter;
  wire comp_bit;
  reg reset_rdata_counter;
  reg [DATA_COUNTER_LEN-1:0] rdata_counter;
  reg reset_wdata_counter;
  reg [DATA_COUNTER_LEN-1:0] wdata_counter;
  reg [DATA_LEN-1:0] received_data = 8'b00000000;
  reg [ADDR_LEN-1:0] slave_address = 7'b1011011;
  reg [ADDR_LEN-1:0] received_address = 7'b0000000;

  parameter Idle = 4'b0000;
  parameter Receive_address = 4'b0001;
  parameter delay_post_ack0 = 4'b0010;
  parameter delay_post_ack1 = 4'b0011;
  parameter Send_data = 4'b0100;
  parameter Check_ACK_NACK = 4'b0101;
  parameter Receive_data = 4'b0110;
  parameter GiveACK = 4'b0111;
  parameter Stop = 4'b1000;
  //parameter GiveACK = ;

  assign comp_bit = (received_address == slave_address);
  assign data_sent = received_data;
  assign sda = sda_write ? sda_reg : 1'bz;

  always @(current_state,sda,sda_reg,scl) begin
    case (current_state)
      Receive_address:
      begin
        if(scl) begin
          //address_counter = address_counter - 1;
          sda_reg = sda;
          if(address_counter == 1) R_W = sda_reg;
          else received_address = (received_address << 1) + sda_reg;
        end
        else if(~scl && address_counter == 0) begin
          if (comp_bit) begin
            sda_write = 1'b1;
            sda_reg = 1'b0;
            next_state = delay_post_ack0;
          end
          else begin
            sda_write = 1'b1;
            sda_reg = 1'b1;
            next_state = delay_post_ack1;
          end
        end

        else next_state = Receive_address;
      end
      delay_post_ack0:
      begin
        if (R_W == 1'b1) begin
          sda_write = 1'b1;
          next_state = Send_data;
          if (~scl) begin
          sda_reg = data_received[DATA_LEN-1];
          end
        end
        else begin
          if (~scl) sda_write = 1'b0;
          next_state = Receive_data;
        end
        //break;
      end
      delay_post_ack1:
      begin
        if (~scl) sda_write = 1'b0;
        next_state = Stop;
        //break;
      end
      Send_data:
      begin
        //rdata_counter -= 1;
        if (~scl) begin
          sda_write = 1'b1;
          if (rdata_counter == 0) begin
            sda_write = 1'b0;
            next_state = Check_ACK_NACK;
          end
          else begin
            sda_reg = data_received[rdata_counter];
            next_state = Send_data;
          end
        end
        
        //break;
      end
      Check_ACK_NACK:
      begin
        sda_write = 1'b0;
        next_state = Stop;
        //break;
      end
      Receive_data:
      begin
        
        if (wdata_counter == 0) begin
          next_state = GiveACK;
          if (~scl) begin 
            sda_write = 1'b1;
            sda_reg = 1'b0;
          end
        end
        else begin
          if (scl) begin
            sda_reg = sda;
            received_data = (received_data << 1) + sda_reg;
          end
          next_state = Receive_data;
        end
        
        //break;
      end
      GiveACK:
      begin
        if (~scl) sda_write = 1'b0;
        next_state = Stop;
      end
      Stop: 
      begin
        sda_write = 1'b0;
        //break;
      end
    endcase
  end

  always @(posedge scl) begin
    case (current_state)
      Idle:
      begin
        stop_signal <= 1'b0;
      end
      Receive_address:
      begin
        start_signal <= 1'b0;
        address_counter <= address_counter - 1;

      end
      delay_post_ack0:
      begin
        if (R_W == 1'b1) begin
          reset_rdata_counter <= 1'b1;
        end
        else begin
          reset_wdata_counter <= 1'b1;
        end
        //break;
      end
      /*delay_post_ack1:
      begin
        //sda <= sda_reg;
        sda_reg = 1'b1;
        reset_address_counter = 1'b1;
        next_state = Receive_address;
        //break;
      end*/
      Send_data:
      begin
        rdata_counter <= rdata_counter - 1;
        //sda_reg <= data_received[rdata_counter-1];
      end
      Check_ACK_NACK:
      begin
        //
      end
      Receive_data:
      begin
        wdata_counter <= wdata_counter - 1;
        
        //break;
      end
      GiveACK:
      begin
        next_state = Stop;
      end
    endcase
  end

always @(start_signal) begin
  if(start_signal) begin
    next_state = Receive_address;
  end
end

always @(posedge scl) begin
  current_state <= next_state;
end

always @(negedge sda) begin
  if (scl) begin
    reset_address_counter <= 1'b1;
    start_signal <= 1'b1;
  end
  
end

always @(posedge sda) begin
  if (scl) stop_signal <= 1'b1;
end

always @(stop_signal) begin
  if (stop_signal) begin
    current_state <= Idle;
  end
end

always @(address_counter, reset_address_counter) begin
  if (reset_address_counter || address_counter < 0 || address_counter > ADDR_LEN) begin
    address_counter = ADDR_LEN;
    reset_address_counter = 0;
  end
end
always @(rdata_counter, reset_rdata_counter) begin
  if (reset_rdata_counter || rdata_counter < 0 || rdata_counter > DATA_LEN-1) begin
    rdata_counter = DATA_LEN-1;
    reset_rdata_counter = 0;
  end
end

always @(wdata_counter, reset_wdata_counter) begin
  if (reset_wdata_counter || wdata_counter < 0 || wdata_counter > DATA_LEN-1) begin
    wdata_counter = DATA_LEN-1;
    reset_wdata_counter = 0;
  end
end

endmodule

master_fsm_rtl/counter.v
module counter(
               input            clk,
               input            rst_n,
               input            rst_count_2,
               input            count_inc,
               output reg [3:0] count
);

always @(posedge clk or negedge rst_n) begin
    if(~rst_n) count <= 0;
    else 
    begin
        if(rst_count_2) count <= 0;
        else if(count_inc)
        begin
            count <= count + 1'b1;
        end
    end
end
endmodule

master_fsm_rtl/sda_gen.v
module sda_generate #(
    //parameter THRESHOLD         = 2,
    parameter ADDR_LEN          = 7,
    parameter DATA_LEN          = 8,
    parameter SETUP_SDA_START   = 2,
    parameter SETUP_SDA_STOP    = 2,
    parameter SETUP_SDA         = 3,
    parameter T_HIGH            = 4,
    parameter T_LOW             = 6
    )(
    input                       clk,
    input                       rst_n,
    input                       start,
    input                       scl,
    input [6:0]                 count_ctrl,
    input [3:0]                 count,
    input                       wait_for_sync,
    input                       add_sent,
    input                       data_received,
    input                       data_sent,
    input [ADDR_LEN-1:0]        add_reg,
    input                       R_W,
    input [DATA_LEN-1:0]        data_1,
    input [DATA_LEN-1:0]        data_2,
    input                       ack_3p,
    inout                       sda,
    output                      rst_count,
    output                      rst_count_2,
    output [3:0]                state_master,
    output [DATA_LEN-1:0]       dout_1,
    output [DATA_LEN-1:0]       dout_2,
    //output                      output_value_valid,
    output                      free
                                           );


    reg [3:0]           current_state;
    reg [3:0]           next_state;
    reg                 sda_reg;
    reg [1:0]           no_of_data_rec;
    reg [1:0]           no_of_data_sent; //See if one can be used
    reg [DATA_LEN-1:0]  data_mem [1:0];
    reg                 ack_reg;
    //wire                output_value_valid;

    parameter Idle            = 4'b0000;
    parameter Ready           = 4'b0001;
    parameter Send_Address    = 4'b0010;
    parameter Check_ACK_addr  = 4'b0011;
    parameter Write_Data      = 4'b0100;
    parameter Check_ACK_data  = 4'b0101;
    parameter Read_Data       = 4'b0110;
    parameter Send_ACK        = 4'b0111;
    parameter Stop            = 4'b1000;


//    assign sda = output_value_valid ? sda_reg : 1'bz;
    assign dout_1 = data_mem[0];
    assign dout_2 =data_mem[1];

assign (strong0, highz1) sda = sda_reg;

//always block for curr_state
    always @(posedge clk or negedge rst_n)
        begin
            if(~rst_n) begin
                current_state <= Idle;
            end else begin
                current_state <= next_state;
            end

        end
    //always block for sda_reg
    always @(posedge clk or negedge rst_n)
    begin
        if(~rst_n) begin
            sda_reg <= 1'b1;
        end
     else begin
        case (current_state) 

        Idle: begin
            sda_reg <= 1'b1;
        end

        Ready : begin
            if(count_ctrl == (SETUP_SDA_START -1)) begin
                sda_reg <= 1'b0;
            end
        end
        
        Send_Address : begin
            if(count <= ADDR_LEN -1) begin
                if(count_ctrl == T_LOW - SETUP_SDA - 1) sda_reg <= add_reg[(ADDR_LEN - 1) - count];
            end else begin
                if(count_ctrl == T_LOW - SETUP_SDA - 1) sda_reg <= R_W;
            end
        end

        Check_ACK_addr: begin
            if(count_ctrl == T_LOW -SETUP_SDA - 1) begin
                sda_reg <= 1'b1;
            end
        end

        Write_Data: begin
            if(count_ctrl == T_LOW -SETUP_SDA -1 && no_of_data_sent == 0) sda_reg <= data_1[DATA_LEN-1-count];
            else if(count_ctrl == T_LOW -SETUP_SDA -1 && no_of_data_sent == 1) sda_reg <= data_2[DATA_LEN-1-count];
        end

        Check_ACK_data: begin
            if(count_ctrl == T_LOW -SETUP_SDA - 1) begin
                sda_reg <= 1'b1;
            end
        end

        Read_Data: begin
            if(count_ctrl == T_LOW -SETUP_SDA -1) begin
                data_mem[no_of_data_sent][DATA_LEN-1-count] <= sda;
                sda_reg <= 1'b1;
            end
        end

        Send_ACK: begin
            if(count_ctrl == T_LOW -SETUP_SDA - 1) sda_reg <= ~ack_3p;
        end

        Stop: begin
            if (count_ctrl == T_HIGH+T_LOW -1 ) begin
                sda_reg <= 1'b1;
            end else if(count_ctrl >= T_LOW + SETUP_SDA_STOP -1) begin
                sda_reg <= 1; 
            end else begin
                sda_reg <= 0;
            end
        end
    
        
     endcase 

     end
    end

//always block for ack_reg
always @(posedge clk or negedge rst_n) begin
    if(~rst_n) begin
        ack_reg <= 0;
    end else begin
        if(add_sent || data_sent) begin
            ack_reg <= 0;
        end else if((state_master == Check_ACK_addr || state_master == Check_ACK_data) && scl && sda) begin
            ack_reg <= 1;
        end
    end 
end

//always block for no_of_data_sent
always @(posedge clk or negedge rst_n) begin
    if(~rst_n) begin
        no_of_data_sent <= 0;
    end else begin
        if(data_sent || data_received) no_of_data_sent <= no_of_data_sent + 1'b1;
        if(current_state == Idle) begin
            no_of_data_sent <= 0;
        end
    end
end

//Combo Logic for next_state
always @(*) begin
    next_state = current_state;

    case(current_state)
        Idle : begin
            if(start) begin
                next_state = Ready;
            end
        end

        Ready: begin
           if(wait_for_sync) begin
                next_state = Send_Address;
           end
        end

        Send_Address: begin
            if(add_sent) next_state = Check_ACK_addr;
        end

        Check_ACK_addr: begin
            if(~ack_reg && (count_ctrl==T_LOW+T_HIGH-1)) begin
                if(R_W) begin
                    next_state = Read_Data;
                end else begin
                    next_state = Write_Data;
                end
            end
            else if(ack_reg && (count_ctrl==T_LOW+T_HIGH-1)) begin
                next_state = Stop;
            end
        end

        Write_Data : begin
            if(data_sent) next_state = Check_ACK_data;
        end

        Check_ACK_data: begin
            if(no_of_data_sent == 1 && ~ack_reg && (count_ctrl==T_LOW+T_HIGH-1)) next_state = Write_Data;
            else if(no_of_data_sent == 1 && ack_reg && (count_ctrl==T_LOW+T_HIGH-1)) next_state = Stop;
            else if (no_of_data_sent == 2 && (count_ctrl == T_LOW + T_HIGH - 1)) next_state = Stop;
        end

        Read_Data: begin
            if(data_received) next_state = Send_ACK;
        end

        Send_ACK: begin
            if(no_of_data_sent < 2 && ack_3p && (count_ctrl==T_LOW+T_HIGH-1)) next_state = Read_Data;
            else if(no_of_data_sent < 2 && ~ack_3p && (count_ctrl==T_LOW+T_HIGH-1)) next_state = Stop;
            else if(no_of_data_sent == 2 && (count_ctrl==T_LOW+T_HIGH-1)) next_state = Stop;
        end

        Stop: begin
            if((count_ctrl==T_LOW+T_HIGH-1)) next_state = Idle;
        end
       
    endcase

end

    
    assign state_master = current_state;
    assign free = (current_state == Idle);
    assign rst_count = (current_state == Idle) || wait_for_sync || free || add_sent || data_sent || data_received ;
    assign rst_count_2 = wait_for_sync || add_sent || data_sent || data_received;
    //assign output_value_valid = !((current_state == Read_Data )||(current_state == Idle) || ((current_state == Check_ACK_data || current_state == Check_ACK_addr) && count_ctrl >= (T_LOW - SETUP_SDA-1)));
    //assign sda = sda_reg;

endmodule

master_fsm_rtl/scl_gen.v
module scl_generate #(
    //parameter THRESHOLD     = 2,
    parameter T_LOW         = 6,
    parameter T_HIGH        = 4,  //SCL is LOW for T_LOW*CLK_PERIOD and HIGH for T_HIGH*CLK_PERIOD
    parameter ADDR_LEN      = 7,
    parameter SETUP_SCL_START = 4,
    parameter DATA_LEN      = 8
)(
    input              clk,
    input              rst_n,
    input [3:0]        state_master,
    input              rst_count,
    input [3:0]        count,
    output reg [6:0]   count_ctrl,
    output reg         scl,
    output             wait_for_sync,
    output             add_sent,
    output             data_received,
    output             data_sent,
    output             count_inc
);


    parameter Idle            = 4'b0000;
    parameter Ready           = 4'b0001;
    parameter Send_Address    = 4'b0010;
    parameter Check_ACK_addr  = 4'b0011;
    parameter Write_Data      = 4'b0100;
    parameter Check_ACK_data  = 4'b0101;
    parameter Read_Data       = 4'b0110;
    parameter Send_ACK        = 4'b0111;
    parameter Stop            = 4'b1000;

//always block for count_ctrl
always @(posedge clk or negedge rst_n) begin
    if(~rst_n) begin
        count_ctrl <= 0;
    end else begin
        if (rst_count) begin
            count_ctrl <= 0;
        end else begin
            if (state_master == Ready) begin
                if(count_ctrl == (SETUP_SCL_START-1)) begin
                    count_ctrl <= 0;
                end else begin
                    count_ctrl <= count_ctrl + 1;
                end
            end else if(state_master != Ready && state_master != Stop && state_master!=Idle) begin
                if (count_ctrl == (T_LOW+T_HIGH-1)) begin
                    count_ctrl <= 0;
                end else begin
                    count_ctrl <= count_ctrl + 1; 
                end
            end else begin //what happens to cnt cntrl in other states?
                count_ctrl <= count_ctrl + 1;
            end
        end
    end
end

//always block for scl
always @(posedge clk or negedge rst_n) begin
    if (~rst_n) begin
        scl <= 1'b1; //check
    end else begin
        if (state_master == Ready) begin
            if (count_ctrl == SETUP_SCL_START-1) begin
                scl <= 1'b0;
            end
        end else if(state_master != Ready && state_master != Idle && state_master != Stop) begin
            if(count_ctrl < T_LOW -1 || count_ctrl == (T_HIGH + T_LOW -1) ) begin
                scl <= 1'b0;
            end else begin
                scl <= 1'b1;
            end
        end
        else if(state_master == Idle) begin
            scl <= 1'b1;
        end
        else if(state_master == Stop) begin
            if(count_ctrl < T_LOW -1) begin
                scl <= 1'b0;
            end else if (count_ctrl == T_HIGH+T_LOW -1 ) begin
                scl <= 1'b1;
            end
            else  begin
                scl <= 1'b1;
            end
        end
    end
end

    assign wait_for_sync = (count_ctrl == (SETUP_SCL_START-1)) && (state_master == Ready);
    assign add_sent      = (count      == ADDR_LEN) && (count_ctrl == T_HIGH + T_LOW -1 ) && (state_master == Send_Address);
    assign data_received = (count      == DATA_LEN-1) && (count_ctrl == T_HIGH + T_LOW - 1) && (state_master == Read_Data);
    assign data_sent     = (count      == DATA_LEN-1) && (count_ctrl == T_HIGH + T_LOW - 1) && (state_master == Write_Data);
    assign count_inc     = (count_ctrl == T_HIGH + T_LOW - 1) && (state_master == Send_Address || state_master == Write_Data|| state_master == Read_Data);

endmodule

master_fsm_rtl/fsm_master.v
// Master Controller
module fsm_master #(
    //parameter FREQ_DIFF = 4,
    parameter T_LOW     = 6,
    parameter T_HIGH    = 4,
    parameter ADDR_LEN  = 7,
    parameter SETUP_SCL_START = 4,
    parameter SETUP_SDA_START = 2,
    parameter SETUP_SDA = 3,
    parameter SETUP_SDA_STOP = 2,
    parameter DATA_LEN  = 8
                            )
    (
        input                   clk,
        input                   rst_n,
        input                   start,
        input [ADDR_LEN-1:0]    add_reg,
        input                   R_W,
        input [DATA_LEN-1:0]    data_1,
        input [DATA_LEN-1:0]    data_2,
        input                   ack_3p,
        output                  scl,
        inout                   sda,
        output [3:0]            state_master,
        output                  free
    );


    //wire [3:0] state_master;
    wire [6:0] count_ctrl;
    wire [3:0] count;
    wire       count_inc;
    wire       rst_count_2;
    wire       rst_count;
    wire       wait_for_sync;
    wire       add_sent;
    wire       data_received;
    wire       data_sent;

    scl_generate #(
        //.THRESHOLD          (FREQ_DIFF/2    ),
        .T_LOW              (T_LOW          ),
        .T_HIGH             (T_HIGH         ),
        .ADDR_LEN           (ADDR_LEN       ),
        .SETUP_SCL_START    (SETUP_SCL_START),
        .DATA_LEN           (DATA_LEN       )
        ) 
        SCL
        (
            .clk                (clk            ),
            .rst_n              (rst_n          ),
            .state_master       (state_master   ),
            .rst_count          (rst_count      ),
            .count              (count          ),
            .count_ctrl         (count_ctrl     ),
            .scl                (scl            ),
            .wait_for_sync      (wait_for_sync  ),
            .add_sent           (add_sent       ),
            .data_received      (data_received  ),
            .data_sent          (data_sent      ),
            .count_inc          (count_inc      )
        );
    
    sda_generate #(
        //.THRESHOLD          (FREQ_DIFF/2    ),
        .ADDR_LEN           (ADDR_LEN       ),
        .SETUP_SDA_START    (SETUP_SDA_START),
        .SETUP_SDA_STOP     (SETUP_SDA_STOP ),
        .SETUP_SDA          (SETUP_SDA      ),
        .DATA_LEN           (DATA_LEN       ),
        .T_LOW              (T_LOW          ),
        .T_HIGH             (T_HIGH         )
        ) SDA(
            .clk                (clk            ),
            .rst_n              (rst_n          ),
            .start              (start          ),
            .scl                (scl            ),
            .count_ctrl         (count_ctrl     ),
            .count              (count          ),
            .wait_for_sync      (wait_for_sync  ),
            .add_sent           (add_sent       ),
            .data_received      (data_received  ),
            .data_sent          (data_sent      ),
            .add_reg            (add_reg        ),
            .R_W                (R_W            ),
            .data_1             (data_1         ),
            .data_2             (data_2         ),
            .ack_3p             (ack_3p         ),
            .sda                (sda            ),
            .rst_count          (rst_count      ),
            .rst_count_2        (rst_count_2    ),
            .state_master       (state_master   ),
            .free               (free           )
        );

    counter COUNTER(
            .clk                (clk            ),
            .rst_n              (rst_n          ),
            .rst_count_2        (rst_count_2    ),
            .count_inc          (count_inc      ),
            .count              (count          )
    );

endmodule

master_fsm_rtl/master_slave_tb.v
module master_slave_tb;

parameter ADDR_LEN = 7;
parameter DATA_LEN = 8;
parameter SETUP_SDA_START=2;
parameter SETUP_SCL_START=4;
parameter SETUP_SDA_STOP = 2;
parameter T_LOW         = 6;
parameter T_HIGH        = 4;
parameter SETUP_SDA     = 3;

parameter ADDR_COUNTER_LEN =3;
parameter DATA_COUNTER_LEN = 3;

reg clk;
reg rst_n;
reg start;
reg [ADDR_LEN-1:0] add_reg;
reg R_W;
reg [DATA_LEN-1:0] data_1;
reg [DATA_LEN-1:0] data_2;
reg                ack_3p;
reg sda_reg;
wire scl;
tri1 sda; // pull-up resistor
wire[3:0] state_master;
wire free;

reg [DATA_LEN-1:0] data_received;
wire [DATA_LEN-1:0] data_sent;

fsm_master #(
    .T_LOW                  (T_LOW          ),
    .T_HIGH                 (T_HIGH         ),
    .ADDR_LEN               (ADDR_LEN       ),
    .SETUP_SCL_START        (SETUP_SCL_START),
    .SETUP_SDA_START        (SETUP_SDA_START),
    .SETUP_SDA              (SETUP_SDA      ),
    .SETUP_SDA_STOP         (SETUP_SDA_STOP ),
    .DATA_LEN               (DATA_LEN       )
) FSM_MASTER_DUT
(
    .clk                (clk        ),
    .rst_n              (rst_n      ),
    .start              (start      ),
    .add_reg            (add_reg    ),
    .R_W                (R_W        ),
    .data_1             (data_1     ),
    .data_2             (data_2     ),
    .ack_3p             (ack_3p     ),
    .scl                (scl        ),
    .sda                (sda        ),
    .state_master       (state_master),
    //.output_value_valid (output_value_valid),
    .free               (free       )
);

slave_sda_generate #(
    .ADDR_LEN           (ADDR_LEN          ),
    .DATA_LEN           (DATA_LEN          ),
    .ADDR_COUNTER_LEN   (ADDR_COUNTER_LEN  ),
    .DATA_COUNTER_LEN   (DATA_COUNTER_LEN   )

) SLAVE_DUT (
    .sda            (sda        ),
    .scl            (scl        ),
    .data_received  (data_received),
    .data_sent      (data_sent  )
);

localparam CLK_PERIOD = 10;
always #(CLK_PERIOD/2) clk=~clk;

initial begin
    clk = 0;
    #5000 $finish;
end

initial begin
    $dumpfile("tb_.vcd");
    $dumpvars(0, master_slave_tb);
end

initial begin
    #CLK_PERIOD rst_n=1'b0; start = 1'b0; add_reg = 7'b1011011; R_W = 0;ack_3p=1; data_1 = 8'b10101100; data_2 = 8'b01000010; sda_reg = 0; data_received = 8'b00011101;
    #CLK_PERIOD rst_n=1'b1;  start = 1'b1; R_W = 1'b0; ack_3p = 1'b1;
    #CLK_PERIOD start=1'b0;
end

endmodule

master_fsm_rtl/tb_.vcd
$date
	Tue Feb 06 18:23:49 2024
$end
$version
	Icarus Verilog
$end
$timescale
	1s
$end
$scope module master_slave_tb $end
$var wire 1 ! sda $end
$var wire 4 " state_master [3:0] $end
$var wire 1 # scl $end
$var wire 1 $ free $end
$var wire 8 % data_sent [7:0] $end
$var reg 1 & R_W $end
$var reg 1 ' ack_3p $end
$var reg 7 ( add_reg [6:0] $end
$var reg 1 ) clk $end
$var reg 8 * data_1 [7:0] $end
$var reg 8 + data_2 [7:0] $end
$var reg 8 , data_received [7:0] $end
$var reg 1 - rst_n $end
$var reg 1 . sda_reg $end
$var reg 1 / start $end
$scope module FSM_MASTER_DUT $end
$var wire 1 & R_W $end
$var wire 1 ' ack_3p $end
$var wire 7 0 add_reg [6:0] $end
$var wire 1 ) clk $end
$var wire 8 1 data_1 [7:0] $end
$var wire 8 2 data_2 [7:0] $end
$var wire 1 - rst_n $end
$var wire 1 ! sda $end
$var wire 1 / start $end
$var wire 1 3 wait_for_sync $end
$var wire 4 4 state_master [3:0] $end
$var wire 1 # scl $end
$var wire 1 5 rst_count_2 $end
$var wire 1 6 rst_count $end
$var wire 1 $ free $end
$var wire 1 7 data_sent $end
$var wire 1 8 data_received $end
$var wire 1 9 count_inc $end
$var wire 7 : count_ctrl [6:0] $end
$var wire 4 ; count [3:0] $end
$var wire 1 < add_sent $end
$scope module COUNTER $end
$var wire 1 ) clk $end
$var wire 1 - rst_n $end
$var wire 1 5 rst_count_2 $end
$var wire 1 9 count_inc $end
$var reg 4 = count [3:0] $end
$upscope $end
$scope module SCL $end
$var wire 1 < add_sent $end
$var wire 1 ) clk $end
$var wire 4 > count [3:0] $end
$var wire 1 9 count_inc $end
$var wire 1 8 data_received $end
$var wire 1 7 data_sent $end
$var wire 1 - rst_n $end
$var wire 1 3 wait_for_sync $end
$var wire 4 ? state_master [3:0] $end
$var wire 1 6 rst_count $end
$var reg 7 @ count_ctrl [6:0] $end
$var reg 1 # scl $end
$upscope $end
$scope module SDA $end
$var wire 1 & R_W $end
$var wire 1 ' ack_3p $end
$var wire 7 A add_reg [6:0] $end
$var wire 1 < add_sent $end
$var wire 1 ) clk $end
$var wire 4 B count [3:0] $end
$var wire 7 C count_ctrl [6:0] $end
$var wire 8 D data_1 [7:0] $end
$var wire 8 E data_2 [7:0] $end
$var wire 1 8 data_received $end
$var wire 1 7 data_sent $end
$var wire 8 F dout_1 [7:0] $end
$var wire 8 G dout_2 [7:0] $end
$var wire 1 6 rst_count $end
$var wire 1 5 rst_count_2 $end
$var wire 1 - rst_n $end
$var wire 1 # scl $end
$var wire 1 ! sda $end
$var wire 1 / start $end
$var wire 4 H state_master [3:0] $end
$var wire 1 3 wait_for_sync $end
$var wire 1 $ free $end
$var reg 1 I ack_reg $end
$var reg 4 J current_state [3:0] $end
$var reg 4 K next_state [3:0] $end
$var reg 2 L no_of_data_sent [1:0] $end
$var reg 1 M sda_reg $end
$upscope $end
$upscope $end
$scope module SLAVE_DUT $end
$var wire 8 N data_received [7:0] $end
$var wire 8 O data_sent [7:0] $end
$var wire 1 # scl $end
$var wire 1 ! sda $end
$var wire 1 P comp_bit $end
$var reg 1 Q R_W $end
$var reg 4 R address_counter [3:0] $end
$var reg 4 S current_state [3:0] $end
$var reg 4 T next_state [3:0] $end
$var reg 3 U rdata_counter [2:0] $end
$var reg 7 V received_address [6:0] $end
$var reg 8 W received_data [7:0] $end
$var reg 1 X reset_address_counter $end
$var reg 1 Y reset_rdata_counter $end
$var reg 1 Z reset_wdata_counter $end
$var reg 1 [ sda_reg $end
$var reg 1 \ sda_write $end
$var reg 7 ] slave_address [6:0] $end
$var reg 1 ^ start_signal $end
$var reg 1 _ stop_signal $end
$var reg 3 ` wdata_counter [2:0] $end
$upscope $end
$upscope $end
$enddefinitions $end
#0
$dumpvars
bx `
0_
0^
b1011011 ]
0\
1[
xZ
xY
xX
b0 W
b0 V
bx U
b0 T
b0 S
bx R
xQ
0P
b0 O
bx N
xM
bx L
bx K
bx J
xI
bx H
bx G
bx F
bx E
bx D
bx C
bx B
bx A
bx @
bx ?
bx >
bx =
x<
bx ;
bx :
x9
x8
x7
x6
x5
bx 4
x3
bx 2
bx 1
bx 0
x/
x.
x-
bx ,
bx +
bx *
0)
bx (
x'
x&
b0 %
x$
x#
bx "
x!
$end
#5
1)
#10
1_
16
05
07
08
0<
03
09
b0 K
b0 ;
b0 =
b0 >
b0 B
b0 L
0I
1!
1M
1$
b0 "
b0 4
b0 ?
b0 H
b0 J
1#
b0 :
b0 @
b0 C
0)
b11101 ,
b11101 N
0.
b1000010 +
b1000010 2
b1000010 E
b10101100 *
b10101100 1
b10101100 D
1'
0&
b1011011 (
b1011011 0
b1011011 A
0/
0-
#15
1)
#20
b1 K
0)
1/
1-
#25
06
0$
b1 "
b1 4
b1 ?
b1 H
b1 J
1)
#30
0)
0/
#35
b1 :
b1 @
b1 C
1)
#40
0)
#45
b1 T
b111 R
1^
0X
0!
0M
b10 :
b10 @
b10 C
1)
#50
0)
#55
16
15
b10 K
13
b11 :
b11 @
b11 C
1)
#60
0)
#65
06
05
03
b10 "
b10 4
b10 ?
b10 H
b10 J
0#
b0 :
b0 @
b0 C
1)
#70
0)
#75
b1 :
b1 @
b1 C
1)
#80
0)
#85
b10 :
b10 @
b10 C
1)
#90
0)
#95
b11 :
b11 @
b11 C
1!
1M
1)
#100
0)
#105
b100 :
b100 @
b100 C
1)
#110
0)
#115
b101 :
b101 @
b101 C
1)
#120
0)
#125
b1 V
b1 S
0_
1#
b110 :
b110 @
b110 C
1)
#130
0)
#135
b111 :
b111 @
b111 C
1)
#140
0)
#145
b1000 :
b1000 @
b1000 C
1)
#150
0)
#155
19
b1001 :
b1001 @
b1001 C
1)
#160
0)
#165
09
b1 ;
b1 =
b1 >
b1 B
0#
b0 :
b0 @
b0 C
1)
#170
0)
#175
b1 :
b1 @
b1 C
1)
#180
0)
#185
b10 :
b10 @
b10 C
1)
#190
0)
#195
b11 :
b11 @
b11 C
0!
0M
1)
#200
0)
#205
b100 :
b100 @
b100 C
1)
#210
0)
#215
b101 :
b101 @
b101 C
1)
#220
0)
#225
b110 R
0^
b10 V
0[
1#
b110 :
b110 @
b110 C
1)
#230
0)
#235
b111 :
b111 @
b111 C
1)
#240
0)
#245
b1000 :
b1000 @
b1000 C
1)
#250
0)
#255
19
b1001 :
b1001 @
b1001 C
1)
#260
0)
#265
09
b10 ;
b10 =
b10 >
b10 B
0#
b0 :
b0 @
b0 C
1)
#270
0)
#275
b1 :
b1 @
b1 C
1)
#280
0)
#285
b10 :
b10 @
b10 C
1)
#290
0)
#295
b11 :
b11 @
b11 C
1!
1M
1)
#300
0)
#305
b100 :
b100 @
b100 C
1)
#310
0)
#315
b101 :
b101 @
b101 C
1)
#320
0)
#325
b101 R
b101 V
1[
1#
b110 :
b110 @
b110 C
1)
#330
0)
#335
b111 :
b111 @
b111 C
1)
#340
0)
#345
b1000 :
b1000 @
b1000 C
1)
#350
0)
#355
19
b1001 :
b1001 @
b1001 C
1)
#360
0)
#365
09
b11 ;
b11 =
b11 >
b11 B
0#
b0 :
b0 @
b0 C
1)
#370
0)
#375
b1 :
b1 @
b1 C
1)
#380
0)
#385
b10 :
b10 @
b10 C
1)
#390
0)
#395
b11 :
b11 @
b11 C
1)
#400
0)
#405
b100 :
b100 @
b100 C
1)
#410
0)
#415
b101 :
b101 @
b101 C
1)
#420
0)
#425
b100 R
b1011 V
1#
b110 :
b110 @
b110 C
1)
#430
0)
#435
b111 :
b111 @
b111 C
1)
#440
0)
#445
b1000 :
b1000 @
b1000 C
1)
#450
0)
#455
19
b1001 :
b1001 @
b1001 C
1)
#460
0)
#465
09
b100 ;
b100 =
b100 >
b100 B
0#
b0 :
b0 @
b0 C
1)
#470
0)
#475
b1 :
b1 @
b1 C
1)
#480
0)
#485
b10 :
b10 @
b10 C
1)
#490
0)
#495
b11 :
b11 @
b11 C
0!
0M
1)
#500
0)
#505
b100 :
b100 @
b100 C
1)
#510
0)
#515
b101 :
b101 @
b101 C
1)
#520
0)
#525
b11 R
b10110 V
0[
1#
b110 :
b110 @
b110 C
1)
#530
0)
#535
b111 :
b111 @
b111 C
1)
#540
0)
#545
b1000 :
b1000 @
b1000 C
1)
#550
0)
#555
19
b1001 :
b1001 @
b1001 C
1)
#560
0)
#565
09
b101 ;
b101 =
b101 >
b101 B
0#
b0 :
b0 @
b0 C
1)
#570
0)
#575
b1 :
b1 @
b1 C
1)
#580
0)
#585
b10 :
b10 @
b10 C
1)
#590
0)
#595
b11 :
b11 @
b11 C
1!
1M
1)
#600
0)
#605
b100 :
b100 @
b100 C
1)
#610
0)
#615
b101 :
b101 @
b101 C
1)
#620
0)
#625
b10 R
b101101 V
1[
1#
b110 :
b110 @
b110 C
1)
#630
0)
#635
b111 :
b111 @
b111 C
1)
#640
0)
#645
b1000 :
b1000 @
b1000 C
1)
#650
0)
#655
19
b1001 :
b1001 @
b1001 C
1)
#660
0)
#665
09
b110 ;
b110 =
b110 >
b110 B
0#
b0 :
b0 @
b0 C
1)
#670
0)
#675
b1 :
b1 @
b1 C
1)
#680
0)
#685
b10 :
b10 @
b10 C
1)
#690
0)
#695
b11 :
b11 @
b11 C
1)
#700
0)
#705
b100 :
b100 @
b100 C
1)
#710
0)
#715
b101 :
b101 @
b101 C
1)
#720
0)
#725
b1 R
1P
b1011011 V
1#
b110 :
b110 @
b110 C
1)
#730
0)
#735
b111 :
b111 @
b111 C
1)
#740
0)
#745
b1000 :
b1000 @
b1000 C
1)
#750
0)
#755
19
b1001 :
b1001 @
b1001 C
1)
#760
0)
#765
09
b111 ;
b111 =
b111 >
b111 B
0#
b0 :
b0 @
b0 C
1)
#770
0)
#775
b1 :
b1 @
b1 C
1)
#780
0)
